Workbook
Name Fenestration: Lists!$A$5:$A$11
Name Res: Lists!$A$1:$A$2
Name SURFACE2: 'Raw Data'!$Q$3:$Q$24
Name re: Lists!$R$65
Name BSA: 'Lighting Zones'!$D$2:$D$6
Name Doors: Lists!$A$49:$A$50
Name Path: '4. Compliance'!$B$4
Name rf: Lists!$R$66
Name Roof_Type: Lists!$A$31:$A$33
Name Res: Lists!$A$1:$A$2
Name cfm: 'HVAC Air-side'!$C$18
Name Ltg_Space: 'Lighting Lookup'!$E$2:$E$108
Name bhp: 'HVAC Air-side'!$C$26
Name Yes_No: Lists!$N$1:$N$2
Name YESNO: 'Lighting Zones'!$B$11:$B$12
Name SxSCategories: 'Lighting Lookup'!$E$2:$E$112
Name Modeled_Square_Feet: '1,2,3 Information'!$C$32
Name Slab: Lists!$A$46:$A$47
Name rd: Lists!$R$64
Name Ltg_ctrl: 'Lighting Lookup'!$I$2:$I$6
Name Type: Lists!$A$1:$A$2
Name BAMCategories: 'Lighting Lookup'!$A$2:$A$33
Name fan_eff: 'HVAC Air-side'!$C$27
Name Floor: Lists!$A$42:$A$44
Name Ltg_Bldg: 'Lighting Lookup'!$A$2:$A$33
Name rb: Lists!$R$62
Name Res: Lists!$A$1:$A$2
Name LZ: 'Lighting Zones'!$B$2:$B$6
Name LZDEC: 'Lighting Zones'!$C$2:$C$6
Name LZONE: 'Lighting Zones'!$A$2:$A$6
Name Wall_Type: Lists!$A$35:$A$38
Name ra: Lists!$R$61
Name rca: Lists!$R$63
Name Env_Type: Lists!$A$1:$A$3
Name Res: Lists!$A$1:$A$2
Name HVAC: Lists!$A$54:$A$77

Sheet Color legend
A4: WORKBOOK COLOR LEGEND
A5: Do not edit: information
A6: Do not edit: formulas
A7: Do not edit: error
A8: User edit: required information
A9: User edit: drop-down menu
A10: User edit: drop-down menu (only for use with Appendix G)
A11: User edit: formula + drop-down menu
A12: User edit: fill in box

Sheet Schedules - Assembly
A1: Hour of Day (Time) | B1: Schedule for Occupancy | E1: Schedule for Lighting/Receptacle | H1: Schedule for HVAC System | K1: Schedule for Service Hot Water | N1: Schedule for Elevator
B2: Percent of Maximum Load | E2: Percent of Maximum Load | K2: Percent of Maximum Load | N2: Percent of Maximum Load
B3: Wk | C3: Sat | D3: Sun | E3: Wk | F3: Sat | G3: Sun | H3: Wk | I3: Sat | J3: Sun | K3: Wk | L3: Sat | M3: Sun | N3: Wk | O3: Sat | P3: Sun
A4: 1 (12-1am) | B4: 0 | C4: 0 | D4: 0 | E4: 5 | F4: 5 | G4: 5 | H4: Off | I4: Off | J4: Off | K4: 0 | L4: 0 | M4: 0 | N4: 0 | O4: 0 | P4: 0
A5: 2 (1-2am) | B5: 0 | C5: 0 | D5: 0 | E5: 5 | F5: 5 | G5: 5 | H5: Off | I5: Off | J5: Off | K5: 0 | L5: 0 | M5: 0 | N5: 0 | O5: 0 | P5: 0
A6: 3 (2-3am) | B6: 0 | C6: 0 | D6: 0 | E6: 5 | F6: 5 | G6: 5 | H6: Off | I6: Off | J6: Off | K6: 0 | L6: 0 | M6: 0 | N6: 0 | O6: 0 | P6: 0
A7: 4 (3-4am) | B7: 0 | C7: 0 | D7: 0 | E7: 5 | F7: 5 | G7: 5 | H7: Off | I7: Off | J7: Off | K7: 0 | L7: 0 | M7: 0 | N7: 0 | O7: 0 | P7: 0
A8: 5 (4-5am) | B8: 0 | C8: 0 | D8: 0 | E8: 5 | F8: 5 | G8: 5 | H8: Off | I8: Off | J8: Off | K8: 0 | L8: 0 | M8: 0 | N8: 0 | O8: 0 | P8: 0
A9: 6 (5-6am) | B9: 0 | C9: 0 | D9: 0 | E9: 5 | F9: 5 | G9: 5 | H9: On | I9: Off | J9: Off | K9: 0 | L9: 0 | M9: 0 | N9: 0 | O9: 0 | P9: 0
A10: 7 (6-7am) | B10: 0 | C10: 0 | D10: 0 | E10: 35/40 | F10: 5 | G10: 5 | H10: On | I10: On | J10: On | K10: 0 | L10: 0 | M10: 0 | N10: 0 | O10: 0 | P10: 0
A11: 8 (7-8am) | B11: 0 | C11: 0 | D11: 0 | E11: 35/40 | F11: 30 | G11: 30 | H11: On | I11: On | J11: On | K11: 0 | L11: 0 | M11: 0 | N11: 0 | O11: 0 | P11: 0
A12: 9 (8-9am) | B12: 20 | C12: 20 | D12: 10 | E12: 35/40 | F12: 30 | G12: 30 | H12: On | I12: On | J12: On | K12: 0 | L12: 0 | M12: 0 | N12: 0 | O12: 0 | P12: 0
A13: 10 (9-10am) | B13: 20 | C13: 20 | D13: 10 | E13: 65/75 | F13: 40/50 | G13: 30 | H13: On | I13: On | J13: On | K13: 5 | L13: 5 | M13: 5 | N13: 0 | O13: 0 | P13: 0
A14: 11 (10-11am) | B14: 20 | C14: 20 | D14: 10 | E14: 65/75 | F14: 40/50 | G14: 30 | H14: On | I14: On | J14: On | K14: 5 | L14: 5 | M14: 5 | N14: 0 | O14: 0 | P14: 0
A15: 12 (11-12pm) | B15: 80 | C15: 60 | D15: 10 | E15: 65/75 | F15: 40/50 | G15: 30 | H15: On | I15: On | J15: On | K15: 35 | L15: 20 | M15: 10 | N15: 0 | O15: 0 | P15: 0
A16: 13 (12-1pm) | B16: 80 | C16: 60 | D16: 10 | E16: 65/75 | F16: 40/50 | G16: 55/65 | H16: On | I16: On | J16: On | K16: 5 | L16: 0 | M16: 0 | N16: 0 | O16: 0 | P16: 0
A17: 14 (1-2pm) | B17: 80 | C17: 60 | D17: 70 | E17: 65/75 | F17: 40/50 | G17: 55/65 | H17: On | I17: On | J17: On | K17: 5 | L17: 0 | M17: 0 | N17: 0 | O17: 0 | P17: 0
A18: 15 (2-3pm) | B18: 80 | C18: 60 | D18: 70 | E18: 65/75 | F18: 40/50 | G18: 55/65 | H18: On | I18: On | J18: On | K18: 5 | L18: 0 | M18: 0 | N18: 0 | O18: 0 | P18: 0
A19: 16 (3-4pm) | B19: 80 | C19: 60 | D19: 70 | E19: 65/75 | F19: 40/50 | G19: 55/65 | H19: On | I19: On | J19: On | K19: 5 | L19: 0 | M19: 0 | N19: 0 | O19: 0 | P19: 0
A20: 17 (4-5pm) | B20: 80 | C20: 60 | D20: 70 | E20: 65/75 | F20: 40/50 | G20: 55/65 | H20: On | I20: On | J20: On | K20: 5 | L20: 0 | M20: 0 | N20: 0 | O20: 0 | P20: 0
A21: 18 (5-6pm) | B21: 80 | C21: 60 | D21: 70 | E21: 65/75 | F21: 40/50 | G21: 55/65 | H21: On | I21: On | J21: On | K21: 0 | L21: 0 | M21: 0 | N21: 0 | O21: 0 | P21: 0
A22: 19 (6-7pm) | B22: 20 | C22: 60 | D22: 70 | E22: 65/75 | F22: 40/50 | G22: 55/65 | H22: On | I22: On | J22: On | K22: 0 | L22: 0 | M22: 0 | N22: 0 | O22: 0 | P22: 0
A23: 20 (7-8pm) | B23: 20 | C23: 60 | D23: 70 | E23: 65/75 | F23: 40/50 | G23: 55/65 | H23: On | I23: On | J23: On | K23: 0 | L23: 65 | M23: 65 | N23: 0 | O23: 0 | P23: 0
A24: 21 (8-9pm) | B24: 20 | C24: 60 | D24: 70 | E24: 65/75 | F24: 40/50 | G24: 55/65 | H24: On | I24: On | J24: On | K24: 0 | L24: 30 | M24: 30 | N24: 0 | O24: 0 | P24: 0
A25: 22 (9-10pm) | B25: 20 | C25: 80 | D25: 70 | E25: 65/75 | F25: 40/50 | G25: 55/65 | H25: On | I25: On | J25: On | K25: 0 | L25: 0 | M25: 0 | N25: 0 | O25: 0 | P25: 0
A26: 23 (10-11pm) | B26: 10 | C26: 10 | D26: 20 | E26: 25 | F26: 40/50 | G26: 55/65 | H26: On | I26: On | J26: On | K26: 0 | L26: 0 | M26: 0 | N26: 0 | O26: 0 | P26: 0
A27: 24 (11-12am) | B27: 0 | C27: 0 | D27: 0 | E27: 5 | F27: 5 | G27: 5 | H27: Off | I27: Off | J27: Off | K27: 0 | L27: 0 | M27: 0 | N27: 0 | O27: 0 | P27: 0
A28: Total/Day | B28: =SUM(B4:B27) -> 710 | C28: =SUM(C4:C27) -> 750 | D28: =SUM(D4:D27) -> 700 | E28: 1010/1155 | F28: 660/800 | G28: 745/845 | H28: 1800 | I28: 1700 | J28: 1700 | K28: =SUM(K4:K27) -> 70 | L28: =SUM(L4:L27) -> 125 | M28: =SUM(M4:M27) -> 115 | N28: =SUM(N4:N27) -> 0 | O28: =SUM(O4:O27) -> 0 | P28: =SUM(P4:P27) -> 0
A29: Total/Week | B29: =((B28/100)*5+C28/100+D28/100) -> 50 | E29: 64.55/74.2 | H29: =((H28/100)*5+I28/100+J28/100) -> 124 | K29: =((K28/100)*5+L28/100+M28/100) -> 5.9 | N29: =((N28/100)*5+O28/100+P28/100) -> 0
A30: Total/Year | B30: =B29*52.14 -> 2607 | E30: 3357/3869 | H30: =H29*52.14 -> 6465.36 | K30: =K29*52.14 -> 307.626 | N30: =N29*52.14 -> 0

Sheet Schedules - Office
A1: Hour of Day (Time) | B1: Schedule for Occupancy | E1: Schedule for Lighting/Receptacle | H1: Schedule for HVAC System | K1: Schedule for Service Hot Water | N1: Schedule for Elevator
B2: Percent of Maximum Load | E2: Percent of Maximum Load | K2: Percent of Maximum Load | N2: Percent of Maximum Load
B3: Wk | C3: Sat | D3: Sun | E3: Wk | F3: Sat | G3: Sun | H3: Wk | I3: Sat | J3: Sun | K3: Wk | L3: Sat | M3: Sun | N3: Wk | O3: Sat | P3: Sun
A4: 1 (12-1am) | B4: 0 | C4: 0 | D4: 0 | E4: 5 | F4: 5 | G4: 5 | H4: Off | I4: Off | J4: Off | K4: 5 | L4: 5 | M4: 4 | N4: 0 | O4: 0 | P4: 0
A5: 2 (1-2am) | B5: 0 | C5: 0 | D5: 0 | E5: 5 | F5: 5 | G5: 5 | H5: Off | I5: Off | J5: Off | K5: 5 | L5: 5 | M5: 4 | N5: 0 | O5: 0 | P5: 0
A6: 3 (2-3am) | B6: 0 | C6: 0 | D6: 0 | E6: 5 | F6: 5 | G6: 5 | H6: Off | I6: Off | J6: Off | K6: 5 | L6: 5 | M6: 4 | N6: 0 | O6: 0 | P6: 0
A7: 4 (3-4am) | B7: 0 | C7: 0 | D7: 0 | E7: 5 | F7: 5 | G7: 5 | H7: Off | I7: Off | J7: Off | K7: 5 | L7: 5 | M7: 4 | N7: 0 | O7: 0 | P7: 0
A8: 5 (4-5am) | B8: 0 | C8: 0 | D8: 0 | E8: 5 | F8: 5 | G8: 5 | H8: Off | I8: Off | J8: Off | K8: 5 | L8: 5 | M8: 4 | N8: 0 | O8: 0 | P8: 0
A9: 6 (5-6am) | B9: 0 | C9: 0 | D9: 0 | E9: 10 | F9: 5 | G9: 5 | H9: Off | I9: Off | J9: Off | K9: 8 | L9: 8 | M9: 7 | N9: 0 | O9: 0 | P9: 0
A10: 7 (6-7am) | B10: 10 | C10: 10 | D10: 5 | E10: 10 | F10: 10 | G10: 5 | H10: On | I10: On | J10: Off | K10: 7 | L10: 7 | M10: 4 | N10: 0 | O10: 0 | P10: 0
A11: 8 (7-8am) | B11: 20 | C11: 10 | D11: 5 | E11: 30 | F11: 10 | G11: 5 | H11: On | I11: On | J11: Off | K11: 19 | L11: 11 | M11: 4 | N11: 35 | O11: 16 | P11: 0
A12: 9 (8-9am) | B12: 95 | C12: 30 | D12: 5 | E12: 65/95 | F12: 30 | G12: 5 | H12: On | I12: On | J12: Off | K12: 35 | L12: 15 | M12: 4 | N12: 69 | O12: 14 | P12: 0
A13: 10 (9-10am) | B13: 95 | C13: 30 | D13: 5 | E13: 65/95 | F13: 30 | G13: 5 | H13: On | I13: On | J13: Off | K13: 38 | L13: 21 | M13: 4 | N13: 43 | O13: 21 | P13: 0
A14: 11 (10-11am) | B14: 95 | C14: 30 | D14: 5 | E14: 65/95 | F14: 30 | G14: 5 | H14: On | I14: On | J14: Off | K14: 39 | L14: 19 | M14: 4 | N14: 37 | O14: 18 | P14: 0
A15: 12 (11-12pm) | B15: 95 | C15: 30 | D15: 5 | E15: 65/95 | F15: 30 | G15: 5 | H15: On | I15: On | J15: Off | K15: 47 | L15: 23 | M15: 6 | N15: 43 | O15: 25 | P15: 0
A16: 13 (12-1pm) | B16: 50 | C16: 10 | D16: 5 | E16: 55/80 | F16: 15 | G16: 5 | H16: On | I16: On | J16: Off | K16: 57 | L16: 20 | M16: 6 | N16: 58 | O16: 21 | P16: 0
A17: 14 (1-2pm) | B17: 95 | C17: 10 | D17: 5 | E17: 65/95 | F17: 15 | G17: 5 | H17: On | I17: On | J17: Off | K17: 54 | L17: 19 | M17: 9 | N17: 48 | O17: 13 | P17: 0
A18: 15 (2-3pm) | B18: 95 | C18: 10 | D18: 5 | E18: 65/95 | F18: 15 | G18: 5 | H18: On | I18: On | J18: Off | K18: 34 | L18: 15 | M18: 6 | N18: 37 | O18: 8 | P18: 0
A19: 16 (3-4pm) | B19: 95 | C19: 10 | D19: 5 | E19: 65/95 | F19: 15 | G19: 5 | H19: On | I19: On | J19: Off | K19: 33 | L19: 12 | M19: 4 | N19: 37 | O19: 4 | P19: 0
A20: 17 (4-5pm) | B20: 95 | C20: 10 | D20: 5 | E20: 65/95 | F20: 15 | G20: 5 | H20: On | I20: On | J20: Off | K20: 44 | L20: 14 | M20: 4 | N20: 46 | O20: 5 | P20: 0
A21: 18 (5-6pm) | B21: 30 | C21: 5 | D21: 5 | E21: 35/50 | F21: 5 | G21: 5 | H21: On | I21: On | J21: Off | K21: 26 | L21: 7 | M21: 4 | N21: 62 | O21: 6 | P21: 0
A22: 19 (6-7pm) | B22: 10 | C22: 5 | D22: 0 | E22: 30 | F22: 5 | G22: 5 | H22: On | I22: Off | J22: Off | K22: 21 | L22: 7 | M22: 4 | N22: 20 | O22: 0 | P22: 0
A23: 20 (7-8pm) | B23: 10 | C23: 0 | D23: 0 | E23: 30 | F23: 5 | G23: 5 | H23: On | I23: Off | J23: Off | K23: 15 | L23: 7 | M23: 4 | N23: 12 | O23: 0 | P23: 0
A24: 21 (8-9pm) | B24: 10 | C24: 0 | D24: 0 | E24: 20 | F24: 5 | G24: 5 | H24: On | I24: Off | J24: Off | K24: 17 | L24: 7 | M24: 4 | N24: 4 | O24: 0 | P24: 0
A25: 22 (9-10pm) | B25: 10 | C25: 0 | D25: 0 | E25: 20 | F25: 5 | G25: 5 | H25: On | I25: Off | J25: Off | K25: 8 | L25: 9 | M25: 7 | N25: 4 | O25: 0 | P25: 0
A26: 23 (10-11pm) | B26: 5 | C26: 0 | D26: 0 | E26: 10 | F26: 5 | G26: 5 | H26: Off | I26: Off | J26: Off | K26: 5 | L26: 5 | M26: 4 | N26: 0 | O26: 0 | P26: 0
A27: 24 (11-12am) | B27: 5 | C27: 0 | D27: 0 | E27: 5 | F27: 5 | G27: 5 | H27: Off | I27: Off | J27: Off | K27: 5 | L27: 5 | M27: 4 | N27: 0 | O27: 0 | P27: 0
A28: Total/Day | B28: =SUM(B4:B27) -> 920 | C28: =SUM(C4:C27) -> 200 | D28: =SUM(D4:D27) -> 60 | E28: 800/1040 | F28: 280 | G28: 120 | H28: 1600 | I28: 1200 | J28: 0 | K28: =SUM(K4:K27) -> 537 | L28: =SUM(L4:L27) -> 256 | M28: =SUM(M4:M27) -> 113 | N28: =SUM(N4:N27) -> 555 | O28: =SUM(O4:O27) -> 151 | P28: =SUM(P4:P27) -> 0
A29: Total/Week | B29: =((B28/100)*5+C28/100+D28/100) -> 48.6 | E29: 44.00/56.00 | H29: =((H28/100)*5+I28/100+J28/100) -> 92 | K29: =((K28/100)*5+L28/100+M28/100) -> 30.54 | N29: =((N28/100)*5+O28/100+P28/100) -> 29.26
A30: Total/Year | B30: =B29*52.14 -> 2534.004 | E30: 2288/2920 | H30: =H29*52.14 -> 4796.88 | K30: =K29*52.14 -> 1592.3556 | N30: =N29*52.14 -> 1525.6164

Sheet Schedules - Retail
A1: Hour of Day (Time) | B1: Schedule for Occupancy | E1: Schedule for Lighting/Receptacle | H1: Schedule for HVAC System | K1: Schedule for Service Hot Water | N1: Schedule for Elevator
B2: Percent of Maximum Load | E2: Percent of Maximum Load | K2: Percent of Maximum Load | N2: Percent of Maximum Load
B3: Wk | C3: Sat | D3: Sun | E3: Wk | F3: Sat | G3: Sun | H3: Wk | I3: Sat | J3: Sun | K3: Wk | L3: Sat | M3: Sun | N3: Wk | O3: Sat | P3: Sun
A4: 1 (12-1am) | B4: 0 | C4: 0 | D4: 0 | E4: 5 | F4: 5 | G4: 5 | H4: Off | I4: Off | J4: Off | K4: 4 | L4: 11 | M4: 7 | N4: 0 | O4: 0 | P4: 0
A5: 2 (1-2am) | B5: 0 | C5: 0 | D5: 0 | E5: 5 | F5: 5 | G5: 5 | H5: Off | I5: Off | J5: Off | K5: 5 | L5: 10 | M5: 7 | N5: 0 | O5: 0 | P5: 0
A6: 3 (2-3am) | B6: 0 | C6: 0 | D6: 0 | E6: 5 | F6: 5 | G6: 5 | H6: Off | I6: Off | J6: Off | K6: 5 | L6: 8 | M6: 7 | N6: 0 | O6: 0 | P6: 0
A7: 4 (3-4am) | B7: 0 | C7: 0 | D7: 0 | E7: 5 | F7: 5 | G7: 5 | H7: Off | I7: Off | J7: Off | K7: 4 | L7: 6 | M7: 6 | N7: 0 | O7: 0 | P7: 0
A8: 5 (4-5am) | B8: 0 | C8: 0 | D8: 0 | E8: 5 | F8: 5 | G8: 5 | H8: Off | I8: Off | J8: Off | K8: 4 | L8: 6 | M8: 6 | N8: 0 | O8: 0 | P8: 0
A9: 6 (5-6am) | B9: 0 | C9: 0 | D9: 0 | E9: 5 | F9: 5 | G9: 5 | H9: Off | I9: Off | J9: Off | K9: 4 | L9: 6 | M9: 6 | N9: 0 | O9: 0 | P9: 0
A10: 7 (6-7am) | B10: 0 | C10: 0 | D10: 0 | E10: 5 | F10: 5 | G10: 5 | H10: On | I10: On | J10: Off | K10: 4 | L10: 7 | M10: 7 | N10: 0 | O10: 0 | P10: 0
A11: 8 (7-8am) | B11: 10 | C11: 10 | D11: 0 | E11: 20 | F11: 10 | G11: 5 | H11: On | I11: On | J11: Off | K11: 15 | L11: 20 | M11: 10 | N11: 12 | O11: 9 | P11: 0
A12: 9 (8-9am) | B12: 20 | C12: 20 | D12: 0 | E12: 50 | F12: 30 | G12: 10 | H12: On | I12: On | J12: On | K12: 23 | L12: 24 | M12: 12 | N12: 22 | O12: 21 | P12: 0
A13: 10 (9-10am) | B13: 50 | C13: 50 | D13: 10 | E13: 85/90 | F13: 55/60 | G13: 10 | H13: On | I13: On | J13: On | K13: 32 | L13: 27 | M13: 14 | N13: 64 | O13: 56 | P13: 11
A14: 11 (10-11am) | B14: 50 | C14: 60 | D14: 20 | E14: 85/90 | F14: 85/90 | G14: 40 | H14: On | I14: On | J14: On | K14: 41 | L14: 42 | M14: 29 | N14: 74 | O14: 66 | P14: 13
A15: 12 (11-12pm) | B15: 70 | C15: 80 | D15: 20 | E15: 85/90 | F15: 85/90 | G15: 40 | H15: On | I15: On | J15: On | K15: 57 | L15: 54 | M15: 31 | N15: 68 | O15: 68 | P15: 35
A16: 13 (12-1pm) | B16: 70 | C16: 80 | D16: 40 | E16: 85/90 | F16: 85/90 | G16: 55/60 | H16: On | I16: On | J16: On | K16: 62 | L16: 59 | M16: 36 | N16: 68 | O16: 68 | P16: 37
A17: 14 (1-2pm) | B17: 70 | C17: 80 | D17: 40 | E17: 85/90 | F17: 85/90 | G17: 55/60 | H17: On | I17: On | J17: On | K17: 61 | L17: 60 | M17: 36 | N17: 71 | O17: 69 | P17: 37
A18: 15 (2-3pm) | B18: 70 | C18: 80 | D18: 40 | E18: 85/90 | F18: 85/90 | G18: 55/60 | H18: On | I18: On | J18: On | K18: 50 | L18: 49 | M18: 34 | N18: 72 | O18: 70 | P18: 39
A19: 16 (3-4pm) | B19: 80 | C19: 80 | D19: 40 | E19: 85/90 | F19: 85/90 | G19: 55/60 | H19: On | I19: On | J19: On | K19: 45 | L19: 48 | M19: 35 | N19: 72 | O19: 69 | P19: 41
A20: 17 (4-5pm) | B20: 70 | C20: 80 | D20: 40 | E20: 85/90 | F20: 85/90 | G20: 55/60 | H20: On | I20: On | J20: On | K20: 46 | L20: 47 | M20: 37 | N20: 73 | O20: 66 | P20: 38
A21: 18 (5-6pm) | B21: 50 | C21: 60 | D21: 20 | E21: 85/90 | F21: 85/90 | G21: 40 | H21: On | I21: On | J21: Off | K21: 47 | L21: 46 | M21: 34 | N21: 68 | O21: 58 | P21: 34
A22: 19 (6-7pm) | B22: 50 | C22: 20 | D22: 10 | E22: 55/60 | F22: 50 | G22: 20 | H22: On | I22: On | J22: Off | K22: 42 | L22: 44 | M22: 25 | N22: 68 | O22: 47 | P22: 3
A23: 20 (7-8pm) | B23: 30 | C23: 20 | D23: 0 | E23: 55/60 | F23: 30 | G23: 5 | H23: On | I23: On | J23: Off | K23: 34 | L23: 36 | M23: 27 | N23: 58 | O23: 43 | P23: 0
A24: 21 (8-9pm) | B24: 30 | C24: 20 | D24: 0 | E24: 50 | F24: 30 | G24: 5 | H24: On | I24: On | J24: Off | K24: 33 | L24: 29 | M24: 21 | N24: 54 | O24: 43 | P24: 0
A25: 22 (9-10pm) | B25: 0 | C25: 10 | D25: 0 | E25: 20 | F25: 10 | G25: 5 | H25: Off | I25: On | J25: Off | K25: 23 | L25: 22 | M25: 16 | N25: 0 | O25: 8 | P25: 0
A26: 23 (10-11pm) | B26: 0 | C26: 0 | D26: 0 | E26: 5 | F26: 5 | G26: 5 | H26: Off | I26: Off | J26: Off | K26: 13 | L26: 16 | M26: 10 | N26: 0 | O26: 0 | P26: 0
A27: 24 (11-12am) | B27: 0 | C27: 0 | D27: 0 | E27: 5 | F27: 5 | G27: 5 | H27: Off | I27: Off | J27: Off | K27: 8 | L27: 13 | M27: 6 | N27: 0 | O27: 0 | P27: 0
A28: Total/Day | B28: =SUM(B4:B27) -> 720 | C28: =SUM(C4:C27) -> 750 | D28: =SUM(D4:D27) -> 280 | E28: 1060/1155 | F28: 940/985 | G28: 500/525 | H28: 1500 | I28: 1600 | J28: 900 | K28: =SUM(K4:K27) -> 662 | L28: =SUM(L4:L27) -> 690 | M28: =SUM(M4:M27) -> 459 | N28: =SUM(N4:N27) -> 844 | O28: =SUM(O4:O27) -> 761 | P28: =SUM(P4:P27) -> 288
A29: Total/Week | B29: =((B28/100)*5+C28/100+D28/100) -> 46.3 | E29: 67.40/70.85 | H29: =((H28/100)*5+I28/100+J28/100) -> 100 | K29: =((K28/100)*5+L28/100+M28/100) -> 44.59 | N29: =((N28/100)*5+O28/100+P28/100) -> 52.69
A30: Total/Year | B30: =B29*52.14 -> 2414.082 | E30: 3505/3694 | H30: =H29*52.14 -> 5214 | K30: =K29*52.14 -> 2324.9226 | N30: =N29*52.14 -> 2747.2566

Sheet Schedules - Dwelling Unit
A1: Hour of Day (Time) | B1: Schedule for Occupancy | E1: Schedule for Lighting/Receptacle | H1: Daily Thermostat Schedule | J1: Schedule for Service Hot Water
B2: Percent of Maximum Load | E2: Percent of Maximum Load | J2: Percent of Maximum Load
B3: Wk | C3: Sat | D3: Sun | E3: Wk | F3: Sat | G3: Sun | H3: Cooling | I3: Heating | J3: Wk | K3: Sat | L3: Sun
A4: 1 (12-1am) | B4: 1.6 | C4: 1.6 | D4: 1.6 | E4: 5 | F4: 5 | G4: 5 | H4: 70 | I4: 78 | J4: 5 | K4: 5 | L4: 5
A5: 2 (1-2am) | B5: 1.6 | C5: 1.6 | D5: 1.6 | E5: 5 | F5: 5 | G5: 5 | H5: 70 | I5: 78 | J5: 5 | K5: 5 | L5: 5
A6: 3 (2-3am) | B6: 1.6 | C6: 1.6 | D6: 1.6 | E6: 5 | F6: 5 | G6: 5 | H6: 70 | I6: 78 | J6: 5 | K6: 5 | L6: 5
A7: 4 (3-4am) | B7: 1.6 | C7: 1.6 | D7: 1.6 | E7: 5 | F7: 5 | G7: 5 | H7: 70 | I7: 78 | J7: 5 | K7: 5 | L7: 5
A8: 5 (4-5am) | B8: 1.6 | C8: 1.6 | D8: 1.6 | E8: 5 | F8: 5 | G8: 5 | H8: 70 | I8: 78 | J8: 5 | K8: 5 | L8: 5
A9: 6 (5-6am) | B9: 1.6 | C9: 1.6 | D9: 1.6 | E9: 5 | F9: 5 | G9: 5 | H9: 70 | I9: 78 | J9: 5 | K9: 5 | L9: 5
A10: 7 (6-7am) | B10: 7.7 | C10: 7.7 | D10: 7.7 | E10: 5 | F10: 5 | G10: 5 | H10: 72 | I10: 78 | J10: 30 | K10: 30 | L10: 30
A11: 8 (7-8am) | B11: 14 | C11: 14 | D11: 14 | E11: 5 | F11: 5 | G11: 5 | H11: 72 | I11: 78 | J11: 50 | K11: 50 | L11: 50
A12: 9 (8-9am) | B12: 14 | C12: 14 | D12: 14 | E12: 50 | F12: 50 | G12: 50 | H12: 72 | I12: 78 | J12: 40 | K12: 40 | L12: 40
A13: 10 (9-10am) | B13: 10.8 | C13: 10.8 | D13: 10.8 | E13: 50 | F13: 50 | G13: 50 | H13: 72 | I13: 80 | J13: 30 | K13: 30 | L13: 30
A14: 11 (10-11am) | B14: 10.8 | C14: 10.8 | D14: 10.8 | E14: 50 | F14: 50 | G14: 50 | H14: 72 | I14: 80 | J14: 30 | K14: 30 | L14: 30
A15: 12 (11-12pm) | B15: 10.8 | C15: 10.8 | D15: 10.8 | E15: 50 | F15: 50 | G15: 50 | H15: 72 | I15: 80 | J15: 35 | K15: 35 | L15: 35
... A27: 24 (11-12am) | B27: 1.6 | C27: 1.6 | D27: 1.6 | E27: 5 | F27: 5 | G27: 5 | H27: 70 | I27: 78 | J27: 5 | K27: 5 | L27: 5
A28: Total/Day | B28: =SUM(B4:B27) -> 234 | C28: =SUM(C4:C27) -> 234 | D28: =SUM(D4:D27) -> 234 | E28: =SUM(E4:E27) -> 580 | F28: =SUM(F4:F27) -> 580 | G28: =SUM(G4:G27) -> 580 | J28: =SUM(J4:J27) -> 670 | K28: =SUM(K4:K27) -> 670 | L28: =SUM(L4:L27) -> 670
A29: Total/Week | B29: =((B28/100)*5+C28/100+D28/100) -> 16.38 | E29: =((E28/100)*5+F28/100+G28/100) -> 40.6 | J29: =((J28/100)*5+K28/100+L28/100) -> 46.9
A30: Total/Year | B30: =B29*52.14 -> 854.0532 | E30: =E29*52.14 -> 2116.884 | J30: =J29*52.14 -> 2445.366

Sheet Version Control
A1: Version # | B1: Issue Date | C1: Fixes
A2: Version 1 | B2: 43963
A3: Version 2 | B3: 43965 | C3: 1,2,3. - edit cell B7, add dropdown cell C7
C4: 3d. - edit cell/formula in D18
C5: 4. - unlock cell D17
C6: 5b. - edit cells C18:L18
C7: 6c. - unlock ability to add rows
C8: 6d.1 - align with spaces/lpd (not blg area)
C9: 6f. - add formulas to C20:D21
C10: 6g. - add formula for baseline
A11: Version 3 | B11: 43973 | C11: 6b. - add more fenestration rows
C12: 6b. - fixed cell M22 for no skylight
C13: 6c1. - rename tab, remove ability to add rows
C14: 6c2. - add new tab for additional opaque rows
C15: 6d.1 - align all rows with spaces/lpd (not blg area)
C16: 6d.1 - edit formula for cell B31
C17: Instructions for HVAC_Cover - added Items 5 & 6
A18: Version 4 | B18: 44125 | C18: 4. - edited H19:I20 to consistant units of kBTU, instead of kwh and therm
C19: 5b. - added missing formula to cell d11
A20: Version 5 | B20: 44175 | C20: UNPROTECT WORKBOOK
A21: Version 6 | B21: 45057 | C21: Edited "Lighting Lookup" tab for Multifamily Dwelling Unit LPD from 0.70 to 1.07 (per Table G3.7)
B22: 45063 | C22: Edited 6d.1 & 6d.2, corrected sum formula for building and space areas
A23: Verson 7 | B23: 45148 | C23: Unprotected "HVAC Air-side" tab
C24: Protected "HVAC_Cover" tab

Sheet 1,2,3 Information
A2: Enter information for sections 1, 2 and 3 - incorporate in the drawing set.
A3: Must be typewritten
A4: 1 | B4: Location Information
B5: House No(s) 79 | C5: Street Name WINTHROP STREET
B6: Borough BROOKLYN | C6: Block 5045 | D6: Lot 72 | E6: BIN 3115681 | G6: CB No. 309
B7: Job Type (NB, Alt, etc.) | C7: New Building
A10: 2a | B10: Applicant Information
B11: Last Name FAYBYSHENKO | D11: First Name GENNADIY | I11: Middle Initial B.
B12: Business Name CHOSEN MEP, CORP. | F12: Business Email
B13: Business Address 31-00 47TH AVENUE SUITE #3100 | F13: Business Telephone 347-766-5010
B14: City LONG ISLAND CITY | C14: State NY | E14: Zip 11101
B15: Email INFO@CHOSENMEP.COM | G15: License Number 091045
A18: 2b | B18: Modeling Firm
B19: Last Name (lead modeler) BEREGOVYKH | D19: First Name (lead modeler) NIKITA | I19: Middle Initial
B20: Business Name LIBER CREATIVE LLC | F20: Email (lead modeler) NVBEREGOVYKH@LIBERPICT.COM
B21: Business Address 2306 OCEAN AVENUE | F21: Telephone (lead modeler) 929-356-1398
B22: City BROOKLYN | C22: State NY | E22: Zip 11229
A25: 3a | B25: Energy Modeling Information | F25: 3b | G25: Energy Modeling Information per Modeled Square Feet
B26: Modeling Protocol (Sect 11 or Apx G) | C26: =IF(Path="","Select Path on tab 4. Compliance",Path) -> Appendix G PRM | G26: Proposed | H26: Total Energy Cost ($/sf) | I26: ='4. Compliance'!G12/'1,2,3 Information'!C32 -> 2.1859941
B27: Modeling Software & version | C27: EnergyPlus Version 25.1.0-1c11a3d85f | H27: Site EUI (kBtu/sf) | I27: =('5b. Usage Summary'!G17*3.412+'5b. Usage Summary'!H17*100)/'1,2,3 Information'!C32 -> 29.834739
B28: Weather File | C28: NEW YORK LAGUARDIA ARPT NY USA TMY3 | H28: Source EUI (kBtu/sf) | I28: =('5b. Usage Summary'!G17*3.412*2.55+'5b. Usage Summary'!H17*100*1.05)/'1,2,3 Information'!C32 -> 76.078585
B29: Proposed Unmet Load Hours | C29: 70.66 | H29: GHG (tCO2e/sf) | I29: ='3d. LL97 GHG Summary'!E33/'1,2,3 Information'!C32 -> 0.0025267016
B30: Baseline Unmet Load Hours | C30: 34.66 | G30: Baseline | H30: Total Energy Cost ($/sf) | I30: ='4. Compliance'!E12/'1,2,3 Information'!C32 -> 3.4558825
B31: Gross Square Feet | C31: 12381.63 | H31: Site EUI (kBtu/sf) | I31: =('5b. Usage Summary'!C17*3.412+'5b. Usage Summary'!D17*100)/'1,2,3 Information'!C32 -> 80.627983
B32: Modeled Square Feet | C32: 11690.791 | H32: Source EUI (kBtu/sf) | I32: =('5b. Usage Summary'!C17*3.412*2.55+'5b. Usage Summary'!D17*100*1.05)/'1,2,3 Information'!C32 -> 143.02646
B33: Conditioned Square Feet | C33: 11169.925 | H33: GHG (tCO2e/sf) | I33: =SUM('3d. LL97 GHG Summary'!J24:J28)/'1,2,3 Information'!C32 -> 0.0055109706
B34: Semi-heated Square Feet | C34: 0 | G34: % Savings | H34: Total Energy Cost ($/sf) | I34: =(I30-I26)/I30 -> 0.36745706
B35: Unconditioned Square Feet | C35: 520.866 | H35: Site EUI (kBtu/sf) | I35: =(I31-I27)/I31 -> 0.62997041
H36: Source EUI (kBtu/sf) | I36: =(I32-I28)/I32 -> 0.46808036
A37: 3c | B37: List all Job Numbers Associated with this Model | H37: GHG (tCO2e/sf) | I37: =(I33-I29)/I33 -> 0.54151423
B38: ARCHITECTURAL | C38: B01304513-P1
B39: MECHANICAL | C39: B01304513-P6
B40: PLUMBING | C40: B01304513-P5

Sheet 3d. LL97 GHG Summary
A3: FOR INFORMATIONAL PURPOSES ONLY: NOT REQUIRED FOR ENERGY CODE COMPLIANCE
B8: 3d | C8: Carbon Emissions Limit (LL97)
C9: Occupancy | D9: Total Gross SQFT per occupancy | F9: tCO2e limit (2024) | H9: tCO2e limit (2030)
F10: =IF(C10="","",VLOOKUP(C10,Lists!A134:B143,2,FALSE)) | H10: =IF(C10="","",VLOOKUP(C10,Lists!$A$133:$C$143,3,FALSE))
F11: =IF(C11="","",VLOOKUP(C11,Lists!$A$134:$F$144,2,FALSE)) | H11: =IF(C11="","",VLOOKUP(C11,Lists!$A$133:$C$143,3,FALSE))
F12: =IF(C12="","",VLOOKUP(C12,Lists!$A$134:$F$144,2,FALSE)) | H12: =IF(C12="","",VLOOKUP(C12,Lists!$A$133:$C$143,3,FALSE))
F13: =IF(C13="","",VLOOKUP(C13,Lists!$A$134:$F$144,2,FALSE)) | H13: =IF(C13="","",VLOOKUP(C13,Lists!$A$133:$C$143,3,FALSE))
F14: =IF(C14="","",VLOOKUP(C14,Lists!$A$134:$F$144,2,FALSE)) | H14: =IF(C14="","",VLOOKUP(C14,Lists!$A$133:$C$143,3,FALSE))
F15: =IF(C15="","",VLOOKUP(C15,Lists!$A$134:$F$144,2,FALSE)) | H15: =IF(C15="","",VLOOKUP(C15,Lists!$A$133:$C$143,3,FALSE))
F16: =IF(C16="","",VLOOKUP(C16,Lists!$A$134:$F$144,2,FALSE)) | H16: =IF(C16="","",VLOOKUP(C16,Lists!$A$133:$C$143,3,FALSE))
F17: =IF(C17="","",VLOOKUP(C17,Lists!$A$134:$F$144,2,FALSE)) | H17: =IF(C17="","",VLOOKUP(C17,Lists!$A$133:$C$143,3,FALSE))
C18: TOTAL | D18: =IF(D10="","",IF(SUM(D10:E17)='1,2,3 Information'!C31,SUM(D10:E17),"Total area does not align with GROSS FLOOR AREA of the building"))
C19: GHG Building Emission Limits | F19: =SUMPRODUCT(D10:D17,F10:F17) -> 0 | H19: =SUMPRODUCT(D10:D17,H10:H17) -> 0
C20: Proposed Building GHG (estimated from model) | F20: =SUM(F24:F28) -> 29.53914
B22: 3e | C22: Carbon Emissions Proposed Building (LL97) | G22: Carbon Emissions Baseline Building (LL97)
D23: (kBTU) | E23: tCO2e per kBTU | F23: tCO2e | H23: (kBTU) | I23: tCO2e per kBTU | J23: tCO2e
C24: Electricity (kwh) | D24: =IF('5b. Usage Summary'!$G$17="","",'5b. Usage Summary'!$G$17) -> 102225 | E24: 0.000288962 | F24: =IF(D24="","",E24*D24) -> 29.53914 | G24: Electricity (kwh) | H24: =IF('5b. Usage Summary'!$C$17="","",'5b. Usage Summary'!$C$17) -> 133325 | I24: 0.000288962 | J24: =IF(H24="","",I24*H24) -> 38.525859
C25: Natural Gas | D25: =IF('5b. Usage Summary'!$H$17="","",'5b. Usage Summary'!$H$17*100) -> 0 | E25: 5.311e-05 | F25: =IF(D25="","",E25*D25) -> 0 | G25: Natural Gas | H25: =IF('5b. Usage Summary'!$D$17="","",'5b. Usage Summary'!$D$17*100) -> 487700 | I25: 5.311e-05 | J25: =IF(H25="","",I25*H25) -> 25.901747
C26: #2 Fuel Oil | E26: 7.421e-05 | F26: =IF(D26="","",E26*D26) | G26: #2 Fuel Oil | I26: 7.421e-05 | J26: =IF(H26="","",I26*H26)
C27: #4 Fuel Oil | E27: 7.529e-05 | F27: =IF(D27="","",E27*D27) | G27: #4 Fuel Oil | I27: 7.529e-05 | J27: =IF(H27="","",I27*H27)
C28: District Steam | E28: 4.493e-05 | F28: =IF(D28="","",E28*D28) | G28: District Steam | I28: 4.493e-05 | J28: =IF(H28="","",I28*H28)
B30: 3e | C30: Carbon Emissions Information (LL97)
E31: tCO2e Limits for 2024-2029 | G31: tCO2e Limits for 2030-2034
C32: tCO2e Limit (LL97) | E32: =IF('3d. LL97 GHG Summary'!F19="","",'3d. LL97 GHG Summary'!F19) -> 0 | G32: =IF('3d. LL97 GHG Summary'!H19="","",'3d. LL97 GHG Summary'!H19) -> 0
C33: tCO2e for this Building | E33: =IF('5b. Usage Summary'!G17="","",SUM('3d. LL97 GHG Summary'!F24:F28)) -> 29.53914
C34: Does this building comply with LL97? | E34: =IF(E33="","",IF(E33="","",IF(AND(E33<E32,E33<G32),"This building is subject to meeting LL97 of 2019. The proposed design is estimated to comply with the Carbon Limits for 2024-2029 & 2030-2035.",IF(AND(E33<E32,E33>G32),"This building is subject to meeting LL97 of 2019. By 2030, this proposed design may not comply with the requirements of LL97 based on the estimated carbon emissions.","This building is subject to meeting LL97 of 2019. By 2024, this proposed design may not comply with the requirements of LL97 based on the estimated carbon emissions.")))) -> This building is subject to meeting LL97 of 2019. By 2024, this proposed design may not comply with the requirements of LL97 based on the estimated carbon emissions.
C36: **Total carbon emissions (tCO2e) for this building is an estimate for informational purposes based on the proposed occupancy, gross square footage, and modeled annual energy usage. The performance of the building will be affected by construction quality, occupancy, and operational impacts. Actual carbon emissions may be higher or lower than this estimate. **

Sheet 4. Compliance
A3: 4a. | B3: Energy Modeling Protocol (select)
B4: Appendix G PRM
A6: 4b. | B6: Purchased Energy Rates & Compliance Documentation
A7: Fuel | C7: Utility Rate Provider/Rate Structure (i.e ConEd) | D7: Virtual Utility Rate ($/unit) | E7: Baseline Design Total Charge ($) | F7: Virtual Utility Rate ($/unit) | G7: Proposed Design Total Charge ($) | H7: Supporting Doc. Location | I7: Model Output Report
A8: Electric | C8: Con Edison | D8: 0.25 | E8: ='5a. Baseline Rotations'!O23 -> 33332 | F8: 0.25 | G8: 25556 | H8: Energy Model (Appendix G) | I8: BEPU, BEPU-P
A9: Gas/Steam | C9: Con Edison | D9: 1.45 | E9: ='5a. Baseline Rotations'!O24 -> 7070 | H9: Energy Model (Appendix G) | I9: BEPU, BEPU-P
A10: Other - ($/kBTU) | E10: ='5a. Baseline Rotations'!O25 | H10: Energy Model (Appendix G) | I10: BEPU, BEPU-P
H11: COST SAVINGS | I11: COMPLIES?
A12: TOTAL | E12: =IF(SUM(E8:E10)=0,"",SUM(E8:E10)) -> 40402 | G12: =IF(SUM(G8:G10)=0,"",SUM(G8:G10)) -> 25556 | H12: =IF(E12="","",E12-G12) -> 14846 | I12: =IF(E12="","",IF(B4="Section 11 ECB",IF(G12<E12,"COMPLIES","DOES NOT COMPLY"),IF(D21<C21,"COMPLIES","DOES NOT COMPLY"))) -> COMPLIES
A15: 4c. | B15: Performance Cost Index - Appendix G ONLY | F15: 4d. | G15: Performance Source Energy Index - Appendix G ONLY
C16: Baseline Building | D16: Proposed Building | H16: Baseline Building | I16: Proposed Building
A17: Building Performance Factor | C17: =IF(D17="","",IF(D17="Weighted Average",D25,VLOOKUP(D17,Lists!M13:N22,2))) -> 0.67 | D17: Multifamily | F17: Building Performance Factor | H17: =IF(I17="","",IF(I17="Weighted Average",D27,VLOOKUP(I17,Lists!M13:O22,3))) -> 0.68 | I17: =IF(D17="","",D17) -> Multifamily
A18: Baseline Regulated Cost | C18: =IF(B4="Section 11 ECB","",IF(C20="","",C20-C19)) -> 39679.75 | D18: =IF(B4="Section 11 ECB","",IF(D20="","",D20-D19)) -> 24833.75 | F18: Baseline Regulated Source Energy | H18: =IF(B4="Section 11 ECB","",IF(I17="","",H20-H19)) -> 1646956.5 | I18: =IF(B4="Section 11 ECB","",IF(I17="","",I20-I19)) -> 864282.8
A19: Baseline Unregulated Cost | C19: =('5b. Usage Summary'!$C$7)*D8+('5b. Usage Summary'!$D$7)*D9 -> 722.25 | D19: =('5b. Usage Summary'!$G$7)*F8+('5b. Usage Summary'!$H$7)*F9 -> 722.25 | F19: Baseline Unregulated Source Energy | H19: =('5b. Usage Summary'!$C$7)*3.412*2.55+('5b. Usage Summary'!$D$7)*100*1.05 -> 25136.033 | I19: =('5b. Usage Summary'!$G$7)*3.412*2.55+('5b. Usage Summary'!$H$7)*100*1.05 -> 25136.033
A20: Total Energy Cost | C20: =IF(B4="Section 11 ECB","",E12) -> 40402 | D20: =IF(B4="Section 11 ECB","",G12) -> 25556 | F20: Total Source Energy | H20: =IF(B4="Section 11 ECB","",IF(I17="","",SUM('5b. Usage Summary'!C17*3.412*2.55,'5b. Usage Summary'!D17*100*1.05))) -> 1672092.5 | I20: =IF(B4="Section 11 ECB","",IF(I17="","",SUM('5b. Usage Summary'!G17*3.412*2.55,'5b. Usage Summary'!H17*100*1.05))) -> 889418.83
A21: Performance Cost Index | C21: =IF(C20="","",(C19+(C18*C17))/C20) -> 0.67589927 | D21: =IF(D20="","",D20/C20) -> 0.63254294 | F21: Performance Source Energy Index | H21: =IF(H20="","",(H19+(H18*H17))/H20) -> 0.68481046 | I21: =IF(I20="","",I20/H20) -> 0.53191964
A23: 4e. | B23: Weighted BPF | F23: 4f. | G23: Weighted Envelope Backstop (results from ComCheck)
A24: Space Classification | C24: Modeled Area | D24: Weighted BPF (energy cost) | F24: Allowable Margin (baseline)
A25: All Other | D25: =IF(AND(D17="Weighted Average",SUM(C25:C34)<>0),SUMPRODUCT(C25:C34,Lists!N13:N22)/SUM(C25:C34),"Input modeled areas for each space classification") -> Input modeled areas for each space classification | F25: Envelope Design (proposed)
A26: Dormitory | D26: Weighted BPF (source energy)
A27: Healthcare/ hospital | D27: =IF(AND(I17="Weighted Average",SUM(C25:C34)<>0),SUMPRODUCT(C25:C34,Lists!O13:O22)/SUM(C25:C34),"Input modeled areas for each space classification") -> Input modeled areas for each space classification
A28: Hotel/motel
A29: Multifamily | C29: 11690.791
A30: Office
A31: Restaurant
A32: Retail
A33: School
A34: Warehouse
A35: TOTAL | C35: =IF(SUM(C25:C34)<>'1,2,3 Information'!C32,"NOT EQUAL TO MODELED AREA",SUM(C25:C34)) -> 11690.791

Sheet 5a. Baseline Rotations
A2: INSTRUCTIONS: If the modeling parameters call for averaging 4 rotations, enter the data into each of the white columns. If the modeling protocol does not require averaging the 4 rotations, enter the data into only the column labeled "0'" (do not enter '0' into the columns labeled 90, 180, 270).
A4: 5a | B4: Baseline Rotations
A5: Baseline Model
C6: 0' | F6: 90' | I6: 180' | L6: 270' | O6: Average of 4 rotations | R6: Model Output Location (Report)
A7: Annual usage (kwh/therm/kBTU)
C8: kwh | D8: therm | E8: kBTU | F8: kwh | G8: therm | H8: kBTU | I8: kwh | J8: therm | K8: kBTU | L8: kwh | M8: therm | N8: kBTU | O8: kwh | P8: therm | Q8: kBTU
A9: Interior Lighting | C9: 29869 | D9: 0 | E9: 0 | O9: =IF(C9="","",IF(F9=0,C9,AVERAGE(C9,F9,I9,L9))) -> 29869 | P9: =IF(D9="","",IF(G9=0,D9,AVERAGE(D9,G9,J9,M9))) -> 0 | Q9: =IF(E9="","",IF(H9=0,E9,AVERAGE(E9,H9,K9,N9))) -> 0 | R9: BEPU
A10: Misc. Equip. Unregulated | C10: 2889 | D10: 0 | E10: 0 | O10: =IF(C10="","",IF(F10=0,C10,AVERAGE(C10,F10,I10,L10))) -> 2889 | P10: =IF(D10="","",IF(G10=0,D10,AVERAGE(D10,G10,J10,M10))) -> 0 | Q10: =IF(E10="","",IF(H10=0,E10,AVERAGE(E10,H10,K10,N10))) -> 0 | R10: BEPU
A11: Misc. Equip. Regulated | C11: 0 | D11: 0 | E11: 0 | O11: =IF(C11="","",IF(F11=0,C11,AVERAGE(C11,F11,I11,L11))) -> 0 | P11: =IF(D11="","",IF(G11=0,D11,AVERAGE(D11,G11,J11,M11))) -> 0 | Q11: =IF(E11="","",IF(H11=0,E11,AVERAGE(E11,H11,K11,N11))) -> 0 | R11: BEPU
A12: Space Heat | C12: 0 | D12: 3493 | E12: 0 | O12: =IF(C12="","",IF(F12=0,C12,AVERAGE(C12,F12,I12,L12))) -> 0 | P12: =IF(D12="","",IF(G12=0,D12,AVERAGE(D12,G12,J12,M12))) -> 3493 | Q12: =IF(E12="","",IF(H12=0,E12,AVERAGE(E12,H12,K12,N12))) -> 0 | R12: BEPU
A13: Space Cool | C13: 20828 | D13: 0 | E13: 0 | O13: =IF(C13="","",IF(F13=0,C13,AVERAGE(C13,F13,I13,L13))) -> 20828 | P13: =IF(D13="","",IF(G13=0,D13,AVERAGE(D13,G13,J13,M13))) -> 0 | Q13: =IF(E13="","",IF(H13=0,E13,AVERAGE(E13,H13,K13,N13))) -> 0 | R13: BEPU
A14: Heat Rejection | C14: 0 | D14: 0 | E14: 0 | O14: =IF(C14="","",IF(F14=0,C14,AVERAGE(C14,F14,I14,L14))) -> 0 | P14: =IF(D14="","",IF(G14=0,D14,AVERAGE(D14,G14,J14,M14))) -> 0 | Q14: =IF(E14="","",IF(H14=0,E14,AVERAGE(E14,H14,K14,N14))) -> 0 | R14: BEPU
A15: Pumps & Misc | C15: 5433 | D15: 0 | E15: 0 | O15: =IF(C15="","",IF(F15=0,C15,AVERAGE(C15,F15,I15,L15))) -> 5433 | P15: =IF(D15="","",IF(G15=0,D15,AVERAGE(D15,G15,J15,M15))) -> 0 | Q15: =IF(E15="","",IF(H15=0,E15,AVERAGE(E15,H15,K15,N15))) -> 0 | R15: BEPU
A16: Vent Fans | C16: 73953 | D16: 0 | E16: 0 | O16: =IF(C16="","",IF(F16=0,C16,AVERAGE(C16,F16,I16,L16))) -> 73953 | P16: =IF(D16="","",IF(G16=0,D16,AVERAGE(D16,G16,J16,M16))) -> 0 | Q16: =IF(E16="","",IF(H16=0,E16,AVERAGE(E16,H16,K16,N16))) -> 0 | R16: BEPU
A17: Dom. Hot Water | C17: 75 | D17: 1384 | E17: 0 | O17: =IF(C17="","",IF(F17=0,C17,AVERAGE(C17,F17,I17,L17))) -> 75 | P17: =IF(D17="","",IF(G17=0,D17,AVERAGE(D17,G17,J17,M17))) -> 1384 | Q17: =IF(E17="","",IF(H17=0,E17,AVERAGE(E17,H17,K17,N17))) -> 0 | R17: BEPU
A18: Exterior Lighting | C18: 278 | D18: 0 | E18: 0 | O18: =IF(C18="","",IF(F18=0,C18,AVERAGE(C18,F18,I18,L18))) -> 278 | P18: =IF(D18="","",IF(G18=0,D18,AVERAGE(D18,G18,J18,M18))) -> 0 | Q18: =IF(E18="","",IF(H18=0,E18,AVERAGE(E18,H18,K18,N18))) -> 0 | R18: BEPU
A19: Exterior Misc. | C19: 0 | D19: 0 | E19: 0 | O19: =IF(C19="","",IF(F19=0,C19,AVERAGE(C19,F19,I19,L19))) -> 0 | P19: =IF(D19="","",IF(G19=0,D19,AVERAGE(D19,G19,J19,M19))) -> 0 | Q19: =IF(E19="","",IF(H19=0,E19,AVERAGE(E19,H19,K19,N19))) -> 0 | R19: BEPU
A20: TOTAL | C20: =IF(SUM(C9:C19)=0,"",SUM(C9:C19)) -> 133325 | D20: =IF(SUM(D9:D19)=0,"",SUM(D9:D19)) -> 4877 | E20: =IF(SUM(E9:E19)=0,"",SUM(E9:E19)) | F20: =IF(SUM(F9:F19)=0,"",SUM(F9:F19)) | G20: =IF(SUM(G9:G19)=0,"",SUM(G9:G19)) | H20: =IF(SUM(H9:H19)=0,"",SUM(H9:H19)) | I20: =IF(SUM(I9:I19)=0,"",SUM(I9:I19)) | J20: =IF(SUM(J9:J19)=0,"",SUM(J9:J19)) | ... N20: =IF(SUM(N9:N19)=0,"",SUM(N9:N19)) | O20: =IF(C20="","",IF(F20=0,C20,AVERAGE(C20,F20,I20,L20))) -> 133325 | P20: =IF(D20="","",IF(G20=0,D20,AVERAGE(D20,G20,J20,M20))) -> 4877 | Q20: =IF(E20="","",IF(H20=0,E20,AVERAGE(E20,H20,K20,N20))) | R20: BEPU
A21: Annual cost ($)
A23: Electric | C23: 33332 | O23: =IF(C23="","",IF(F23="",C23,AVERAGE(C23:M23))) -> 33332 | R23: BEPU
A24: Gas/Steam | C24: 7070 | O24: =IF(C24="","",IF(F24="",C24,AVERAGE(C24:M24))) -> 7070 | R24: BEPU
A25: Other | O25: =IF(C25="","",IF(F25="",C25,AVERAGE(C25:M25))) | R25: BEPU
A26: TOTAL | C26: =IF(C23="","",SUM(C23:D25)) -> 40402 | F26: =IF(F23="","",SUM(F23:G25)) | I26: =IF(I23="","",SUM(I23:J25)) | L26: =IF(L23="","",SUM(L23:M25)) | O26: =IF(O23="","",SUM(O23:P25)) -> 40402 | R26: BEPU

Sheet 5b. Usage Summary
A2: 5b | B2: Energy Modeling Usage Summary
A3: =CONCATENATE("Compliance based on ",IF(Path="","",Path)) -> Compliance based on Appendix G PRM
C4: Baseline Model | G4: Proposed Model
C5: Electric Usage (kwh) | D5: Gas/Steam Usage (Therm) | E5: Other (i.e. chilled water) (kBTU) | F5: % Usage | G5: Electric Usage (kwh) | H5: Gas/Steam Usage (Therm) | I5: Other (i.e. chilled water) (kBTU) | J5: % Usage | K5: Energy Savings Per End Use (%) | L5: Cost Savings per End Use (%) | M5: Model Output Location (Report)
A6: Interior Lighting | C6: =IF('5a. Baseline Rotations'!O9="","",'5a. Baseline Rotations'!O9) -> 29869 | D6: =IF('5a. Baseline Rotations'!P9="","",'5a. Baseline Rotations'!P9) -> 0 | E6: =IF('5a. Baseline Rotations'!Q9="","",'5a. Baseline Rotations'!Q9) -> 0 | F6: =IF(C6="","",(C6*3.412+D6*100+E6)/($C$17*3.412+$D$17*100+$E$17)) -> 0.1081185 | G6: 3408 | H6: 0 | I6: 0 | J6: =IF(G6="","",(G6*3.412+H6*100+I6)/($G$17*3.412+$H$17*100+$I$17)) -> 0.033338224 | K6: =IF(AND(C6="",D6=""),"",((C6-G6)*3.412+(D6-H6)*100+(E6-I6))/(($C$17-$G$17)*3.412+($D$17-$H$17)*100+($E$17-$I$17))) -> 0.15204265 | L6: =IF(AND(C6="",D6=""),"",(($C6-$G6)*'4. Compliance'!$F$8+($D6-$H6)*'4. Compliance'!$F$9+($E6-$I6)*'4. Compliance'!$F$10)/(($C$17-$G$17)*'4. Compliance'!$F$8+($D$17-$H$17)*'4. Compliance'!$F$9+($E$17-$I$17)*'4. Compliance'!$F$10)) -> 0.85083601 | M6: BEPU, BEPU-P
A7: Misc. Equip. Unregulated | C7: =IF('5a. Baseline Rotations'!O10="","",'5a. Baseline Rotations'!O10) -> 2889 | D7: =IF('5a. Baseline Rotations'!P10="","",'5a. Baseline Rotations'!P10) -> 0 | E7: =IF('5a. Baseline Rotations'!Q10="","",'5a. Baseline Rotations'!Q10) -> 0 | F7: =IF(C7="","",(C7*3.412+D7*100+E7)/($C$17*3.412+$D$17*100+$E$17)) -> 0.010457476 | G7: 2889 | H7: 0 | I7: 0 | J7: =IF(G7="","",(G7*3.412+H7*100+I7)/($G$17*3.412+$H$17*100+$I$17)) -> 0.028261189 | K7: =IF(AND(C7="",D7=""),"",((C7-G7)*3.412+(D7-H7)*100+(E7-I7))/(($C$17-$G$17)*3.412+($D$17-$H$17)*100+($E$17-$I$17))) -> 0 | L7: =IF(AND(C7="",D7=""),"",(($C7-$G7)*'4. Compliance'!$F$8+($D7-$H7)*'4. Compliance'!$F$9+($E7-$I7)*'4. Compliance'!$F$10)/(($C$17-$G$17)*'4. Compliance'!$F$8+($D$17-$H$17)*'4. Compliance'!$F$9+($E$17-$I$17)*'4. Compliance'!$F$10)) -> 0 | M7: BEPU, BEPU-P
A8: Misc. Equip. Regulated | C8: =IF('5a. Baseline Rotations'!O11="","",'5a. Baseline Rotations'!O11) -> 0 | D8: =IF('5a. Baseline Rotations'!P11="","",'5a. Baseline Rotations'!P11) -> 0 | E8: =IF('5a. Baseline Rotations'!Q11="","",'5a. Baseline Rotations'!Q11) -> 0 | F8: =IF(C8="","",(C8*3.412+D8*100+E8)/($C$17*3.412+$D$17*100+$E$17)) -> 0 | G8: 0 | H8: 0 | I8: 0 | J8: =IF(G8="","",(G8*3.412+H8*100+I8)/($G$17*3.412+$H$17*100+$I$17)) -> 0 | K8: =IF(AND(C8="",D8=""),"",((C8-G8)*3.412+(D8-H8)*100+(E8-I8))/(($C$17-$G$17)*3.412+($D$17-$H$17)*100+($E$17-$I$17))) -> 0 | L8: =IF(AND(C8="",D8=""),"",(($C8-$G8)*'4. Compliance'!$F$8+($D8-$H8)*'4. Compliance'!$F$9+($E8-$I8)*'4. Compliance'!$F$10)/(($C$17-$G$17)*'4. Compliance'!$F$8+($D$17-$H$17)*'4. Compliance'!$F$9+($E$17-$I$17)*'4. Compliance'!$F$10)) -> 0 | M8: BEPU, BEPU-P
A9: Space Heat | C9: =IF('5a. Baseline Rotations'!O12="","",'5a. Baseline Rotations'!O12) -> 0 | D9: =IF('5a. Baseline Rotations'!P12="","",'5a. Baseline Rotations'!P12) -> 3493 | E9: =IF('5a. Baseline Rotations'!Q12="","",'5a. Baseline Rotations'!Q12) -> 0 | F9: =IF(C9="","",(C9*3.412+D9*100+E9)/($C$17*3.412+$D$17*100+$E$17)) -> 0.37056884 | G9: 25217 | H9: 0 | I9: 0 | J9: =IF(G9="","",(G9*3.412+H9*100+I9)/($G$17*3.412+$H$17*100+$I$17)) -> 0.24668134 | K9: =IF(AND(C9="",D9=""),"",((C9-G9)*3.412+(D9-H9)*100+(E9-I9))/(($C$17-$G$17)*3.412+($D$17-$H$17)*100+($E$17-$I$17))) -> 0.44333739 | L9: =IF(AND(C9="",D9=""),"",(($C9-$G9)*'4. Compliance'!$F$8+($D9-$H9)*'4. Compliance'!$F$9+($E9-$I9)*'4. Compliance'!$F$10)/(($C$17-$G$17)*'4. Compliance'!$F$8+($D$17-$H$17)*'4. Compliance'!$F$9+($E$17-$I$17)*'4. Compliance'!$F$10)) -> -0.81083601 | M9: BEPU, BEPU-P
A10: Space Cool | C10: =IF('5a. Baseline Rotations'!O13="","",'5a. Baseline Rotations'!O13) -> 20828 | D10: =IF('5a. Baseline Rotations'!P13="","",'5a. Baseline Rotations'!P13) -> 0 | E10: =IF('5a. Baseline Rotations'!Q13="","",'5a. Baseline Rotations'!Q13) -> 0 | F10: =IF(C10="","",(C10*3.412+D10*100+E10)/($C$17*3.412+$D$17*100+$E$17)) -> 0.075392284 | G10: 6767 | H10: 0 | I10: 0 | J10: =IF(G10="","",(G10*3.412+H10*100+I10)/($G$17*3.412+$H$17*100+$I$17)) -> 0.066197114 | K10: =IF(AND(C10="",D10=""),"",((C10-G10)*3.412+(D10-H10)*100+(E10-I10))/(($C$17-$G$17)*3.412+($D$17-$H$17)*100+($E$17-$I$17))) -> 0.080793307 | L10: =IF(AND(C10="",D10=""),"",(($C10-$G10)*'4. Compliance'!$F$8+($D10-$H10)*'4. Compliance'!$F$9+($E10-$I10)*'4. Compliance'!$F$10)/(($C$17-$G$17)*'4. Compliance'!$F$8+($D$17-$H$17)*'4. Compliance'!$F$9+($E$17-$I$17)*'4. Compliance'!$F$10)) -> 0.45212219 | M10: BEPU, BEPU-P
A11: Heat Rejection | C11: =IF('5a. Baseline Rotations'!O14="","",'5a. Baseline Rotations'!O14) -> 0 | D11: =IF('5a. Baseline Rotations'!P14="","",'5a. Baseline Rotations'!P14) -> 0 | E11: =IF('5a. Baseline Rotations'!Q14="","",'5a. Baseline Rotations'!Q14) -> 0 | F11: =IF(C11="","",(C11*3.412+D11*100+E11)/($C$17*3.412+$D$17*100+$E$17)) -> 0 | G11: 0 | H11: 0 | I11: 0 | J11: =IF(G11="","",(G11*3.412+H11*100+I11)/($G$17*3.412+$H$17*100+$I$17)) -> 0 | K11: =IF(AND(C11="",D11=""),"",((C11-G11)*3.412+(D11-H11)*100+(E11-I11))/(($C$17-$G$17)*3.412+($D$17-$H$17)*100+($E$17-$I$17))) -> 0 | L11: =IF(AND(C11="",D11=""),"",(($C11-$G11)*'4. Compliance'!$F$8+($D11-$H11)*'4. Compliance'!$F$9+($E11-$I11)*'4. Compliance'!$F$10)/(($C$17-$G$17)*'4. Compliance'!$F$8+($D$17-$H$17)*'4. Compliance'!$F$9+($E$17-$I$17)*'4. Compliance'!$F$10)) -> 0 | M11: BEPU, BEPU-P
A12: Pumps & Misc | C12: =IF('5a. Baseline Rotations'!O15="","",'5a. Baseline Rotations'!O15) -> 5433 | D12: =IF('5a. Baseline Rotations'!P15="","",'5a. Baseline Rotations'!P15) -> 0 | E12: =IF('5a. Baseline Rotations'!Q15="","",'5a. Baseline Rotations'!Q15) -> 0 | F12: =IF(C12="","",(C12*3.412+D12*100+E12)/($C$17*3.412+$D$17*100+$E$17)) -> 0.019666136 | G12: 5319 | H12: 0 | I12: 0 | J12: =IF(G12="","",(G12*3.412+H12*100+I12)/($G$17*3.412+$H$17*100+$I$17)) -> 0.052032282 | K12: =IF(AND(C12="",D12=""),"",((C12-G12)*3.412+(D12-H12)*100+(E12-I12))/(($C$17-$G$17)*3.412+($D$17-$H$17)*100+($E$17-$I$17))) -> 0.00065503428 | L12: =IF(AND(C12="",D12=""),"",(($C12-$G12)*'4. Compliance'!$F$8+($D12-$H12)*'4. Compliance'!$F$9+($E12-$I12)*'4. Compliance'!$F$10)/(($C$17-$G$17)*'4. Compliance'!$F$8+($D$17-$H$17)*'4. Compliance'!$F$9+($E$17-$I$17)*'4. Compliance'!$F$10)) -> 0.0036655949 | M12: BEPU, BEPU-P
A13: Vent Fans | C13: =IF('5a. Baseline Rotations'!O16="","",'5a. Baseline Rotations'!O16) -> 73953 | D13: =IF('5a. Baseline Rotations'!P16="","",'5a. Baseline Rotations'!P16) -> 0 | E13: =IF('5a. Baseline Rotations'!Q16="","",'5a. Baseline Rotations'!Q16) -> 0 | F13: =IF(C13="","",(C13*3.412+D13*100+E13)/($C$17*3.412+$D$17*100+$E$17)) -> 0.26769184 | G13: 17675 | H13: 0 | I13: 0 | J13: =IF(G13="","",(G13*3.412+H13*100+I13)/($G$17*3.412+$H$17*100+$I$17)) -> 0.17290291 | K13: =IF(AND(C13="",D13=""),"",((C13-G13)*3.412+(D13-H13)*100+(E13-I13))/(($C$17-$G$17)*3.412+($D$17-$H$17)*100+($E$17-$I$17))) -> 0.32336859 | L13: =IF(AND(C13="",D13=""),"",(($C13-$G13)*'4. Compliance'!$F$8+($D13-$H13)*'4. Compliance'!$F$9+($E13-$I13)*'4. Compliance'!$F$10)/(($C$17-$G$17)*'4. Compliance'!$F$8+($D$17-$H$17)*'4. Compliance'!$F$9+($E$17-$I$17)*'4. Compliance'!$F$10)) -> 1.809582 | M13: BEPU, BEPU-P
A14: Dom. Hot Water | C14: =IF('5a. Baseline Rotations'!O17="","",'5a. Baseline Rotations'!O17) -> 75 | D14: =IF('5a. Baseline Rotations'!P17="","",'5a. Baseline Rotations'!P17) -> 1384 | E14: =IF('5a. Baseline Rotations'!Q17="","",'5a. Baseline Rotations'!Q17) -> 0 | F14: =IF(C14="","",(C14*3.412+D14*100+E14)/($C$17*3.412+$D$17*100+$E$17)) -> 0.14709864 | G14: 40669 | H14: 0 | I14: 0 | J14: =IF(G14="","",(G14*3.412+H14*100+I14)/($G$17*3.412+$H$17*100+$I$17)) -> 0.3978381 | K14: =IF(AND(C14="",D14=""),"",((C14-G14)*3.412+(D14-H14)*100+(E14-I14))/(($C$17-$G$17)*3.412+($D$17-$H$17)*100+($E$17-$I$17))) -> -0.00017973329 | L14: =IF(AND(C14="",D14=""),"",(($C14-$G14)*'4. Compliance'!$F$8+($D14-$H14)*'4. Compliance'!$F$9+($E14-$I14)*'4. Compliance'!$F$10)/(($C$17-$G$17)*'4. Compliance'!$F$8+($D$17-$H$17)*'4. Compliance'!$F$9+($E$17-$I$17)*'4. Compliance'!$F$10)) -> -1.3052733 | M14: BEPU, BEPU-P
A15: Exterior Lighting | C15: =IF('5a. Baseline Rotations'!O18="","",'5a. Baseline Rotations'!O18) -> 278 | D15: =IF('5a. Baseline Rotations'!P18="","",'5a. Baseline Rotations'!P18) -> 0 | E15: =IF('5a. Baseline Rotations'!Q18="","",'5a. Baseline Rotations'!Q18) -> 0 | F15: =IF(C15="","",(C15*3.412+D15*100+E15)/($C$17*3.412+$D$17*100+$E$17)) -> 0.0010062922 | G15: 281 | H15: 0 | I15: 0 | J15: =IF(G15="","",(G15*3.412+H15*100+I15)/($G$17*3.412+$H$17*100+$I$17)) -> 0.0027488383 | K15: =IF(AND(C15="",D15=""),"",((C15-G15)*3.412+(D15-H15)*100+(E15-I15))/(($C$17-$G$17)*3.412+($D$17-$H$17)*100+($E$17-$I$17))) -> -1.7237744e-05 | L15: =IF(AND(C15="",D15=""),"",(($C15-$G15)*'4. Compliance'!$F$8+($D15-$H15)*'4. Compliance'!$F$9+($E15-$I15)*'4. Compliance'!$F$10)/(($C$17-$G$17)*'4. Compliance'!$F$8+($D$17-$H$17)*'4. Compliance'!$F$9+($E$17-$I$17)*'4. Compliance'!$F$10)) -> -9.6463023e-05 | M15: BEPU, BEPU-P
A16: Exterior Misc. | C16: =IF('5a. Baseline Rotations'!O19="","",'5a. Baseline Rotations'!O19) -> 0 | D16: =IF('5a. Baseline Rotations'!P19="","",'5a. Baseline Rotations'!P19) -> 0 | E16: =IF('5a. Baseline Rotations'!Q19="","",'5a. Baseline Rotations'!Q19) -> 0 | F16: =IF(C16="","",(C16*3.412+D16*100+E16)/($C$17*3.412+$D$17*100+$E$17)) -> 0 | G16: 0 | H16: 0 | I16: 0 | J16: =IF(G16="","",(G16*3.412+H16*100+I16)/($G$17*3.412+$H$17*100+$I$17)) -> 0 | K16: =IF(AND(C16="",D16=""),"",((C16-G16)*3.412+(D16-H16)*100+(E16-I16))/(($C$17-$G$17)*3.412+($D$17-$H$17)*100+($E$17-$I$17))) -> 0 | L16: =IF(AND(C16="",D16=""),"",(($C16-$G16)*'4. Compliance'!$F$8+($D16-$H16)*'4. Compliance'!$F$9+($E16-$I16)*'4. Compliance'!$F$10)/(($C$17-$G$17)*'4. Compliance'!$F$8+($D$17-$H$17)*'4. Compliance'!$F$9+($E$17-$I$17)*'4. Compliance'!$F$10)) -> 0 | M16: BEPU, BEPU-P
A17: TOTAL | C17: =IF(SUM(C6:C16)=0,0,SUM(C6:C16)) -> 133325 | D17: =IF(SUM(D6:D16)=0,0,SUM(D6:D16)) -> 4877 | E17: =IF(SUM(E6:E16)=0,0,SUM(E6:E16)) -> 0 | F17: =IF(SUM(F6:F16)=0,0,SUM(F6:F16)) -> 1 | G17: =IF(SUM(G6:G16)=0,0,SUM(G6:G16)) -> 102225 | H17: =IF(SUM(H6:H16)=0,0,SUM(H7:H16)) -> 0 | I17: =IF(SUM(I6:I16)=0,0,SUM(I7:I16)) -> 0 | J17: =SUM(J6:J16) -> 1 | K17: =SUM(K6:K16) -> 1 | L17: =SUM(L6:L16) -> 1 | M17: BEPU, BEPU-P
A19: 5c | B19: Energy Related Design Features
A20: List energy related features in the design that exceed the mandatory/prescriptive requirements under each category. | H20: List energy related features in the design that do not meet the prescriptive requirements under each category.
A22: Opaque Envelope | C22: High-performance insulated roof assembly exceeding minimum NYCECC thermal requirements. Insulated exterior wall assemblies with continuous insulation. | H22: Opaque Envelope
A25: Fenestration & WWR | C25: High-performance triple-pane low-E windows with U-factor and SHGC exceeding prescriptive limits. Window-to-wall ratio maintained below maximum allowable limits. | H25: Fenestration & WWR
A28: Ventilation Systems | C28: Central energy recovery ventilator (ERV) providing heat recovery in excess of prescriptive requirements. | H28: Ventilation Systems
A31: Cooling Systems | C31: High-efficiency air-source heat pump systems exceeding minimum efficiency requirements. | H31: Cooling Systems
A34: Heating Systems | C34: High-efficiency air-source heat pump heating | H34: Heating Systems
C35: with variable-speed operation.
A37: Service Water Heating | C37: All-electric service water heating system with demand-controlled hot water recirculation. | H37: Service Water Heating
A40: Lighting Power | C40: Interior lighting power densities below prescriptive maximums using high-efficiency LED fixtures. Exterior lighting power below prescriptive allowances. | H40: Lighting Power
A43: Lighting Controls | C43: Automatic lighting controls including occupancy sensors and time-based controls in accordance with NYCECC. | H43: Lighting Controls
A46: Other | C46: Fully electric building design reducing fossil fuel use and associated emissions. | H46: Other

Sheet 5a. Description of Project
A3: 5 | B3: Energy Modeling Usage Summary
C4: Baseline Model | F4: Proposed Model
C5: Electric Usage (kwh) | D5: Gas/Steam Usage (Therm) | E5: Other Usage (i.e. chilled water) (indicate units) | F5: Electric Usage (kwh) | G5: Gas/Steam Usage (Therm) | H5: Other Usage (i.e. chilled water) (indicate units) | I5: Energy Savings Per End Use (%) | J5: Cost Savings per End Use (%) | K5: Model Output Location (Report)
A6: Interior Lighting | C6: 1745801.2 | D6: 0 | E6: 0 | F6: 1556051 | I6: =IF(AND(C6="",D6=""),"",((C6-F6)*0.0341214+(D6-G6))/(($C$16-$F$16)*0.0341214+($D$16-$G$16))) -> 0.17052566 | J6: =IF(AND(C6="",D6=""),"",(($C6-$F6)*'4. Compliance'!$F$8+($D6-$G6)*'4. Compliance'!$F$9)/(($C$16-$F$16)*'4. Compliance'!$F$8+($D$16-$G$16)*'4. Compliance'!$F$9)) -> 0.24092983 | K6: BEPU
A7: Misc. Equip. | C7: 1392190 | D7: 0 | E7: 0 | F7: 1392190 | I7: =IF(AND(C7="",D7=""),"",((C7-F7)*0.00341214+(D7-G7)*0.1)/(($C$16-$F$16)*0.00341214+($D$16-$G$16)*0.1)) -> 0 | J7: =IF(AND(C7="",D7=""),"",(($C7-$F7)*'4. Compliance'!$F$8+($D7-$G7)*'4. Compliance'!$F$9)/(($C$16-$F$16)*'4. Compliance'!$F$8+($D$16-$G$16)*'4. Compliance'!$F$9)) -> 0 | K7: BEPU
A8: Space Heat | C8: 531458.5 | D8: 109038 | E8: 0 | F8: 368529 | G8: 126064 | I8: =IF(AND(C8="",D8=""),"",((C8-F8)*0.0341214+(D8-G8))/(($C$16-$F$16)*0.0341214+($D$16-$G$16))) -> -0.30200619 | J8: =IF(AND(C8="",D8=""),"",(($C8-$F8)*'4. Compliance'!$F$8+($D8-$G8)*'4. Compliance'!$F$9)/(($C$16-$F$16)*'4. Compliance'!$F$8+($D$16-$G$16)*'4. Compliance'!$F$9)) -> 0.20687497 | K8: BEPU
A9: Space Cool | C9: 1303419.2 | D9: 0 | E9: 0 | F9: 1113250 | I9: =IF(AND(C9="",D9=""),"",((C9-F9)*0.0341214+(D9-G9))/(($C$16-$F$16)*0.0341214+($D$16-$G$16))) -> 0.1709022 | J9: =IF(AND(C9="",D9=""),"",(($C9-$F9)*'4. Compliance'!$F$8+($D9-$G9)*'4. Compliance'!$F$9)/(($C$16-$F$16)*'4. Compliance'!$F$8+($D$16-$G$16)*'4. Compliance'!$F$9)) -> 0.24146184 | K9: BEPU
A10: Heat Rejection | C10: 35071.5 | D10: 0 | E10: 0 | F10: 8053 | I10: =IF(AND(C10="",D10=""),"",((C10-F10)*0.0341214+(D10-G10))/(($C$16-$F$16)*0.0341214+($D$16-$G$16))) -> 0.024281114 | J10: =IF(AND(C10="",D10=""),"",(($C10-$F10)*'4. Compliance'!$F$8+($D10-$G10)*'4. Compliance'!$F$9)/(($C$16-$F$16)*'4. Compliance'!$F$8+($D$16-$G$16)*'4. Compliance'!$F$9)) -> 0.03430595 | K10: BEPU
A11: Pumps & Misc | C11: 757739 | D11: 0 | E11: 0 | F11: 510815 | I11: =IF(AND(C11="",D11=""),"",((C11-F11)*0.0341214+(D11-G11))/(($C$16-$F$16)*0.0341214+($D$16-$G$16))) -> 0.22190683 | J11: =IF(AND(C11="",D11=""),"",(($C11-$F11)*'4. Compliance'!$F$8+($D11-$G11)*'4. Compliance'!$F$9)/(($C$16-$F$16)*'4. Compliance'!$F$8+($D$16-$G$16)*'4. Compliance'!$F$9)) -> 0.31352453 | K11: BEPU
A12: Vent Fans | C12: 1224198.2 | D12: 0 | E12: 0 | F12: 1262322 | I12: =IF(AND(C12="",D12=""),"",((C12-F12)*0.0341214+(D12-G12))/(($C$16-$F$16)*0.0341214+($D$16-$G$16))) -> -0.034261233 | J12: =IF(AND(C12="",D12=""),"",(($C12-$F12)*'4. Compliance'!$F$8+($D12-$G12)*'4. Compliance'!$F$9)/(($C$16-$F$16)*'4. Compliance'!$F$8+($D$16-$G$16)*'4. Compliance'!$F$9)) -> -0.048406516 | K12: BEPU
A13: Dom. Hot Water | C13: 0 | D13: 214343 | E13: 0 | G13: 186222 | I13: =IF(AND(C13="",D13=""),"",((C13-F13)*0.0341214+(D13-G13))/(($C$16-$F$16)*0.0341214+($D$16-$G$16))) -> 0.74064703 | J13: =IF(AND(C13="",D13=""),"",(($C13-$F13)*'4. Compliance'!$F$8+($D13-$G13)*'4. Compliance'!$F$9)/(($C$16-$F$16)*'4. Compliance'!$F$8+($D$16-$G$16)*'4. Compliance'!$F$9)) -> 0 | K13: BEPU
A14: Exterior Lighting | C14: 33575 | D14: 0 | E14: 0 | F14: 24668 | I14: =IF(AND(C14="",D14=""),"",((C14-F14)*0.0341214+(D14-G14))/(($C$16-$F$16)*0.0341214+($D$16-$G$16))) -> 0.008004585 | J14: =IF(AND(C14="",D14=""),"",(($C14-$F14)*'4. Compliance'!$F$8+($D14-$G14)*'4. Compliance'!$F$9)/(($C$16-$F$16)*'4. Compliance'!$F$8+($D$16-$G$16)*'4. Compliance'!$F$9)) -> 0.011309403 | K14: BEPU
A15: Exterior Misc. | C15: 0 | D15: 0 | E15: 0 | F15: 0 | G15: 0 | I15: =IF(AND(C15="",D15=""),"",((C15-F15)*0.0341214+(D15-G15))/(($C$16-$F$16)*0.0341214+($D$16-$G$16))) -> 0 | J15: =IF(AND(C15="",D15=""),"",(($C15-$F15)*'4. Compliance'!$F$8+($D15-$G15)*'4. Compliance'!$F$9)/(($C$16-$F$16)*'4. Compliance'!$F$8+($D$16-$G$16)*'4. Compliance'!$F$9)) -> 0 | K15: BEPU
A16: TOTAL | C16: =IF(SUM(C6:C15)=0,"",SUM(C6:C15)) -> 7023452.8 | D16: =IF(SUM(D6:D15)=0,"",SUM(D6:D15)) -> 323381 | E16: =IF(SUM(E6:E15)=0,"",SUM(E6:E15)) | F16: =IF(SUM(F6:F15)=0,"",SUM(F6:F15)) -> 6235878 | G16: =IF(SUM(G7:G15)=0,"",SUM(G7:G15)) -> 312286 | H16: =IF(SUM(H6:H15)=0,"",SUM(H6:H15)) | I16: =IF(AND(C16="",D16=""),"",((C16-F16)*0.0341214+(D16-G16))/(($C$16-$F$16)*0.0341214+($D$16-$G$16))) -> 1 | J16: =IF(AND(C16="",D16=""),"",(($C16-$F16)*'4. Compliance'!$F$8+($D16-$G16)*'4. Compliance'!$F$9)/(($C$16-$F$16)*'4. Compliance'!$F$8+($D$16-$G$16)*'4. Compliance'!$F$9)) -> 1
G17: =IF(J17="","",IF(J17='4. Compliance'!E12-'4. Compliance'!G12,"Aligns with Section 4","Does Not Align with Section 4")) -> Does Not Align with Section 4 | J17: =($C$16-$F$16)*'4. Compliance'!$F$8+($D$16-$G$16)*'4. Compliance'!$F$9 -> 196893.69
A19: 5a | B19: Energy Related Design Features
A20: List energy related features that are included in the design and contribute to the energy savings in Section 5.

Sheet 6a. Ext. Wall Areas
A3: 6a | B3: Above-Grade Wall & Fenestration Areas
A4: =CONCATENATE("Compliance based on ",IF(Path="","",Path)) -> Compliance based on Appendix G PRM
E5: Baseline Case | H5: Proposed Case | K5: Supporting Doc. Location | L5: Model Output Report
E6: Other
A7: Above-Grade Wall & Vertical Glazing Area by Orientation | C7: Orientation | E7: Window + Wall Area (ft2) | F7: Vertical Glazing Area | H7: Window + Wall Area (ft2) | I7: Vertical Glazing Area
F8: (ft2) | G8: (%) | I8: (ft2) | J8: (%)
C9: North | E9: 1800.479 | F9: 667.147 | G9: =IF(AND(E9="",F9=""),"",F9/E9*100) -> 37.053862 | H9: 1800.479 | I9: 1078.436 | J9: =IF(AND(H9="",I9=""),"",I9/H9*100) -> 59.897172 | K9: EN-006 | L9: ERV, ERV-W
C10: East | E10: 3209.583 | F10: 22.712 | G10: =IF(AND(E10="",F10=""),"",F10/E10*100) -> 0.70763087 | H10: 3209.583 | I10: 48.653 | J10: =IF(AND(H10="",I10=""),"",I10/H10*100) -> 1.5158667 | K10: EN-006 | L10: ERV, ERV-W
C11: South | E11: 1821.899 | F11: 784.151 | G11: =IF(AND(E11="",F11=""),"",F11/E11*100) -> 43.040311 | H11: 1821.899 | I11: 1053.464 | J11: =IF(AND(H11="",I11=""),"",I11/H11*100) -> 57.822305 | K11: EN-006 | L11: ERV, ERV-W
C12: West | E12: 3466.517 | F12: 35.951 | G12: =IF(AND(E12="",F12=""),"",F12/E12*100) -> 1.0370929 | H12: 3466.517 | I12: 81.59 | J12: =IF(AND(H12="",I12=""),"",I12/H12*100) -> 2.3536593 | K12: EN-006 | L12: ERV, ERV-W
C13: Total | E13: =IF(SUM(E9:E12)=0,"",SUM(E9:E12)) -> 10298.478 | F13: =IF(SUM(F9:F12)=0,"",SUM(F9:F12)) -> 1509.961 | G13: =IF(AND(E13="",F13=""),"",F13/E13*100) -> 14.661982 | H13: =IF(SUM(H9:H12)=0,"",SUM(H9:H12)) -> 10298.478 | I13: =IF(SUM(I9:I12)=0,"",SUM(I9:I12)) -> 2262.143 | J13: =IF(AND(H13="",I13=""),"",I13/H13*100) -> 21.965799 | K13: EN-006 | L13: ERV, ERV-W
A14: Roof & Skylight Area | C14: Roof + Skylight Area (ft2) | F14: Skylight Area | H14: Roof + Skylight Area (ft2) | I14: Skylight Area | K14: Supporting Doc. Location | L14: Model Output Report
F15: (ft2) | G15: (%) | I15: (ft2) | J15: (%)
C16: Total | E16: 2126.303 | F16: 0 | G16: =IF(AND(E16="",F16=""),"",F16/E16*100) -> 0 | H16: 2126.303 | I16: 0 | J16: =IF(AND(H16="",I16=""),"",I16/H16*100) -> 0 | K16: EN-007 | L16: SV-A, SV-A-P

Sheet 6b. Fenestration
A3: 6b | B3: Vertical Fenestration
A4: =CONCATENATE("Compliance based on ",IF(Path="","",Path)) -> Compliance based on Appendix G PRM
A5: Model Input Parameter | C5: Category (Res/Non-Res) | E5: Baseline Case | I5: Proposed Case | N5: Supporting Doc. Location | O5: Model Output Report
D6: Item # | E6: Description (from ASHRAE) | F6: U-factor | G6: SHGC | H6: VLT | I6: Description (from design) | J6: U-factor | K6: SHGC | L6: VLT | M6: % Overall Wall/Roof Area
A7: Vertical | C7: Residential | D7: 1 | E7: Metal framing (fixed), below 95ft | F7: {=IF(C7="","",IF(E7="","",IF('4. Compliance'!$B$4="Section 11 ECB",INDEX(Lists!$A$4:$D$11,(MATCH($E7,Lists!$A$4:$A$11,0)),(MATCH($C7,Lists!$A$4:$D$4,0))),INDEX(Lists!$F$4:$I$11,(MATCH($E7,Lists!$F$4:$F$11,0)),(MATCH($C7,Lists!$F$4:$I$4,0))))))} -> U-0.57 | G7: {=IF(C7="","",IF(E7="","",IF('4. Compliance'!$B$4="Section 11 ECB",INDEX(Lists!$A$13:$D$20,(MATCH($E7,Lists!$A$13:$A$20,0)),(MATCH($C7,Lists!$A$13:$D$13,0))),INDEX(Lists!$F$13:$I$20,(MATCH($E7,Lists!$F$13:$F$20,0)),(MATCH($C7,Lists!$F$13:$I$13,0))))))} -> 0.39 | H7: =IF(L7="","",L7) -> 0.452 | I7: Triple Pane Low-E (A-400) | J7: 0.3 | K7: 0.3 | L7: 0.452 | M7: 0.21965799 | N7: A-400.00 | O7: ERV, ERV-W
A8: Vertical | D8: 2 | F8: {=IF(C8="","",IF(E8="","",IF('4. Compliance'!$B$4="Section 11 ECB",INDEX(Lists!$A$4:$D$11,(MATCH($E8,Lists!$A$4:$A$11,0)),(MATCH($C8,Lists!$A$4:$D$4,0))),INDEX(Lists!$F$4:$I$11,(MATCH($E8,Lists!$F$4:$F$11,0)),(MATCH($C8,Lists!$F$4:$I$4,0))))))} | G8: {=IF(C8="","",IF(E8="","",IF('4. Compliance'!$B$4="Section 11 ECB",INDEX(Lists!$A$13:$D$20,(MATCH($E8,Lists!$A$13:$A$20,0)),(MATCH($C8,Lists!$A$13:$D$13,0))),INDEX(Lists!$F$13:$I$20,(MATCH($E8,Lists!$F$13:$F$20,0)),(MATCH($C8,Lists!$F$13:$I$13,0))))))} | H8: =IF(L8="","",L8)
A9: Vertical | D9: 3 | F9: {=IF(C9="","",IF(E9="","",IF('4. Compliance'!$B$4="Section 11 ECB",INDEX(Lists!$A$4:$D$11,(MATCH($E9,Lists!$A$4:$A$11,0)),(MATCH($C9,Lists!$A$4:$D$4,0))),INDEX(Lists!$F$4:$I$11,(MATCH($E9,Lists!$F$4:$F$11,0)),(MATCH($C9,Lists!$F$4:$I$4,0))))))} | G9: {=IF(C9="","",IF(E9="","",IF('4. Compliance'!$B$4="Section 11 ECB",INDEX(Lists!$A$13:$D$20,(MATCH($E9,Lists!$A$13:$A$20,0)),(MATCH($C9,Lists!$A$13:$D$13,0))),INDEX(Lists!$F$13:$I$20,(MATCH($E9,Lists!$F$13:$F$20,0)),(MATCH($C9,Lists!$F$13:$I$13,0))))))} | H9: =IF(L9="","",L9)
A10: Vertical | D10: 4 | F10: {=IF(C10="","",IF(E10="","",IF('4. Compliance'!$B$4="Section 11 ECB",INDEX(Lists!$A$4:$D$11,(MATCH($E10,Lists!$A$4:$A$11,0)),(MATCH($C10,Lists!$A$4:$D$4,0))),INDEX(Lists!$F$4:$I$11,(MATCH($E10,Lists!$F$4:$F$11,0)),(MATCH($C10,Lists!$F$4:$I$4,0))))))} | G10: {=IF(C10="","",IF(E10="","",IF('4. Compliance'!$B$4="Section 11 ECB",INDEX(Lists!$A$13:$D$20,(MATCH($E10,Lists!$A$13:$A$20,0)),(MATCH($C10,Lists!$A$13:$D$13,0))),INDEX(Lists!$F$13:$I$20,(MATCH($E10,Lists!$F$13:$F$20,0)),(MATCH($C10,Lists!$F$13:$I$13,0))))))} | H10: =IF(L10="","",L10)
A11: Vertical | D11: 5 | F11: {=IF(C11="","",IF(E11="","",IF('4. Compliance'!$B$4="Section 11 ECB",INDEX(Lists!$A$4:$D$11,(MATCH($E11,Lists!$A$4:$A$11,0)),(MATCH($C11,Lists!$A$4:$D$4,0))),INDEX(Lists!$F$4:$I$11,(MATCH($E11,Lists!$F$4:$F$11,0)),(MATCH($C11,Lists!$F$4:$I$4,0))))))} | G11: {=IF(C11="","",IF(E11="","",IF('4. Compliance'!$B$4="Section 11 ECB",INDEX(Lists!$A$13:$D$20,(MATCH($E11,Lists!$A$13:$A$20,0)),(MATCH($C11,Lists!$A$13:$D$13,0))),INDEX(Lists!$F$13:$I$20,(MATCH($E11,Lists!$F$13:$F$20,0)),(MATCH($C11,Lists!$F$13:$I$13,0))))))} | H11: =IF(L11="","",L11)
A12: Vertical | D12: 6 | F12: {=IF(C12="","",IF(E12="","",IF('4. Compliance'!$B$4="Section 11 ECB",INDEX(Lists!$A$4:$D$11,(MATCH($E12,Lists!$A$4:$A$11,0)),(MATCH($C12,Lists!$A$4:$D$4,0))),INDEX(Lists!$F$4:$I$11,(MATCH($E12,Lists!$F$4:$F$11,0)),(MATCH($C12,Lists!$F$4:$I$4,0))))))} | G12: {=IF(C12="","",IF(E12="","",IF('4. Compliance'!$B$4="Section 11 ECB",INDEX(Lists!$A$13:$D$20,(MATCH($E12,Lists!$A$13:$A$20,0)),(MATCH($C12,Lists!$A$13:$D$13,0))),INDEX(Lists!$F$13:$I$20,(MATCH($E12,Lists!$F$13:$F$20,0)),(MATCH($C12,Lists!$F$13:$I$13,0))))))} | H12: =IF(L12="","",L12)
A13: Vertical | D13: 7 | F13: {=IF(C13="","",IF(E13="","",IF('4. Compliance'!$B$4="Section 11 ECB",INDEX(Lists!$A$4:$D$11,(MATCH($E13,Lists!$A$4:$A$11,0)),(MATCH($C13,Lists!$A$4:$D$4,0))),INDEX(Lists!$F$4:$I$11,(MATCH($E13,Lists!$F$4:$F$11,0)),(MATCH($C13,Lists!$F$4:$I$4,0))))))} | G13: {=IF(C13="","",IF(E13="","",IF('4. Compliance'!$B$4="Section 11 ECB",INDEX(Lists!$A$13:$D$20,(MATCH($E13,Lists!$A$13:$A$20,0)),(MATCH($C13,Lists!$A$13:$D$13,0))),INDEX(Lists!$F$13:$I$20,(MATCH($E13,Lists!$F$13:$F$20,0)),(MATCH($C13,Lists!$F$13:$I$13,0))))))} | H13: =IF(L13="","",L13)
A14: Vertical | D14: 8 | F14: {=IF(C14="","",IF(E14="","",IF('4. Compliance'!$B$4="Section 11 ECB",INDEX(Lists!$A$4:$D$11,(MATCH($E14,Lists!$A$4:$A$11,0)),(MATCH($C14,Lists!$A$4:$D$4,0))),INDEX(Lists!$F$4:$I$11,(MATCH($E14,Lists!$F$4:$F$11,0)),(MATCH($C14,Lists!$F$4:$I$4,0))))))} | G14: {=IF(C14="","",IF(E14="","",IF('4. Compliance'!$B$4="Section 11 ECB",INDEX(Lists!$A$13:$D$20,(MATCH($E14,Lists!$A$13:$A$20,0)),(MATCH($C14,Lists!$A$13:$D$13,0))),INDEX(Lists!$F$13:$I$20,(MATCH($E14,Lists!$F$13:$F$20,0)),(MATCH($C14,Lists!$F$13:$I$13,0))))))} | H14: =IF(L14="","",L14)
A15: Vertical | D15: 9 | F15: {=IF(C15="","",IF(E15="","",IF('4. Compliance'!$B$4="Section 11 ECB",INDEX(Lists!$A$4:$D$11,(MATCH($E15,Lists!$A$4:$A$11,0)),(MATCH($C15,Lists!$A$4:$D$4,0))),INDEX(Lists!$F$4:$I$11,(MATCH($E15,Lists!$F$4:$F$11,0)),(MATCH($C15,Lists!$F$4:$I$4,0))))))} | G15: {=IF(C15="","",IF(E15="","",IF('4. Compliance'!$B$4="Section 11 ECB",INDEX(Lists!$A$13:$D$20,(MATCH($E15,Lists!$A$13:$A$20,0)),(MATCH($C15,Lists!$A$13:$D$13,0))),INDEX(Lists!$F$13:$I$20,(MATCH($E15,Lists!$F$13:$F$20,0)),(MATCH($C15,Lists!$F$13:$I$13,0))))))} | H15: =IF(L15="","",L15)
A16: Vertical | D16: 10 | F16: {=IF(C16="","",IF(E16="","",IF('4. Compliance'!$B$4="Section 11 ECB",INDEX(Lists!$A$4:$D$11,(MATCH($E16,Lists!$A$4:$A$11,0)),(MATCH($C16,Lists!$A$4:$D$4,0))),INDEX(Lists!$F$4:$I$11,(MATCH($E16,Lists!$F$4:$F$11,0)),(MATCH($C16,Lists!$F$4:$I$4,0))))))} | G16: {=IF(C16="","",IF(E16="","",IF('4. Compliance'!$B$4="Section 11 ECB",INDEX(Lists!$A$13:$D$20,(MATCH($E16,Lists!$A$13:$A$20,0)),(MATCH($C16,Lists!$A$13:$D$13,0))),INDEX(Lists!$F$13:$I$20,(MATCH($E16,Lists!$F$13:$F$20,0)),(MATCH($C16,Lists!$F$13:$I$13,0))))))} | H16: =IF(L16="","",L16)
A17: Vertical | D17: 11 | F17: {=IF(C17="","",IF(E17="","",IF('4. Compliance'!$B$4="Section 11 ECB",INDEX(Lists!$A$4:$D$11,(MATCH($E17,Lists!$A$4:$A$11,0)),(MATCH($C17,Lists!$A$4:$D$4,0))),INDEX(Lists!$F$4:$I$11,(MATCH($E17,Lists!$F$4:$F$11,0)),(MATCH($C17,Lists!$F$4:$I$4,0))))))} | G17: {=IF(C17="","",IF(E17="","",IF('4. Compliance'!$B$4="Section 11 ECB",INDEX(Lists!$A$13:$D$20,(MATCH($E17,Lists!$A$13:$A$20,0)),(MATCH($C17,Lists!$A$13:$D$13,0))),INDEX(Lists!$F$13:$I$20,(MATCH($E17,Lists!$F$13:$F$20,0)),(MATCH($C17,Lists!$F$13:$I$13,0))))))} | H17: =IF(L17="","",L17)
A18: Vertical | D18: 12 | F18: {=IF(C18="","",IF(E18="","",IF('4. Compliance'!$B$4="Section 11 ECB",INDEX(Lists!$A$4:$D$11,(MATCH($E18,Lists!$A$4:$A$11,0)),(MATCH($C18,Lists!$A$4:$D$4,0))),INDEX(Lists!$F$4:$I$11,(MATCH($E18,Lists!$F$4:$F$11,0)),(MATCH($C18,Lists!$F$4:$I$4,0))))))} | G18: {=IF(C18="","",IF(E18="","",IF('4. Compliance'!$B$4="Section 11 ECB",INDEX(Lists!$A$13:$D$20,(MATCH($E18,Lists!$A$13:$A$20,0)),(MATCH($C18,Lists!$A$13:$D$13,0))),INDEX(Lists!$F$13:$I$20,(MATCH($E18,Lists!$F$13:$F$20,0)),(MATCH($C18,Lists!$F$13:$I$13,0))))))} | H18: =IF(L18="","",L18)
A19: Skylight | D19: 1 | F19: {=IF(C19="","",IF(E19="","",IF('4. Compliance'!$B$4="Section 11 ECB",INDEX(Lists!$A$22:$D$24,(MATCH($E19,Lists!$A$22:$A$24,0)),(MATCH($C19,Lists!$A$22:$D$22,0))),INDEX(Lists!$F$22:$I$24,(MATCH($E19,Lists!$F$22:$F$24,0)),(MATCH($C19,Lists!$F$22:$I$22,0))))))} | G19: {=IF(C19="","",IF(E19="","",IF('4. Compliance'!$B$4="Section 11 ECB",INDEX(Lists!$A$26:$D$28,(MATCH($E19,Lists!$A$26:$A$28,0)),(MATCH($C19,Lists!$A$26:$D$26,0))),INDEX(Lists!$F$26:$I$28,(MATCH($E19,Lists!$F$26:$F$28,0)),(MATCH($C19,Lists!$F$26:$I$26,0))))))} | H19: =IF(L19="","",L19)
A20: Skylight | D20: 2 | F20: {=IF(C20="","",IF(E20="","",IF('4. Compliance'!$B$4="Section 11 ECB",INDEX(Lists!$A$22:$D$24,(MATCH($E20,Lists!$A$22:$A$24,0)),(MATCH($C20,Lists!$A$22:$D$22,0))),INDEX(Lists!$F$22:$I$24,(MATCH($E20,Lists!$F$22:$F$24,0)),(MATCH($C20,Lists!$F$22:$I$22,0))))))} | G20: {=IF(C20="","",IF(E20="","",IF('4. Compliance'!$B$4="Section 11 ECB",INDEX(Lists!$A$26:$D$28,(MATCH($E20,Lists!$A$26:$A$28,0)),(MATCH($C20,Lists!$A$26:$D$26,0))),INDEX(Lists!$F$26:$I$28,(MATCH($E20,Lists!$F$26:$F$28,0)),(MATCH($C20,Lists!$F$26:$I$26,0))))))} | H20: =IF(L20="","",L20)
A21: Shading Devices | D21: Shading projections, manual shading devices, or self-shading have been modeled. | I21: List any permanent or auto-controlled shading devices: | L21: Total % WWR | M21: =IF(M7="","",IF(AND('6a. Ext. Wall Areas'!J13/100<(SUM(M7:M18)+SUM(M7:M18)*0.01),'6a. Ext. Wall Areas'!J13/100>(SUM(M7:M18)-SUM(M7:M18)*0.01)),SUM(M7:M18),"WWR does not equal tab 6a.")) -> 0.21965799
D22: Any shading by adjacent structures has been modeled identically to the proposed case. | L22: Total % skylt | M22: =IF(M19="","",IF(AND('6a. Ext. Wall Areas'!J16/100<(SUM(M19:M20)+SUM(M19:M20)*0.01),'6a. Ext. Wall Areas'!J16/100>(SUM(M19:M20)-SUM(M19:M20)*0.01)),SUM(M19:M20),"WWR does not equal tab 6a."))

Sheet 6c1. Wall Types
A2: 6c | B2: Opaque Elements
A3: =CONCATENATE("Compliance based on ",IF(Path="","",Path)) -> Compliance based on Appendix G PRM
A4: Model Input Parameter | B4: Space-Conditioning Category | C4: Item # | D4: Baseline Case | F4: Proposed Case | I4: Supporting Doc Location | J4: Model Output Report
D5: Description | E5: U-factor/ C-factor/ F-factor | F5: Description | G5: Assembly U-factor/ C-factor/ F-factor | H5: % of above-grade wall
A6: Roof Construction | B6: Residential | C6: 1 | D6: Insulation Entirely Above Deck | E6: {=IF(B6="","",IF(D6="","",IF('4. Compliance'!$B$4="Section 11 ECB",INDEX(Lists!$A$30:$D$33,(MATCH($D6,Lists!$A$30:$A$33,0)),(MATCH($B6,Lists!$A$30:$D$30,0))),INDEX(Lists!$F$30:$I$33,(MATCH($D6,Lists!$F$30:$F$33,0)),(MATCH($B6,Lists!$F$30:$I$30,0))))))} -> U-0.063 | F6: Roof assembly (TPO + 6" spray foam + 3" GPS rigid) | G6: 0.024 | H6: 100 | I6: A-500 | J6: ERV, ERV-W
D7: Solar Reflectance | E7: SR =
C8: 2 | E8: {=IF(B8="","",IF(D8="","",IF('4. Compliance'!$B$4="Section 11 ECB",INDEX(Lists!$A$30:$D$33,(MATCH($D8,Lists!$A$30:$A$33,0)),(MATCH($B8,Lists!$A$30:$D$30,0))),INDEX(Lists!$F$30:$I$33,(MATCH($D8,Lists!$F$30:$F$33,0)),(MATCH($B8,Lists!$F$30:$I$30,0))))))}
D9: Solar Reflectance | E9: SR =
A10: Above-Grade Exterior Wall Construction (Values on this tab should align with modeled inputs. For additional rows, use tab 6c2) | B10: Residential | C10: 1 | D10: Steel-Framed | E10: {=IF(B10="","",IF(D10="","",IF('4. Compliance'!$B$4="Section 11 ECB",INDEX(Lists!$A$34:$D$38,(MATCH($D10,Lists!$A$34:$A$38,0)),(MATCH($B10,Lists!$A$34:$D$34,0))),INDEX(Lists!$F$34:$I$38,(MATCH($D10,Lists!$F$34:$F$38,0)),(MATCH($B10,Lists!$F$34:$I$34,0))))))} -> U-0.064 | F10: Ext wall (brick veneer + EIFS R-8 + spray foam) | G10: 0.047 | H10: 0.78034201 | I10: A-500 | J10: ERV, ERV-W
C11: 2 | E11: {=IF(B11="","",IF(D11="","",IF('4. Compliance'!$B$4="Section 11 ECB",INDEX(Lists!$A$34:$D$38,(MATCH($D11,Lists!$A$34:$A$38,0)),(MATCH($B11,Lists!$A$34:$D$34,0))),INDEX(Lists!$F$34:$I$38,(MATCH($D11,Lists!$F$34:$F$38,0)),(MATCH($B11,Lists!$F$34:$I$34,0))))))}
C12: 3 | E12: {=IF(B12="","",IF(D12="","",IF('4. Compliance'!$B$4="Section 11 ECB",INDEX(Lists!$A$34:$D$38,(MATCH($D12,Lists!$A$34:$A$38,0)),(MATCH($B12,Lists!$A$34:$D$34,0))),INDEX(Lists!$F$34:$I$38,(MATCH($D12,Lists!$F$34:$F$38,0)),(MATCH($B12,Lists!$F$34:$I$34,0))))))}
C13: 4 | E13: {=IF(B13="","",IF(D13="","",IF('4. Compliance'!$B$4="Section 11 ECB",INDEX(Lists!$A$34:$D$38,(MATCH($D13,Lists!$A$34:$A$38,0)),(MATCH($B13,Lists!$A$34:$D$34,0))),INDEX(Lists!$F$34:$I$38,(MATCH($D13,Lists!$F$34:$F$38,0)),(MATCH($B13,Lists!$F$34:$I$34,0))))))}
C14: 5 | E14: {=IF(B14="","",IF(D14="","",IF('4. Compliance'!$B$4="Section 11 ECB",INDEX(Lists!$A$34:$D$38,(MATCH($D14,Lists!$A$34:$A$38,0)),(MATCH($B14,Lists!$A$34:$D$34,0))),INDEX(Lists!$F$34:$I$38,(MATCH($D14,Lists!$F$34:$F$38,0)),(MATCH($B14,Lists!$F$34:$I$34,0))))))}
C15: 6
C16: 7
C17: 8 | E17: {=IF(B17="","",IF(D17="","",IF('4. Compliance'!$B$4="Section 11 ECB",INDEX(Lists!$A$34:$D$38,(MATCH($D17,Lists!$A$34:$A$38,0)),(MATCH($B17,Lists!$A$34:$D$34,0))),INDEX(Lists!$F$34:$I$38,(MATCH($D17,Lists!$F$34:$F$38,0)),(MATCH($B17,Lists!$F$34:$I$34,0))))))}
C18: 9 | E18: {=IF(B18="","",IF(D18="","",IF('4. Compliance'!$B$4="Section 11 ECB",INDEX(Lists!$A$34:$D$38,(MATCH($D18,Lists!$A$34:$A$38,0)),(MATCH($B18,Lists!$A$34:$D$34,0))),INDEX(Lists!$F$34:$I$38,(MATCH($D18,Lists!$F$34:$F$38,0)),(MATCH($B18,Lists!$F$34:$I$34,0))))))}
C19: 10 | E19: {=IF(B19="","",IF(D19="","",IF('4. Compliance'!$B$4="Section 11 ECB",INDEX(Lists!$A$34:$D$38,(MATCH($D19,Lists!$A$34:$A$38,0)),(MATCH($B19,Lists!$A$34:$D$34,0))),INDEX(Lists!$F$34:$I$38,(MATCH($D19,Lists!$F$34:$F$38,0)),(MATCH($B19,Lists!$F$34:$I$34,0))))))}
A20: Below-Grade Exterior Wall Construction | B20: Semiheated | C20: 1 | D20: Below-Grade Wall | E20: {=IF(B20="","",IF(D20="","",IF('4. Compliance'!$B$4="Section 11 ECB",INDEX(Lists!$A$39:$D$40,(MATCH($D20,Lists!$A$39:$A$40,0)),(MATCH($B20,Lists!$A$39:$D$39,0))),INDEX(Lists!$F$39:$I$40,(MATCH($D20,Lists!$F$39:$F$40,0)),(MATCH($B20,Lists!$F$39:$I$39,0))))))} -> C-1.140 | F20: Below-grade concrete wall with continuous rigid insulation | G20: 0.048 | H20: 100 | I20: A-500 | J20: ERV, ERV-W
C21: 2 | E21: {=IF(B21="","",IF(D21="","",IF('4. Compliance'!$B$4="Section 11 ECB",INDEX(Lists!$A$39:$D$40,(MATCH($D21,Lists!$A$39:$A$40,0)),(MATCH($B21,Lists!$A$39:$D$39,0))),INDEX(Lists!$F$39:$I$40,(MATCH($D21,Lists!$F$39:$F$40,0)),(MATCH($B21,Lists!$F$39:$I$39,0))))))}
A22: Exposed Floor Construction | C22: 1 | E22: {=IF(B22="","",IF(D22="","",IF('4. Compliance'!$B$4="Section 11 ECB",INDEX(Lists!$A$41:$D$44,(MATCH($D22,Lists!$A$41:$A$44,0)),(MATCH($B22,Lists!$A$41:$D$41,0))),INDEX(Lists!$F$41:$I$44,(MATCH($D22,Lists!$F$41:$F$44,0)),(MATCH($B22,Lists!$F$41:$I$41,0))))))}
A23: Slab-On-Grade Floors | B23: Residential | C23: 1 | D23: Unheated | E23: {=IF(B23="","",IF(D23="","",IF('4. Compliance'!$B$4="Section 11 ECB",INDEX(Lists!$A$45:$D$47,(MATCH($D23,Lists!$A$45:$A$47,0)),(MATCH($B23,Lists!$A$45:$D$45,0))),INDEX(Lists!$F$45:$I$47,(MATCH($D23,Lists!$F$45:$F$47,0)),(MATCH($B23,Lists!$F$45:$I$45,0))))))} -> F-0.730 | F23: Slab on grade (unheated) | G23: 0.73 | H23: 100 | I23: A-500 | J23: ERV, ERV-W
A24: Opaque Doors | B24: Residential | C24: 1 | D24: Swinging | E24: {=IF(B24="","",IF(D24="","",IF('4. Compliance'!$B$4="Section 11 ECB",INDEX(Lists!$A$48:$D$50,(MATCH($D24,Lists!$A$48:$A$50,0)),(MATCH($B24,Lists!$A$48:$D$48,0))),INDEX(Lists!$F$48:$I$50,(MATCH($D24,Lists!$F$48:$F$50,0)),(MATCH($B24,Lists!$F$48:$I$48,0))))))} -> U-0.700 | F24: Exterior doors (U=0.30, SHGC=0.30) per A-400 | G24: 0.3 | H24: 1 | I24: A-500 | J24: ERV, ERV-W
C25: 2 | E25: {=IF(B25="","",IF(D25="","",IF('4. Compliance'!$B$4="Section 11 ECB",INDEX(Lists!$A$48:$D$50,(MATCH($D25,Lists!$A$48:$A$50,0)),(MATCH($B25,Lists!$A$48:$D$48,0))),INDEX(Lists!$F$48:$I$50,(MATCH($D25,Lists!$F$48:$F$50,0)),(MATCH($B25,Lists!$F$48:$I$48,0))))))}
G26: Total % Opaque Wall | H26: =IF(H10="","",IF(AND(((100-'6a. Ext. Wall Areas'!J13)/100)<(SUM(H10:H19)+SUM(H10:H19)*0.01),((100-'6a. Ext. Wall Areas'!J13)/100)>(SUM(H10:H19)-SUM(H10:H19)*0.01)),SUM(H10:H19),"Above grade % does not equal tab 6a.")) -> 0.78034201

Sheet 6c2. Wall Types - Addl Rows
A2: 6c | B2: Opaque Elements - Weighted Average
A3: =CONCATENATE("Compliance based on ",IF(Path="","",Path)) -> Compliance based on Appendix G PRM
A4: Model Input Parameter | B4: Space-Conditioning Category | C4: Item # | D4: Baseline Case | F4: Proposed Case | I4: Supporting Doc Location | J4: Model Output Report
D5: Description | E5: U-factor/ C-factor/ F-factor | F5: Description | G5: Assembly U-factor/ C-factor/ F-factor | H5: % of above-grade wall
A6: Roof Construction | C6: 1 | E6: {=IF(B6="","",IF(D6="","",IF('4. Compliance'!$B$4="Section 11 ECB",INDEX(Lists!$A$30:$D$33,(MATCH($D6,Lists!$A$30:$A$33,0)),(MATCH($B6,Lists!$A$30:$D$30,0))),INDEX(Lists!$F$30:$I$33,(MATCH($D6,Lists!$F$30:$F$33,0)),(MATCH($B6,Lists!$F$30:$I$30,0))))))}
C7: 2 | E7: {=IF(B7="","",IF(D7="","",IF('4. Compliance'!$B$4="Section 11 ECB",INDEX(Lists!$A$30:$D$33,(MATCH($D7,Lists!$A$30:$A$33,0)),(MATCH($B7,Lists!$A$30:$D$30,0))),INDEX(Lists!$F$30:$I$33,(MATCH($D7,Lists!$F$30:$F$33,0)),(MATCH($B7,Lists!$F$30:$I$30,0))))))}
C8: 3 | E8: {=IF(B8="","",IF(D8="","",IF('4. Compliance'!$B$4="Section 11 ECB",INDEX(Lists!$A$30:$D$33,(MATCH($D8,Lists!$A$30:$A$33,0)),(MATCH($B8,Lists!$A$30:$D$30,0))),INDEX(Lists!$F$30:$I$33,(MATCH($D8,Lists!$F$30:$F$33,0)),(MATCH($B8,Lists!$F$30:$I$30,0))))))}
C9: 4 | E9: {=IF(B9="","",IF(D9="","",IF('4. Compliance'!$B$4="Section 11 ECB",INDEX(Lists!$A$30:$D$33,(MATCH($D9,Lists!$A$30:$A$33,0)),(MATCH($B9,Lists!$A$30:$D$30,0))),INDEX(Lists!$F$30:$I$33,(MATCH($D9,Lists!$F$30:$F$33,0)),(MATCH($B9,Lists!$F$30:$I$30,0))))))}
C10: 5 | E10: {=IF(B10="","",IF(D10="","",IF('4. Compliance'!$B$4="Section 11 ECB",INDEX(Lists!$A$30:$D$33,(MATCH($D10,Lists!$A$30:$A$33,0)),(MATCH($B10,Lists!$A$30:$D$30,0))),INDEX(Lists!$F$30:$I$33,(MATCH($D10,Lists!$F$30:$F$33,0)),(MATCH($B10,Lists!$F$30:$I$30,0))))))}
C11: 6 | E11: {=IF(B11="","",IF(D11="","",IF('4. Compliance'!$B$4="Section 11 ECB",INDEX(Lists!$A$30:$D$33,(MATCH($D11,Lists!$A$30:$A$33,0)),(MATCH($B11,Lists!$A$30:$D$30,0))),INDEX(Lists!$F$30:$I$33,(MATCH($D11,Lists!$F$30:$F$33,0)),(MATCH($B11,Lists!$F$30:$I$30,0))))))}
C12: 7 | E12: {=IF(B12="","",IF(D12="","",IF('4. Compliance'!$B$4="Section 11 ECB",INDEX(Lists!$A$30:$D$33,(MATCH($D12,Lists!$A$30:$A$33,0)),(MATCH($B12,Lists!$A$30:$D$30,0))),INDEX(Lists!$F$30:$I$33,(MATCH($D12,Lists!$F$30:$F$33,0)),(MATCH($B12,Lists!$F$30:$I$30,0))))))}
A13: Above-Grade Opaque Wall Construction | C13: 1 | E13: {=IF(B13="","",IF(D13="","",IF('4. Compliance'!$B$4="Section 11 ECB",INDEX(Lists!$A$34:$D$38,(MATCH($D13,Lists!$A$34:$A$38,0)),(MATCH($B13,Lists!$A$34:$D$34,0))),INDEX(Lists!$F$34:$I$38,(MATCH($D13,Lists!$F$34:$F$38,0)),(MATCH($B13,Lists!$F$34:$I$34,0))))))}
C14: 2 | E14: {=IF(B14="","",IF(D14="","",IF('4. Compliance'!$B$4="Section 11 ECB",INDEX(Lists!$A$34:$D$38,(MATCH($D14,Lists!$A$34:$A$38,0)),(MATCH($B14,Lists!$A$34:$D$34,0))),INDEX(Lists!$F$34:$I$38,(MATCH($D14,Lists!$F$34:$F$38,0)),(MATCH($B14,Lists!$F$34:$I$34,0))))))}
C15: 3 | E15: {=IF(B15="","",IF(D15="","",IF('4. Compliance'!$B$4="Section 11 ECB",INDEX(Lists!$A$34:$D$38,(MATCH($D15,Lists!$A$34:$A$38,0)),(MATCH($B15,Lists!$A$34:$D$34,0))),INDEX(Lists!$F$34:$I$38,(MATCH($D15,Lists!$F$34:$F$38,0)),(MATCH($B15,Lists!$F$34:$I$34,0))))))}
C16: 4 | E16: {=IF(B16="","",IF(D16="","",IF('4. Compliance'!$B$4="Section 11 ECB",INDEX(Lists!$A$34:$D$38,(MATCH($D16,Lists!$A$34:$A$38,0)),(MATCH($B16,Lists!$A$34:$D$34,0))),INDEX(Lists!$F$34:$I$38,(MATCH($D16,Lists!$F$34:$F$38,0)),(MATCH($B16,Lists!$F$34:$I$34,0))))))}
C17: 5 | E17: {=IF(B17="","",IF(D17="","",IF('4. Compliance'!$B$4="Section 11 ECB",INDEX(Lists!$A$34:$D$38,(MATCH($D17,Lists!$A$34:$A$38,0)),(MATCH($B17,Lists!$A$34:$D$34,0))),INDEX(Lists!$F$34:$I$38,(MATCH($D17,Lists!$F$34:$F$38,0)),(MATCH($B17,Lists!$F$34:$I$34,0))))))}
C18: 6 | E18: {=IF(B18="","",IF(D18="","",IF('4. Compliance'!$B$4="Section 11 ECB",INDEX(Lists!$A$34:$D$38,(MATCH($D18,Lists!$A$34:$A$38,0)),(MATCH($B18,Lists!$A$34:$D$34,0))),INDEX(Lists!$F$34:$I$38,(MATCH($D18,Lists!$F$34:$F$38,0)),(MATCH($B18,Lists!$F$34:$I$34,0))))))}
C19: 7 | E19: {=IF(B19="","",IF(D19="","",IF('4. Compliance'!$B$4="Section 11 ECB",INDEX(Lists!$A$34:$D$38,(MATCH($D19,Lists!$A$34:$A$38,0)),(MATCH($B19,Lists!$A$34:$D$34,0))),INDEX(Lists!$F$34:$I$38,(MATCH($D19,Lists!$F$34:$F$38,0)),(MATCH($B19,Lists!$F$34:$I$34,0))))))}
C20: 8 | E20: {=IF(B20="","",IF(D20="","",IF('4. Compliance'!$B$4="Section 11 ECB",INDEX(Lists!$A$34:$D$38,(MATCH($D20,Lists!$A$34:$A$38,0)),(MATCH($B20,Lists!$A$34:$D$34,0))),INDEX(Lists!$F$34:$I$38,(MATCH($D20,Lists!$F$34:$F$38,0)),(MATCH($B20,Lists!$F$34:$I$34,0))))))}
C21: 9 | E21: {=IF(B21="","",IF(D21="","",IF('4. Compliance'!$B$4="Section 11 ECB",INDEX(Lists!$A$34:$D$38,(MATCH($D21,Lists!$A$34:$A$38,0)),(MATCH($B21,Lists!$A$34:$D$34,0))),INDEX(Lists!$F$34:$I$38,(MATCH($D21,Lists!$F$34:$F$38,0)),(MATCH($B21,Lists!$F$34:$I$34,0))))))}
C22: 10 | E22: {=IF(B22="","",IF(D22="","",IF('4. Compliance'!$B$4="Section 11 ECB",INDEX(Lists!$A$34:$D$38,(MATCH($D22,Lists!$A$34:$A$38,0)),(MATCH($B22,Lists!$A$34:$D$34,0))),INDEX(Lists!$F$34:$I$38,(MATCH($D22,Lists!$F$34:$F$38,0)),(MATCH($B22,Lists!$F$34:$I$34,0))))))}
C23: 11 | E23: {=IF(B23="","",IF(D23="","",IF('4. Compliance'!$B$4="Section 11 ECB",INDEX(Lists!$A$34:$D$38,(MATCH($D23,Lists!$A$34:$A$38,0)),(MATCH($B23,Lists!$A$34:$D$34,0))),INDEX(Lists!$F$34:$I$38,(MATCH($D23,Lists!$F$34:$F$38,0)),(MATCH($B23,Lists!$F$34:$I$34,0))))))}
C24: 12 | E24: {=IF(B24="","",IF(D24="","",IF('4. Compliance'!$B$4="Section 11 ECB",INDEX(Lists!$A$34:$D$38,(MATCH($D24,Lists!$A$34:$A$38,0)),(MATCH($B24,Lists!$A$34:$D$34,0))),INDEX(Lists!$F$34:$I$38,(MATCH($D24,Lists!$F$34:$F$38,0)),(MATCH($B24,Lists!$F$34:$I$34,0))))))}
C25: 13 | E25: {=IF(B25="","",IF(D25="","",IF('4. Compliance'!$B$4="Section 11 ECB",INDEX(Lists!$A$34:$D$38,(MATCH($D25,Lists!$A$34:$A$38,0)),(MATCH($B25,Lists!$A$34:$D$34,0))),INDEX(Lists!$F$34:$I$38,(MATCH($D25,Lists!$F$34:$F$38,0)),(MATCH($B25,Lists!$F$34:$I$34,0))))))}
... C47: 35 | E47: {=IF(B47="","",IF(D47="","",IF('4. Compliance'!$B$4="Section 11 ECB",INDEX(Lists!$A$34:$D$38,(MATCH($D47,Lists!$A$34:$A$38,0)),(MATCH($B47,Lists!$A$34:$D$34,0))),INDEX(Lists!$F$34:$I$38,(MATCH($D47,Lists!$F$34:$F$38,0)),(MATCH($B47,Lists!$F$34:$I$34,0))))))}
G48: Total % Opaque Roof | H48: =IF(H6="","",IF(AND(((100-'6a. Ext. Wall Areas'!J16)/100)<(SUM(H6:H12)+SUM(H6:H12)*0.01),((100-'6a. Ext. Wall Areas'!J16)/100)>(SUM(H6:H12)-SUM(H6:H12)*0.01)),SUM(H6:H12),"Opaque roof % does not equal tab 6a."))
G49: Total % Opaque Wall | H49: =IF(H14="","",IF(AND(((100-'6a. Ext. Wall Areas'!J14)/100)<(SUM(H14:H48)+SUM(H14:H48)*0.01),((100-'6a. Ext. Wall Areas'!J14)/100)>(SUM(H14:H48)-SUM(H14:H48)*0.01)),SUM(H14:H48),"Above grade % does not equal tab 6a."))

Sheet 6d.1 Interior LPD-Space Method
A2: 6d.1 | B2: Interior LPD: Space-by-Space Method
A3: =CONCATENATE("Compliance based on ",IF(Path="","",Path)) -> Compliance based on Appendix G PRM
A4: Space Type (Table 9.6.1) | B4: Total Area Space/Blg Type (ft2) | C4: Baseline Case | F4: Additional Power Allowance? | H4: Proposed Case
C5: Auto. Controls (Yes/No) | D5: Daylight Ctrls (Yes/No) | E5: Baseline LPD | F5: Type | G5: Add'l LPD | H5: Auto. Controls (Yes/No) | I5: Daylight Ctrls (Yes/No) | J5: Proposed LPD | K5: Add'l LPD | L5: Supporting Doc. Location | M5: Model Output Report
E6: (W/ft2) | G6: (W/ft2) | J6: (W/ft2) | K6: (W/ft2)
E7: =IF($A7="","",IF($B7="","",IF('4. Compliance'!$B$4="Section 11 ECB",VLOOKUP($A7,'Lighting Lookup'!$E$2:$G$108,2),VLOOKUP($A7,'Lighting Lookup'!$E$2:$G$108,3))))
E8: =IF($A8="","",IF($B8="","",IF('4. Compliance'!$B$4="Section 11 ECB",VLOOKUP($A8,'Lighting Lookup'!$E$2:$G$108,2),VLOOKUP($A8,'Lighting Lookup'!$E$2:$G$108,3))))
E9: =IF($A9="","",IF($B9="","",IF('4. Compliance'!$B$4="Section 11 ECB",VLOOKUP($A9,'Lighting Lookup'!$E$2:$G$108,2),VLOOKUP($A9,'Lighting Lookup'!$E$2:$G$108,3))))
E10: =IF($A10="","",IF($B10="","",IF('4. Compliance'!$B$4="Section 11 ECB",VLOOKUP($A10,'Lighting Lookup'!$E$2:$G$108,2),VLOOKUP($A10,'Lighting Lookup'!$E$2:$G$108,3))))
E11: =IF($A11="","",IF($B11="","",IF('4. Compliance'!$B$4="Section 11 ECB",VLOOKUP($A11,'Lighting Lookup'!$E$2:$G$108,2),VLOOKUP($A11,'Lighting Lookup'!$E$2:$G$108,3))))
E12: =IF($A12="","",IF($B12="","",IF('4. Compliance'!$B$4="Section 11 ECB",VLOOKUP($A12,'Lighting Lookup'!$E$2:$G$108,2),VLOOKUP($A12,'Lighting Lookup'!$E$2:$G$108,3))))
E13: =IF($A13="","",IF($B13="","",IF('4. Compliance'!$B$4="Section 11 ECB",VLOOKUP($A13,'Lighting Lookup'!$E$2:$G$108,2),VLOOKUP($A13,'Lighting Lookup'!$E$2:$G$108,3))))
E14: =IF($A14="","",IF($B14="","",IF('4. Compliance'!$B$4="Section 11 ECB",VLOOKUP($A14,'Lighting Lookup'!$E$2:$G$108,2),VLOOKUP($A14,'Lighting Lookup'!$E$2:$G$108,3))))
E15: =IF($A15="","",IF($B15="","",IF('4. Compliance'!$B$4="Section 11 ECB",VLOOKUP($A15,'Lighting Lookup'!$E$2:$G$108,2),VLOOKUP($A15,'Lighting Lookup'!$E$2:$G$108,3))))
E16: =IF($A16="","",IF($B16="","",IF('4. Compliance'!$B$4="Section 11 ECB",VLOOKUP($A16,'Lighting Lookup'!$E$2:$G$108,2),VLOOKUP($A16,'Lighting Lookup'!$E$2:$G$108,3))))
E17: =IF($A17="","",IF($B17="","",IF('4. Compliance'!$B$4="Section 11 ECB",VLOOKUP($A17,'Lighting Lookup'!$E$2:$G$108,2),VLOOKUP($A17,'Lighting Lookup'!$E$2:$G$108,3))))
E18: =IF($A18="","",IF($B18="","",IF('4. Compliance'!$B$4="Section 11 ECB",VLOOKUP($A18,'Lighting Lookup'!$E$2:$G$108,2),VLOOKUP($A18,'Lighting Lookup'!$E$2:$G$108,3))))
... E30: =IF($A30="","",IF($B30="","",IF('4. Compliance'!$B$4="Section 11 ECB",VLOOKUP($A30,'Lighting Lookup'!$E$2:$G$108,2),VLOOKUP($A30,'Lighting Lookup'!$E$2:$G$108,3))))
A31: Total | B31: =SUM(B7:B30) -> 0 | E31: =IF(B31="","",SUMPRODUCT(B7:B30,E7:E30)/B31) -> #DIV/0! | J31: =IF(J7="","",SUMPRODUCT(B7:B30,J7:J30)/B31)

Sheet 6d.2 Interior LPD-Bldg  Method
A1: 6d.2 | B1: Interior LPD: Building Area Method
A2: =CONCATENATE("Compliance based on ",IF(Path="","",Path)) -> Compliance based on Appendix G PRM
A3: Building Area Type (Table 9.5.1) | B3: Total Area Space/Blg Type (ft2) | C3: Baseline Case | F3: Proposed Case
C4: Auto. Controls (Yes/No) | D4: Daylight Ctrls (Yes/No) | E4: Modeled LPD | F4: Auto. Controls (Yes/No) | G4: Daylight Ctrls (Yes/No) | H4: Modeled LPD | I4: Supporting Doc. Location | J4: Model Output Report
E5: (W/ft2) | H5: (W/ft2)
A6: Multifamily | B6: 12381.63 | C6: No | D6: No | E6: =IF($A6="","",IF($B6="","",IF('4. Compliance'!$B$4="Section 11 ECB",VLOOKUP($A6,'Lighting Lookup'!$A$2:$C$33,2),VLOOKUP($A6,'Lighting Lookup'!$A$2:$C$33,3)))) -> 0.7 | F6: Yes | G6: No | H6: 0.07 | I6: RCP-001
E7: =IF($A7="","",IF($B7="","",IF('4. Compliance'!$B$4="Section 11 ECB",VLOOKUP($A7,'Lighting Lookup'!$A$2:$C$33,2),VLOOKUP($A7,'Lighting Lookup'!$A$2:$C$33,3))))
E8: =IF($A8="","",IF($B8="","",IF('4. Compliance'!$B$4="Section 11 ECB",VLOOKUP($A8,'Lighting Lookup'!$A$2:$C$33,2),VLOOKUP($A8,'Lighting Lookup'!$A$2:$C$33,3))))
E9: =IF($A9="","",IF($B9="","",IF('4. Compliance'!$B$4="Section 11 ECB",VLOOKUP($A9,'Lighting Lookup'!$A$2:$C$33,2),VLOOKUP($A9,'Lighting Lookup'!$A$2:$C$33,3))))
E10: =IF($A10="","",IF($B10="","",IF('4. Compliance'!$B$4="Section 11 ECB",VLOOKUP($A10,'Lighting Lookup'!$A$2:$C$33,2),VLOOKUP($A10,'Lighting Lookup'!$A$2:$C$33,3))))
E11: =IF($A11="","",IF($B11="","",IF('4. Compliance'!$B$4="Section 11 ECB",VLOOKUP($A11,'Lighting Lookup'!$A$2:$C$33,2),VLOOKUP($A11,'Lighting Lookup'!$A$2:$C$33,3))))
E12: =IF($A12="","",IF($B12="","",IF('4. Compliance'!$B$4="Section 11 ECB",VLOOKUP($A12,'Lighting Lookup'!$A$2:$C$33,2),VLOOKUP($A12,'Lighting Lookup'!$A$2:$C$33,3))))
E13: =IF($A13="","",IF($B13="","",IF('4. Compliance'!$B$4="Section 11 ECB",VLOOKUP($A13,'Lighting Lookup'!$A$2:$C$33,2),VLOOKUP($A13,'Lighting Lookup'!$A$2:$C$33,3))))
E14: =IF($A14="","",IF($B14="","",IF('4. Compliance'!$B$4="Section 11 ECB",VLOOKUP($A14,'Lighting Lookup'!$A$2:$C$33,2),VLOOKUP($A14,'Lighting Lookup'!$A$2:$C$33,3))))
E15: =IF($A15="","",IF($B15="","",IF('4. Compliance'!$B$4="Section 11 ECB",VLOOKUP($A15,'Lighting Lookup'!$A$2:$C$33,2),VLOOKUP($A15,'Lighting Lookup'!$A$2:$C$33,3))))
E16: =IF($A16="","",IF($B16="","",IF('4. Compliance'!$B$4="Section 11 ECB",VLOOKUP($A16,'Lighting Lookup'!$A$2:$C$33,2),VLOOKUP($A16,'Lighting Lookup'!$A$2:$C$33,3))))
E17: =IF($A17="","",IF($B17="","",IF('4. Compliance'!$B$4="Section 11 ECB",VLOOKUP($A17,'Lighting Lookup'!$A$2:$C$33,2),VLOOKUP($A17,'Lighting Lookup'!$A$2:$C$33,3))))
E18: =IF($A18="","",IF($B18="","",IF('4. Compliance'!$B$4="Section 11 ECB",VLOOKUP($A18,'Lighting Lookup'!$A$2:$C$33,2),VLOOKUP($A18,'Lighting Lookup'!$A$2:$C$33,3))))
... E29: =IF($A29="","",IF($B29="","",IF('4. Compliance'!$B$4="Section 11 ECB",VLOOKUP($A29,'Lighting Lookup'!$A$2:$C$33,2),VLOOKUP($A29,'Lighting Lookup'!$A$2:$C$33,3))))
A30: Total | B30: =SUM(B6:B29) -> 12381.63 | E30: =IF(B30="","",SUMPRODUCT(B6:B29,E6:E29)/B30) -> 0.7 | H30: =IF(H6="","",SUMPRODUCT(B6:B29,H6:H29)/B30) -> 0.07

Sheet 6e. Ext LPD
A2: 6e | B2: Exterior Lighting Power
A3: =CONCATENATE("Compliance based on ",IF(Path="","",Path)) -> Compliance based on Appendix G PRM
C4: Baseline Design (Watts) | D4: Proposed Design (Watts) | E4: Supporting Doc. Location | F4: Model Output Report
A5: Tradable Lighting Power | C5: 64 | D5: 64 | E5: RCP-001 | F5: LV-C, LV-D
A6: Non-Tradable Lighting Power | C6: =IF(SUM('6e. Ext LPD'!J29:J37)=0,"",SUM('6e. Ext LPD'!J29:J37)) | D6: =IF(SUM('6e. Ext LPD'!I29:I37)=0,"",SUM('6e. Ext LPD'!I29:I37))
A7: Base Site Allowance | C7: =IF(AND(C5="",C6=""),"",'6e. Ext LPD'!B11) -> 0
A8: Total Lighting Power | C8: =IF(AND(C5="",C6=""),"",SUM(C5:C6)+'6e. Ext LPD'!B11) -> 64 | D8: =IF(AND(D5="",D6=""),"",SUM(D5:D6)) -> 64 | E8: RCP-001 | F8: LV-C, LV-D
B10: 3 | C10: =IF(B10="","",LOOKUP(B10,LZ,LZDEC)) -> M districts, except MX; C districts, except C5, C6 and C overlays on R
B11: =IF(B10="","",IF($B10="","",IF('4. Compliance'!$B$4="Section 11 ECB",VLOOKUP(B10,'Lighting Zones'!B1:D6,3),0))) -> 0 | C11: Base Site Allowance (watts)
B13: Area Type | C13: Area Parameters | H13: Length or Area (FT or SQFT) | I13: Proposed Watts | J13: Baseline Watts | K13: Unit Allowances
A14: Tradable Surfaces | B14: Uncovered Parking Areas | C14: Total area of uncovered parking and drive areas (sq.ft): | J14: =IF(H14="","",H14*K14) | K14: =IF($B$10<>"",IF($B$10=0,0,IF($B10="","",IF('4. Compliance'!$B$4="Section 11 ECB",IF($B$10=1,0.03,IF($B$10=2,0.04,IF($B$10=3,0.05,0.05))),0.15)))) -> 0.15 | L14: W/SF
B15: Building Grounds | C15: Length of walkways less than 10' wide | J15: =IF(H15="","",H15*K15) | K15: =IF($B$10<>"",IF($B$10=0,0,IF($B10="","",IF('4. Compliance'!$B$4="Section 11 ECB",IF($B$10=1,0.5,IF($B$10=2,0.5,IF($B$10=3,0.6,0.7))),1)))) -> 1 | L15: W/SF
C16: Area of walkways greater than 10' wide | J16: =IF(H16="","",H16*K16) | K16: =IF($B$10<>"",IF($B$10=0,0,IF($B10="","",IF('4. Compliance'!$B$4="Section 11 ECB",IF($B$10=1,0.1,IF($B$10=2,0.1,IF($B$10=3,0.11,0.14))),0.2)))) -> 0.2 | L16: W/SF
C17: Plaza areas (sqft) | J17: =IF(H17="","",H17*K17) | K17: =IF($B$10<>"",IF($B$10=0,0,IF($B10="","",IF('4. Compliance'!$B$4="Section 11 ECB",IF($B$10=1,0.1,IF($B$10=2,0.1,IF($B$10=3,0.11,0.14))),0.2)))) -> 0.2 | L17: W/SF
C18: Special feature areas (sqft) | J18: =IF(H18="","",H18*K18) | K18: =IF($B$10<>"",IF($B$10=0,0,IF($B10="","",IF('4. Compliance'!$B$4="Section 11 ECB",IF($B$10=1,0.1,IF($B$10=2,0.1,IF($B$10=3,0.11,0.14))),0.2)))) -> 0.2 | L18: W/SF
C19: Dining ares (sqft) | J19: =IF(H19="","",H19*K19) | K19: =IF($B$10<>"",IF($B$10=0,0,IF($B10="","",IF('4. Compliance'!$B$4="Section 11 ECB",IF($B$10=1,0.65,IF($B$10=2,0.65,IF($B$10=3,0.75,0.95))),IF(I19="","",I19/H19))))) | L19: W/SF
C20: Area of stairways (sqft) | J20: =IF(H20="","",H20*K20) | K20: =IF($B$10<>"",IF($B$10=0,0,IF($B10="","",IF('4. Compliance'!$B$4="Section 11 ECB",IF($B$10=1,0.6,IF($B$10=2,0.7,IF($B$10=3,0.7,0.7))),1)))) -> 1 | L20: W/SF
C21: Area of pedestrian tunnels (sqft) | J21: =IF(H21="","",H21*K21) | K21: =IF($B$10<>"",IF($B$10=0,0,IF($B10="","",IF('4. Compliance'!$B$4="Section 11 ECB",IF($B$10=1,0.12,IF($B$10=2,0.12,IF($B$10=3,0.14,0.21))),IF(H21="","",I21/H21))))) | L21: W/SF
C22: Area of landscaping (sq.ft): | J22: =IF(H22="","",H22*K22) | K22: =IF($B$10<>"",IF($B$10=0,0,IF($B11="","",IF('4. Compliance'!$B$4="Section 11 ECB",IF($B$10=1,0.12,IF($B$10=2,0.12,IF($B$10=3,0.14,0.21))),IF(H22="","",I22/H22))))) | L22: W/SF
B23: Building Entrances & Exits | C23: Total door width of pedestrian and vehicular entrances and exits (ft): | J23: =IF(H23="","",H23*K23) | K23: =IF($B$10<>"",IF($B$10=0,0,IF($B10="","",IF('4. Compliance'!$B$4="Section 11 ECB",IF($B$10=1,12.6,IF($B$10=2,12.6,IF($B$10=3,20,20))),30)))) -> 30 | L23: W/FT
C24: Area of entry canopies (sq.ft): | J24: =IF(H24="","",H24*K24) | K24: =IF($B$10<>"",IF($B$10=0,0,IF($B13="","",IF('4. Compliance'!$B$4="Section 11 ECB",IF($B$10=1,0.12,IF($B$10=2,0.12,IF($B$10=3,0.14,0.21))),IF(H24="","",I24/H24))))) | L24: W/SF
C25: Loading Docks (sq.ft): | J25: =IF(H25="","",H25*K25) | K25: =IF($B$10<>"",IF($B$10=0,0,IF($B14="","",IF('4. Compliance'!$B$4="Section 11 ECB",IF($B$10=1,0.12,IF($B$10=2,0.12,IF($B$10=3,0.14,0.21))),IF(H25="","",I25/H25))))) | L25: W/SF
B26: Sales canopies | C26: Free standing and attached (sq.ft): | J26: =IF(H26="","",H26*K26) | K26: =IF($B$10<>"",IF($B$10=0,0,IF($B15="","",IF('4. Compliance'!$B$4="Section 11 ECB",IF($B$10=1,0.12,IF($B$10=2,0.12,IF($B$10=3,0.14,0.21))),IF(H26="","",I26/H26))))) | L26: W/SF
B27: Outdoor sales areas | C27: Open areas (including vehicle sales and lots) (sq.ft): | J27: =IF(H27="","",H27*K27) | K27: =IF($B$10<>"",IF($B$10=0,0,IF($B10="","",IF('4. Compliance'!$B$4="Section 11 ECB",IF($B$10=1,0.2,IF($B$10=2,0.2,IF($B$10=3,0.35,0.5))),0.5)))) -> 0.5 | L27: W/SF
C28: Total length of street frontage for vehicle sales (ft): | J28: =IF(H28="","",H28*K28) | K28: =IF($B$10<>"",IF($B$10=0,0,IF($B10="","",IF('4. Compliance'!$B$4="Section 11 ECB",IF($B$10=1,0,IF($B$10=2,7,IF($B$10=3,7,21))),20)))) -> 20 | L28: W/FT
A29: Non Tradable Surfaces | B29: Building façades | C29: Area of façade #1 (sqft) | F29: Length of façade #1 (ft) | J29: =IF(AND(E29="",H29=""),"",IF(Path="Section 11 ECB",E29*O29+H29*P29,I29)) | K29: =IF(Path="Section 11 ECB",IF($B$10<>"",IF($B$10=0,0,IF($B$10=1,0,IF($B$10=2,IF(Q29>R29,O29,P29),IF($B$10=3,IF(Q29>R29,O29,P29),IF(Q29>R29,O29,P29))))),""),"") | L29: =IF($B$10<>"",IF($B$10=0,0,IF($B$10=1,0,IF($B$10=2,IF(Q29>R29,"W/SF","W/FT"),IF($B$10=3,IF(Q29>R29,"W/SF","W/FT"),IF(Q29>R29,"W/SF","W/FT"))))),"") -> W/FT | O29: =IF($B$10<>"",IF($B$10=0,0,IF($B$10="","",IF('4. Compliance'!$B$4="Section 11 ECB",IF($B$10=1,0,IF($B$10=2,0.1,IF($B$10=3,0.15,0.2))),E29)))) | P29: =IF($B$10<>"",IF($B$10=0,0,IF($B$10="","",IF('4. Compliance'!$B$4="Section 11 ECB",IF($B$10=1,0,IF($B$10=2,2.5,IF($B$10=3,3.75,5))),H29)))) | Q29: =O29*E29 -> 0 | R29: =H29*P29 -> 0
C30: Area of façade #2 (sqft) | F30: Length of façade #2 (ft) | J30: =IF(AND(E30="",H30=""),"",IF(Path="Section 11 ECB",E30*O30+H30*P30,I30)) | K30: =IF(Path="Section 11 ECB",IF($B$10<>"",IF($B$10=0,0,IF($B$10=1,0,IF($B$10=2,IF(Q30>R30,O30,P30),IF($B$10=3,IF(Q30>R30,O30,P30),IF(Q30>R30,O30,P30))))),""),"") | L30: =IF($B$10<>"",IF($B$10=0,0,IF($B$10=1,0,IF($B$10=2,IF(Q30>R30,"W/SF","W/FT"),IF($B$10=3,IF(Q30>R30,"W/SF","W/FT"),IF(Q30>R30,"W/SF","W/FT"))))),"") -> W/FT | O30: =IF($B$10<>"",IF($B$10=0,0,IF($B$10="","",IF('4. Compliance'!$B$4="Section 11 ECB",IF($B$10=1,0,IF($B$10=2,0.1,IF($B$10=3,0.15,0.2))),E30)))) | P30: =IF($B$10<>"",IF($B$10=0,0,IF($B$10="","",IF('4. Compliance'!$B$4="Section 11 ECB",IF($B$10=1,0,IF($B$10=2,2.5,IF($B$10=3,3.75,5))),H30)))) | Q30: =O30*E30 -> 0 | R30: =H30*P30 -> 0
C31: Area of façade #3 (sqft) | F31: Length of façade #3 (ft) | J31: =IF(AND(E31="",H31=""),"",IF(Path="Section 11 ECB",E31*O31+H31*P31,I31)) | K31: =IF(Path="Section 11 ECB",IF($B$10<>"",IF($B$10=0,0,IF($B$10=1,0,IF($B$10=2,IF(Q31>R31,O31,P31),IF($B$10=3,IF(Q31>R31,O31,P31),IF(Q31>R31,O31,P31))))),""),"") | L31: =IF($B$10<>"",IF($B$10=0,0,IF($B$10=1,0,IF($B$10=2,IF(Q31>R31,"W/SF","W/FT"),IF($B$10=3,IF(Q31>R31,"W/SF","W/FT"),IF(Q31>R31,"W/SF","W/FT"))))),"") -> W/FT | O31: =IF($B$10<>"",IF($B$10=0,0,IF($B$10="","",IF('4. Compliance'!$B$4="Section 11 ECB",IF($B$10=1,0,IF($B$10=2,0.1,IF($B$10=3,0.15,0.2))),E31)))) | P31: =IF($B$10<>"",IF($B$10=0,0,IF($B$10="","",IF('4. Compliance'!$B$4="Section 11 ECB",IF($B$10=1,0,IF($B$10=2,2.5,IF($B$10=3,3.75,5))),H31)))) | Q31: =O31*E31 -> 0 | R31: =H31*P31 -> 0
C32: Area of façade #4 (sqft) | F32: Length of façade #4 (ft) | J32: =IF(AND(E32="",H32=""),"",IF(Path="Section 11 ECB",E32*O32+H32*P32,I32)) | K32: =IF(Path="Section 11 ECB",IF($B$10<>"",IF($B$10=0,0,IF($B$10=1,0,IF($B$10=2,IF(Q32>R32,O32,P32),IF($B$10=3,IF(Q32>R32,O32,P32),IF(Q32>R32,O32,P32))))),""),"") | L32: =IF($B$10<>"",IF($B$10=0,0,IF($B$10=1,0,IF($B$10=2,IF(Q32>R32,"W/SF","W/FT"),IF($B$10=3,IF(Q32>R32,"W/SF","W/FT"),IF(Q32>R32,"W/SF","W/FT"))))),"") -> W/FT | O32: =IF($B$10<>"",IF($B$10=0,0,IF($B$10="","",IF('4. Compliance'!$B$4="Section 11 ECB",IF($B$10=1,0,IF($B$10=2,0.1,IF($B$10=3,0.15,0.2))),E32)))) | P32: =IF($B$10<>"",IF($B$10=0,0,IF($B$10="","",IF('4. Compliance'!$B$4="Section 11 ECB",IF($B$10=1,0,IF($B$10=2,2.5,IF($B$10=3,3.75,5))),5)))) -> 5 | Q32: =O32*E32 -> 0 | R32: =H32*P32 -> 0
B33: ATMs | C33: # of Locations: | G33: Total # of ATMs: | J33: =IF(H33="","",H33*K33) | K33: =IF(Path="Section 11 ECB",IF($B$10<>"",IF($B$10=0,"No allowance","Allowance = 135W per location plus 45W per additional ATM per location."),""),"")
B34: Guarded facility entrances | C34: Area of uncovered entrances and gatehouse inspection areas at guarded facilities (sq.ft): | J34: =IF(H34="","",H34*K34) | K34: =IF($B$10<>"",IF($B$10=0,0,IF($B10="","",IF(Path="Section 11 ECB",IF($B$10=1,0.12,IF($B$10=2,0.12,IF($B$10=3,0.14,0.21))),"")))) | L34: =IF($B$10<>"",IF($B$10=0,0,IF($B$10=1,0,IF($B$10=2,IF(Q34>R34,"W/SF","W/FT"),IF($B$10=3,IF(Q34>R34,"W/SF","W/FT"),IF(Q34>R34,"W/SF","W/FT"))))),"") -> W/FT
B35: Emergency Vehicle Loading Area | C35: Area of uncovered loading areas for emergency service vehicles (sq.ft): | J35: =IF(H35="","",H35*K35) | K35: =IF($B$10<>"",IF($B$10=0,0,IF($B10="","",IF(Path="Section 11 ECB",IF($B$10=1,0.12,IF($B$10=2,0.12,IF($B$10=3,0.14,0.21))),"")))) | L35: =IF($B$10<>"",IF($B$10=0,0,IF($B$10=1,0,IF($B$10=2,IF(Q35>R35,"W/SF","W/FT"),IF($B$10=3,IF(Q35>R35,"W/SF","W/FT"),IF(Q35>R35,"W/SF","W/FT"))))),"") -> W/FT
B36: Drive-throughs | C36: # of drive-throughs: | J36: =IF(H36="","",H36*K36) | K36: =IF($B$10<>"",IF($B$10=0,0,IF(Path="Section 11 ECB",IF($B$10=1,200,IF($B$10=2,200,IF($B$10=3,200,400))),""))) | L36: Watts/drive thru
B37: Parking near 24-hour retail entrances (main only) | C37: # of main entrances: | J37: =IF(H37="","",H37*K37) | K37: =IF($B$10<>"",IF($B$10=0,0,IF(Path="Section 11 ECB",IF($B$10=1,400,IF($B$10=2,400,IF($B$10=3,400,400))),""))) | L37: Watts/entrance

Sheet 6f. Process Equip.
A3: 6f.1 | B3: Miscellaneous Equipment - Regulated
A4: Space Type (or Equipment Type) | C4: Space Area (or # Equip.) | D4: Equipment Power Density (W/SF) or (Equip Demand) | E4: Annual kwh | F4: Modeling Parameters/ Schedule | G4: Baseline Modeled Identically? (Yes/No) | H4: Supporting Doc. Location | I4: Model Output Report
C5: # | D5: =IF(C5="","",IF(C5="#","kW","W/SF")) -> kW | E5: kwh
A6: Elevators
A7: Escalators
A8: Comm. Kitchen Equip
A9: Office Receptacles
A15: TOTAL | C15: =IF(SUM(C6:C14)=0,"",SUM(C6:C14)) | D15: =IF(SUM(D6:D14)=0,"",IF(D5="W/SF",SUMPRODUCT($C$6:$C$14,$D$6:$D$14)/1000,SUMPRODUCT($C$6:$C$14,$D$6:$D$14))) | E15: =IF(E6="","",SUM(E14))
A17: 6f.2 | B17: Miscellaneous Equipment - Un-Regulated
A18: Space Type (or Equipment Type) | C18: Space Area (or # Equip.) | D18: Equipment Power Density (W/SF) or (Equip Demand) | E18: Annual kwh | F18: Modeling Parameters/ Schedule | G18: Baseline Modeled Identically? (Yes/No) | H18: Supporting Doc. Location | I18: Model Output Report
C19: SQFT | D19: =IF(C19="","",IF(C19="#","kW","W/SF")) -> W/SF | E19: kwh
A20: RES | C20: 11690.791 | D20: 0.07 | E20: 2889 | F20: Energy model | G20: Yes | I20: LV-C, LV-D
A21: =IF('6d.1 Interior LPD-Space Method'!A8<>"",'6d.1 Interior LPD-Space Method'!A8,"") | C21: =IF('6d.1 Interior LPD-Space Method'!B8<>"",'6d.1 Interior LPD-Space Method'!B8,"")
A22: =IF('6d.1 Interior LPD-Space Method'!A9<>"",'6d.1 Interior LPD-Space Method'!A9,"") | C22: =IF('6d.1 Interior LPD-Space Method'!B9<>"",'6d.1 Interior LPD-Space Method'!B9,"")
A23: =IF('6d.1 Interior LPD-Space Method'!A10<>"",'6d.1 Interior LPD-Space Method'!A10,"") | C23: =IF('6d.1 Interior LPD-Space Method'!B10<>"",'6d.1 Interior LPD-Space Method'!B10,"")
A24: =IF('6d.1 Interior LPD-Space Method'!A11<>"",'6d.1 Interior LPD-Space Method'!A11,"") | C24: =IF('6d.1 Interior LPD-Space Method'!B11<>"",'6d.1 Interior LPD-Space Method'!B11,"")
A25: =IF('6d.1 Interior LPD-Space Method'!A12<>"",'6d.1 Interior LPD-Space Method'!A12,"") | C25: =IF('6d.1 Interior LPD-Space Method'!B12<>"",'6d.1 Interior LPD-Space Method'!B12,"")
A26: =IF('6d.1 Interior LPD-Space Method'!A13<>"",'6d.1 Interior LPD-Space Method'!A13,"") | C26: =IF('6d.1 Interior LPD-Space Method'!B13<>"",'6d.1 Interior LPD-Space Method'!B13,"")
A27: =IF('6d.1 Interior LPD-Space Method'!A14<>"",'6d.1 Interior LPD-Space Method'!A14,"") | C27: =IF('6d.1 Interior LPD-Space Method'!B14<>"",'6d.1 Interior LPD-Space Method'!B14,"")
A28: =IF('6d.1 Interior LPD-Space Method'!A15<>"",'6d.1 Interior LPD-Space Method'!A15,"") | C28: =IF('6d.1 Interior LPD-Space Method'!B15<>"",'6d.1 Interior LPD-Space Method'!B15,"")
A29: =IF('6d.1 Interior LPD-Space Method'!A16<>"",'6d.1 Interior LPD-Space Method'!A16,"") | C29: =IF('6d.1 Interior LPD-Space Method'!B16<>"",'6d.1 Interior LPD-Space Method'!B16,"")
A30: =IF('6d.1 Interior LPD-Space Method'!A17<>"",'6d.1 Interior LPD-Space Method'!A17,"") | C30: =IF('6d.1 Interior LPD-Space Method'!B17<>"",'6d.1 Interior LPD-Space Method'!B17,"")
A31: =IF('6d.1 Interior LPD-Space Method'!A18<>"",'6d.1 Interior LPD-Space Method'!A18,"") | C31: =IF('6d.1 Interior LPD-Space Method'!B18<>"",'6d.1 Interior LPD-Space Method'!B18,"")
A32: =IF('6d.1 Interior LPD-Space Method'!A19<>"",'6d.1 Interior LPD-Space Method'!A19,"") | C32: =IF('6d.1 Interior LPD-Space Method'!B19<>"",'6d.1 Interior LPD-Space Method'!B19,"")
... A42: =IF('6d.1 Interior LPD-Space Method'!A29<>"",'6d.1 Interior LPD-Space Method'!A29,"") | C42: =IF('6d.1 Interior LPD-Space Method'!B29<>"",'6d.1 Interior LPD-Space Method'!B29,"")
A43: TOTAL | C43: =IF(SUM(C20:C42)=0,"",SUM(C20:C42)) -> 11690.791 | D43: =IF(SUM(D20:D42)=0,"",IF(D19="W/SF",SUMPRODUCT($C$6:$C$14,$D$6:$D$14)/1000,SUMPRODUCT($C$6:$C$14,$D$6:$D$14))) -> 0 | E43: =IF(E20="","",SUM(E24)) -> 0

Sheet 6g. Service HW
A2: 6g. | B2: Service Hot Water Systems
A3: =CONCATENATE("Compliance based on ",IF(Path="","",Path)) -> Compliance based on Appendix G PRM
A4: Model Input Parameter | C4: Baseline Design | D4: Units | E4: Proposed Design | F4: Units | G4: Supporting Doc Location | H4: Model Output Report
C5: Multifamily
A6: System Type & Fuel | C6: =IF(E6="","",IF($C$5="","",IF(Path="Section 11 ECB",E6,VLOOKUP(C5,Lists!$A$95:$B$128,2)))) -> Gas Storage Water Heater | E6: Electric Storage Water Heater(s) + POU | G6: PLUMBING SCHEDULES | H6: SV-A, SV-A-P
A7: Input Rating | D7: kBtu/h | E7: 29.5 | F7: kW | G7: PLUMBING SCHEDULES | H7: SV-A, SV-A-P
A8: Efficiency | C8: 0.8 | D8: EF | E8: 0.93 | F8: Et | G8: PLUMBING SCHEDULES | H8: SV-A, SV-A-P
A9: Storage Volume | D9: Gal | E9: 395 | F9: Gal | G9: PLUMBING SCHEDULES | H9: SV-A, SV-A-P
A10: Storage Temperature | C10: 120 | D10: °F | E10: 120 | F10: °F | G10: PLUMBING SCHEDULES | H10: SV-A, SV-A-P
A11: Peak HW Demand | D11: GPM | E11: 0.58 | F11: GPM | G11: PLUMBING SCHEDULES | H11: SV-A, SV-A-P
A12: Number of Primary DHW pumps | D12: # | E12: 8 | F12: # | G12: PLUMBING SCHEDULES | H12: SV-A, SV-A-P
A13: Primary DHW Pump Power | D13: kW | E13: 4.18 | F13: kW | G13: PLUMBING SCHEDULES | H13: SV-A, SV-A-P
A14: Primary DHW Pump Control | C14: Constant (baseline default) | E14: Demand controlled / continuous (per MEP) | G14: PLUMBING SCHEDULES | H14: SV-A, SV-A-P
A16: 6h HVAC and SHW Narrative | C16: Please provide a narrative of the building's heating, cooling, ventilation & service hot water systems
A17: The proposed building is a new multifamily residential building. Space heating and cooling are provided by individual air-source split-system heat pumps serving each dwelling unit, with outdoor condensing units located on the roof and indoor air handlers within the conditioned spaces. Outdoor ventilation air is provided by a central energy recovery ventilator (ERV) in accordance with ASHRAE 62.1, with exhaust from kitchens and bathrooms discharged to the roof. Service hot water is provided by electric storage water heaters with supplemental point-of-use electric water heaters. The system operates at a storage temperature of 120°F and includes demand-controlled hot water recirculation. For energy code compliance using ASHRAE 90.1-2019 Appendix G, the baseline building is modeled with a gas-fired storage water heater, while the proposed design reflects the all-electric service water heating system shown on the plumbing drawings.

Sheet Instructions for HVAC_Cover
A2: Overview: The HVAC portion of this table is partially automated by using Excel Macros. It is important that the information is entered completely and sequentially. The Macro will create HVAC Air-side Sheets for each Row of HVAC information. For example, the information input on Row 4 will be transferred to a newly created HVAC Air-side Tab. Once there is no information in a Row, the program will stop running. | M2: WORKBOOK COLOR LEGEND
M3: Do not edit: information
M4: Do not edit: formulas
M5: Do not edit: error
M6: User edit: required information
M7: User edit: drop-down menu
M8: User edit: drop-down menu (only for use with Appendix G)
A9: 1. Clear all data fields | M9: User edit: formula + drop-down menu
A10: a. Clear the HVAC Cover sheet by pressing on the ‘Reset’ button (cell G15) | M10: User edit: fill in box
A11: b. After the prompt “This will erase everything you have filled in. Are you sure?” Click Yes
A12: c. This will erase all data fields in ‘HVAC Cover’ and ‘HVAC Air-side’ tabs
A13: 2. Filling in System information (Section 11)
A14: a. The first proposed system must be input on Row 4.
A15: b. Select the proposed system type from the drop down list in Column C - this will automatically populate the ‘Proposed Building Classification’ and ‘Baseline Systems’ (columns G, H, I & J)
A16: c. Check the information in Columns G, H & I – if the pre-populated information is not correct, select the correct information from the drop-down list in each column
A17: d. Input the name of the HVAC system that corresponds with the M-dwgs into Column D
A18: e. Input the name of the HVAC system that corresponds to the Baseline system in the modeling reports into Column E
A19: f. Input the name of the HVAC system that corresponds to the Proposed system in the modeling reports into Column F
A20: g. Repeat steps b through f until all proposed systems are input. Leaving spaces between rows will cause an error.
A21: 3. Filling in System information (Appendix G)
A22: a. The first proposed system must be input on Row 4.
... A44: c. DO NOT RENAME the tab titled "HVAC_Cover" - this will cause the Macro to crash and you may have to start over.

Sheet HVAC_Cover
B2: HVAC Cover Sheet | G2: Proposed Building Classification (auto-populated + drop-down) | J2: =CONCATENATE("Baseline systems correspond to ",IF(Path="","",Path)) -> Baseline systems correspond to Appendix G PRM
B3: =IF(Path="Appendix G PRM", "Building Area Type (Only used for Appendix G)", "This column not used for Section 11 projects") -> Building Area Type (Only used for Appendix G) | C3: Proposed System Design | D3: System Name in Mechanical Schedule | E3: System Name in Model Reports (baseline) | F3: System Name in Model Reports (proposed) | G3: =IF(TRUE, "Condenser Cooling Source", "Section 11 Column") -> Condenser Cooling Source | H3: Heating System Classifcation | I3: Zone Classification | K3: =Path -> Appendix G PRM
B4: Residential | C4: Packaged/split-system heat pump | G4: Air/None | H4: =IFERROR(IF(TRUE, VLOOKUP($C4,Lists!$J$75:$O$88,6,FALSE),""),"") -> Heat Pump | I4: Single-Zone Residential | J4: =IFERROR(IF(Path="Appendix G PRM", VLOOKUP($B4,Lists!$A$73:$B$81,2,FALSE),IFERROR(VLOOKUP(CONCATENATE(G:G,H:H,I:I), Lists!$S$81:$W$98,5,FALSE),"")),"") -> System 1: PTAC
G5: =IFERROR(IF(TRUE, VLOOKUP($C5,Lists!$J$75:$O$88,4,FALSE),""),"") | H5: =IFERROR(IF(TRUE, VLOOKUP($C5,Lists!$J$75:$O$88,6,FALSE),""),"") | I5: =IFERROR(IF(TRUE, VLOOKUP($C5,Lists!$J$75:$O$88,5,FALSE),""),"") | J5: =IFERROR(IF(Path="Appendix G PRM", VLOOKUP($B5,Lists!$A$73:$B$81,2,FALSE),IFERROR(VLOOKUP(CONCATENATE(G:G,H:H,I:I), Lists!$S$81:$W$98,5,FALSE),"")),"")
G6: =IFERROR(IF(TRUE, VLOOKUP($C6,Lists!$J$75:$O$88,4,FALSE),""),"") | H6: =IFERROR(IF(TRUE, VLOOKUP($C6,Lists!$J$75:$O$88,6,FALSE),""),"") | I6: =IFERROR(IF(TRUE, VLOOKUP($C6,Lists!$J$75:$O$88,5,FALSE),""),"") | J6: =IFERROR(IF(Path="Appendix G PRM", VLOOKUP($B6,Lists!$A$73:$B$81,2,FALSE),IFERROR(VLOOKUP(CONCATENATE(G:G,H:H,I:I), Lists!$S$81:$W$98,5,FALSE),"")),"")
G7: =IFERROR(IF(TRUE, VLOOKUP($C7,Lists!$J$75:$O$88,4,FALSE),""),"") | H7: =IFERROR(IF(TRUE, VLOOKUP($C7,Lists!$J$75:$O$88,6,FALSE),""),"") | I7: =IFERROR(IF(TRUE, VLOOKUP($C7,Lists!$J$75:$O$88,5,FALSE),""),"") | J7: =IFERROR(IF(Path="Appendix G PRM", VLOOKUP($B7,Lists!$A$73:$B$81,2,FALSE),IFERROR(VLOOKUP(CONCATENATE(G:G,H:H,I:I), Lists!$S$81:$W$98,5,FALSE),"")),"")
G8: =IFERROR(IF(TRUE, VLOOKUP($C8,Lists!$J$75:$O$88,4,FALSE),""),"") | H8: =IFERROR(IF(TRUE, VLOOKUP($C8,Lists!$J$75:$O$88,6,FALSE),""),"") | I8: =IFERROR(IF(TRUE, VLOOKUP($C8,Lists!$J$75:$O$88,5,FALSE),""),"") | J8: =IFERROR(IF(Path="Appendix G PRM", VLOOKUP($B8,Lists!$A$73:$B$81,2,FALSE),IFERROR(VLOOKUP(CONCATENATE(G:G,H:H,I:I), Lists!$S$81:$W$98,5,FALSE),"")),"")
G9: =IFERROR(IF(TRUE, VLOOKUP($C9,Lists!$J$75:$O$88,4,FALSE),""),"") | H9: =IFERROR(IF(TRUE, VLOOKUP($C9,Lists!$J$75:$O$88,6,FALSE),""),"") | I9: =IFERROR(IF(TRUE, VLOOKUP($C9,Lists!$J$75:$O$88,5,FALSE),""),"") | J9: =IFERROR(IF(Path="Appendix G PRM", VLOOKUP($B9,Lists!$A$73:$B$81,2,FALSE),IFERROR(VLOOKUP(CONCATENATE(G:G,H:H,I:I), Lists!$S$81:$W$98,5,FALSE),"")),"")
G10: =IFERROR(IF(TRUE, VLOOKUP($C10,Lists!$J$75:$O$88,4,FALSE),""),"") | H10: =IFERROR(IF(TRUE, VLOOKUP($C10,Lists!$J$75:$O$88,6,FALSE),""),"") | I10: =IFERROR(IF(TRUE, VLOOKUP($C10,Lists!$J$75:$O$88,5,FALSE),""),"") | J10: =IFERROR(IF(Path="Appendix G PRM", VLOOKUP($B10,Lists!$A$73:$B$81,2,FALSE),IFERROR(VLOOKUP(CONCATENATE(G:G,H:H,I:I), Lists!$S$81:$W$98,5,FALSE),"")),"")
G11: =IFERROR(IF(TRUE, VLOOKUP($C11,Lists!$J$75:$O$88,4,FALSE),""),"") | H11: =IFERROR(IF(TRUE, VLOOKUP($C11,Lists!$J$75:$O$88,6,FALSE),""),"") | I11: =IFERROR(IF(TRUE, VLOOKUP($C11,Lists!$J$75:$O$88,5,FALSE),""),"") | J11: =IFERROR(IF(Path="Appendix G PRM", VLOOKUP($B11,Lists!$A$73:$B$81,2,FALSE),IFERROR(VLOOKUP(CONCATENATE(G:G,H:H,I:I), Lists!$S$81:$W$98,5,FALSE),"")),"")
G12: =IFERROR(IF(TRUE, VLOOKUP($C12,Lists!$J$75:$O$88,4,FALSE),""),"") | H12: =IFERROR(IF(TRUE, VLOOKUP($C12,Lists!$J$75:$O$88,6,FALSE),""),"") | I12: =IFERROR(IF(TRUE, VLOOKUP($C12,Lists!$J$75:$O$88,5,FALSE),""),"") | J12: =IFERROR(IF(Path="Appendix G PRM", VLOOKUP($B12,Lists!$A$73:$B$81,2,FALSE),IFERROR(VLOOKUP(CONCATENATE(G:G,H:H,I:I), Lists!$S$81:$W$98,5,FALSE),"")),"")
G13: =IFERROR(IF(TRUE, VLOOKUP($C13,Lists!$J$75:$O$88,4,FALSE),""),"") | H13: =IFERROR(IF(TRUE, VLOOKUP($C13,Lists!$J$75:$O$88,6,FALSE),""),"") | I13: =IFERROR(IF(TRUE, VLOOKUP($C13,Lists!$J$75:$O$88,5,FALSE),""),"") | J13: =IFERROR(IF(Path="Appendix G PRM", VLOOKUP($B13,Lists!$A$73:$B$81,2,FALSE),IFERROR(VLOOKUP(CONCATENATE(G:G,H:H,I:I), Lists!$S$81:$W$98,5,FALSE),"")),"")
B15: Baseline System | C15: Minimum Efficiencies | D15: Fan Power | E15: =IF(TRUE, "Heating System Classification", "Section 11 Column") -> Heating System Classification
B16: =IFERROR(IF(Path="Appendix G PRM", VLOOKUP($B4,Lists!$A$73:$B$81,2,FALSE),J4),"") -> System 1: PTAC | C16: =IFERROR(IF(Path="Section 11 ECB", VLOOKUP($B16,Lists!$W$81:$Z$98,3,FALSE),VLOOKUP($B16,Lists!$J$61:$P$67,6,FALSE)),"") -> Cool: 3.2 COP -- Heat: Boiler | D16: =IFERROR(IF(Path="Section 11 ECB", VLOOKUP($B16,Lists!$W$81:$Z$98,2,FALSE),VLOOKUP($B16,Lists!$J$61:$P$67,7,FALSE)),"") -> Supply CFM * .3 | E16: =IFERROR(IF(Path="Section 11 ECB", VLOOKUP($B16,Lists!$W$81:$AA$98,5,FALSE),VLOOKUP($B16,Lists!$J$61:$P$67,5,FALSE)),"") -> Hot-water fossil fuel boiler
B17: =IFERROR(IF(Path="Appendix G PRM", VLOOKUP($B5,Lists!$A$73:$B$81,2,FALSE),J5),"") | C17: =IFERROR(IF(Path="Section 11 ECB", VLOOKUP($B17,Lists!$W$81:$Z$98,3,FALSE),VLOOKUP($B17,Lists!$J$61:$P$67,6,FALSE)),"") | D17: =IFERROR(IF(Path="Section 11 ECB", VLOOKUP($B17,Lists!$W$81:$Z$98,2,FALSE),VLOOKUP($B17,Lists!$J$61:$P$67,7,FALSE)),"") | E17: =IFERROR(IF(Path="Section 11 ECB", VLOOKUP($B17,Lists!$W$81:$AA$98,5,FALSE),VLOOKUP($B17,Lists!$J$61:$P$67,5,FALSE)),"") | G17: System Count
B18: =IFERROR(IF(Path="Appendix G PRM", VLOOKUP($B6,Lists!$A$73:$B$81,2,FALSE),J6),"") | C18: =IFERROR(IF(Path="Section 11 ECB", VLOOKUP($B18,Lists!$W$81:$Z$98,3,FALSE),VLOOKUP($B18,Lists!$J$61:$P$67,6,FALSE)),"") | D18: =IFERROR(IF(Path="Section 11 ECB", VLOOKUP($B18,Lists!$W$81:$Z$98,2,FALSE),VLOOKUP($B18,Lists!$J$61:$P$67,7,FALSE)),"") | E18: =IFERROR(IF(Path="Section 11 ECB", VLOOKUP($B18,Lists!$W$81:$AA$98,5,FALSE),VLOOKUP($B18,Lists!$J$61:$P$67,5,FALSE)),"") | G18: =ROWS(C4:C13)-COUNTBLANK(C4:C13) -> 1
B19: =IFERROR(IF(Path="Appendix G PRM", VLOOKUP($B7,Lists!$A$73:$B$81,2,FALSE),J7),"") | C19: =IFERROR(IF(Path="Section 11 ECB", VLOOKUP($B19,Lists!$W$81:$Z$98,3,FALSE),VLOOKUP($B19,Lists!$J$61:$P$67,6,FALSE)),"") | D19: =IFERROR(IF(Path="Section 11 ECB", VLOOKUP($B19,Lists!$W$81:$Z$98,2,FALSE),VLOOKUP($B19,Lists!$J$61:$P$67,7,FALSE)),"") | E19: =IFERROR(IF(Path="Section 11 ECB", VLOOKUP($B19,Lists!$W$81:$AA$98,5,FALSE),VLOOKUP($B19,Lists!$J$61:$P$67,5,FALSE)),"")
B20: =IFERROR(IF(Path="Appendix G PRM", VLOOKUP($B8,Lists!$A$73:$B$81,2,FALSE),J8),"") | C20: =IFERROR(IF(Path="Section 11 ECB", VLOOKUP($B20,Lists!$W$81:$Z$98,3,FALSE),VLOOKUP($B20,Lists!$J$61:$P$67,6,FALSE)),"") | D20: =IFERROR(IF(Path="Section 11 ECB", VLOOKUP($B20,Lists!$W$81:$Z$98,2,FALSE),VLOOKUP($B20,Lists!$J$61:$P$67,7,FALSE)),"") | E20: =IFERROR(IF(Path="Section 11 ECB", VLOOKUP($B20,Lists!$W$81:$AA$98,5,FALSE),VLOOKUP($B20,Lists!$J$61:$P$67,5,FALSE)),"")
B21: =IFERROR(IF(Path="Appendix G PRM", VLOOKUP($B9,Lists!$A$73:$B$81,2,FALSE),J9),"") | C21: =IFERROR(IF(Path="Section 11 ECB", VLOOKUP($B21,Lists!$W$81:$Z$98,3,FALSE),VLOOKUP($B21,Lists!$J$61:$P$67,6,FALSE)),"") | D21: =IFERROR(IF(Path="Section 11 ECB", VLOOKUP($B21,Lists!$W$81:$Z$98,2,FALSE),VLOOKUP($B21,Lists!$J$61:$P$67,7,FALSE)),"") | E21: =IFERROR(IF(Path="Section 11 ECB", VLOOKUP($B21,Lists!$W$81:$AA$98,5,FALSE),VLOOKUP($B21,Lists!$J$61:$P$67,5,FALSE)),"")
B22: =IFERROR(IF(Path="Appendix G PRM", VLOOKUP($B10,Lists!$A$73:$B$81,2,FALSE),J10),"") | C22: =IFERROR(IF(Path="Section 11 ECB", VLOOKUP($B22,Lists!$W$81:$Z$98,3,FALSE),VLOOKUP($B22,Lists!$J$61:$P$67,6,FALSE)),"") | D22: =IFERROR(IF(Path="Section 11 ECB", VLOOKUP($B22,Lists!$W$81:$Z$98,2,FALSE),VLOOKUP($B22,Lists!$J$61:$P$67,7,FALSE)),"") | E22: =IFERROR(IF(Path="Section 11 ECB", VLOOKUP($B22,Lists!$W$81:$AA$98,5,FALSE),VLOOKUP($B22,Lists!$J$61:$P$67,5,FALSE)),"")
B23: =IFERROR(IF(Path="Appendix G PRM", VLOOKUP($B11,Lists!$A$73:$B$81,2,FALSE),J11),"") | C23: =IFERROR(IF(Path="Section 11 ECB", VLOOKUP($B23,Lists!$W$81:$Z$98,3,FALSE),VLOOKUP($B23,Lists!$J$61:$P$67,6,FALSE)),"") | D23: =IFERROR(IF(Path="Section 11 ECB", VLOOKUP($B23,Lists!$W$81:$Z$98,2,FALSE),VLOOKUP($B23,Lists!$J$61:$P$67,7,FALSE)),"") | E23: =IFERROR(IF(Path="Section 11 ECB", VLOOKUP($B23,Lists!$W$81:$AA$98,5,FALSE),VLOOKUP($B23,Lists!$J$61:$P$67,5,FALSE)),"")
B24: =IFERROR(IF(Path="Appendix G PRM", VLOOKUP($B12,Lists!$A$73:$B$81,2,FALSE),J12),"") | C24: =IFERROR(IF(Path="Section 11 ECB", VLOOKUP($B24,Lists!$W$81:$Z$98,3,FALSE),VLOOKUP($B24,Lists!$J$61:$P$67,6,FALSE)),"") | D24: =IFERROR(IF(Path="Section 11 ECB", VLOOKUP($B24,Lists!$W$81:$Z$98,2,FALSE),VLOOKUP($B24,Lists!$J$61:$P$67,7,FALSE)),"") | E24: =IFERROR(IF(Path="Section 11 ECB", VLOOKUP($B24,Lists!$W$81:$AA$98,5,FALSE),VLOOKUP($B24,Lists!$J$61:$P$67,5,FALSE)),"")
B25: =IFERROR(IF(Path="Appendix G PRM", VLOOKUP($B13,Lists!$A$73:$B$81,2,FALSE),J13),"") | C25: =IFERROR(IF(Path="Section 11 ECB", VLOOKUP($B25,Lists!$W$81:$Z$98,3,FALSE),VLOOKUP($B25,Lists!$J$61:$P$67,6,FALSE)),"") | D25: =IFERROR(IF(Path="Section 11 ECB", VLOOKUP($B25,Lists!$W$81:$Z$98,2,FALSE),VLOOKUP($B25,Lists!$J$61:$P$67,7,FALSE)),"") | E25: =IFERROR(IF(Path="Section 11 ECB", VLOOKUP($B25,Lists!$W$81:$AA$98,5,FALSE),VLOOKUP($B25,Lists!$J$61:$P$67,5,FALSE)),"")

Sheet HVAC Air-side
A2: 6i | B2: Air-Side HVAC
C3: HVAC System / Group (BASELINE DESIGN) | F3: HVAC System / Group (PROPOSED DESIGN)
C4: Description | E4: Units | F4: Description | H4: Units | I4: Supporting Doc. Location | J4: Model Output Report
A5: System Description
A8: System Name in Model | C8: HOT WATER LOOP / PTAC | F8: PACKAGED ROOFTOP HEAT PUMP | I8: MECHANICAL EQUIPMENT SCHEDULES | J8: SV-A, SV-A-P
A9: # of Similar Systems | C9: 1 | F9: 1 | I9: MECHANICAL EQUIPMENT SCHEDULES | J9: SV-A, SV-A-P
A10: Total Cooling Capacity | C10: 924846.66 | E10: BTU / h | F10: 281873.61 | H10: BTU/h | I10: MECHANICAL EQUIPMENT SCHEDULES | J10: SV-A, SV-A-P
A11: *Table 6.8.1 Unitary Cooling Capacity Range | E11: BTU / h
A12: *Unitary Cooling Eff. | C12: 8.89 | E12: EER | F12: 10.84 | H12: EER | I12: MECHANICAL EQUIPMENT SCHEDULES | J12: SV-A, SV-A-P
A13: *Unitary Cooling Part-load Eff. (if applicable) | C13: 9.1 | E13: IEER | F13: 11 | H13: IEER | I13: MECHANICAL EQUIPMENT SCHEDULES | J13: SV-A, SV-A-P
A14: Total Heating Capacity | C14: 617087.69 | E14: BTU/h | F14: 293439.54 | H14: BTU/h | I14: MECHANICAL EQUIPMENT SCHEDULES | J14: SV-A, SV-A-P
A15: *Table 6.8.1 Unitary Heating Capacity Range | E15: Et | F15: Et
A16: *Unitary Heating Efficiency | C16: NA- boiler dependent | E16: NA | F16: 1.94 | H16: COP | I16: MECHANICAL EQUIPMENT SCHEDULES | J16: SV-A, SV-A-P
A17: *Fan Control | C17: Single- or two-speed fan | F17: Variable-speed fan | I17: MECHANICAL EQUIPMENT SCHEDULES | J17: SV-A, SV-A-P
A18: Supply Airflow | C18: 28075.16 | E18: cfm | F18: 9259.506 | H18: cfm | I18: MECHANICAL EQUIPMENT SCHEDULES | J18: SV-A, SV-A-P
A19: =IF(AND(C19 <> F19,F19 <> ""),"OUTDOOR AIRFLOW","Outdoor Airflow") -> Outdoor Airflow | E19: cfm | H19: cfm
A20: *Demand Control Ventilation | C20: No | F20: No
A21: Economizer provided?
A22: *Economizer High-Limit Shutoff (°F)
A24: Exhaust Air Energy Recovery System Provided? | C24: No | F24: Yes | I24: MECHANICAL EQUIPMENT SCHEDULES | J24: SV-A, SV-A-P
A25: *Exhaust Air Energy Recovery Effectiveness | C25: =IF(C24="Yes","50%","") | F25: 0.65 | I25: MECHANICAL EQUIPMENT SCHEDULES | J25: SV-A, SV-A-P
A26: Fan Brake Horsepower | C26: 11.320976 | E26: hp | F26: 2.5089182 | H26: hp | I26: MECHANICAL EQUIPMENT SCHEDULES | J26: SV-A, SV-A-P
A27: Fan Motor Efficiency | C27: 80 | E27: % | F27: 90 | H27: % | I27: MECHANICAL EQUIPMENT SCHEDULES | J27: SV-A, SV-A-P
A28: Supply Fan Power | E28: kW | F28: 1.8709 | H28: kW | I28: MECHANICAL EQUIPMENT SCHEDULES | J28: SV-A, SV-A-P
A29: Return Fan Power | E29: kW | H29: kW
A30: Exhaust Fan Power | E30: kW | F30: 0.15 | H30: kW | I30: MECHANICAL EQUIPMENT SCHEDULES | J30: SV-A, SV-A-P
A31: Relief Fan Power | E31: kW | H31: kW
A32: =IF(OR((SUM(C28:D31)<>C32),(SUM(F28:G31)<>F32)),"Allowed/Total Fan Power:","Allowed/Total FAN POWER:") -> Allowed/Total Fan Power: | E32: kW | H32: kW
A33: EIR | C33: =IF(OR(C12="",C12="NA- chiller dependent"),"",3.412/C12) -> 0.38380202 | F33: =IF(OR(F12="",F12="NA- chiller dependent"),"",3.412/F12) -> 0.31476015
A34: HIR | C34: =IF(OR(C16="",C16="NA- boiler dependent"),"",1/C16) | F34: =IF(OR(F16="",F16="NA- boiler dependent"),"",1/F16) -> 0.51546392
A35: % OA | C35: =IF(C19="","",C19/cfm) | F35: =IF(F19="","",F19/cfm)
A36: Other (describe)

Sheet Lists
A1: Non-Residential | B1: Yes | F1: Regulated | J1: New Building | M1: 40 | N1: Yes | Q1: kW | R1: # | S1: kW
A2: Residential | B2: No | F2: Unregulated | J2: New Building w/ Existing Elements ("Big Alt") | N2: No | Q2: kBtu/h | R2: SQFT | S2: W/SF
A3: Semiheated | B3: N/A | J3: Addition
B4: Non-Residential | C4: Residential | D4: Semiheated | G4: Non-Residential | H4: Residential | I4: Semiheated | J4: Alteration | N4: Section 11 ECB | Q4: EF | R4: kBTU/h | S4: EER | T4: Et
A5: Nonmetal framing (all) | B5: U-0.28 | C5: U-0.28 | D5: U-0.51 | F5: Nonmetal framing (all) | G5: U-0.57 | H5: U-0.57 | I5: U-1.22 | J5: Addition + Alteration | N5: Appendix G PRM | Q5: SL | R5: BTU/h | S5: SEER | T5: Ec
A6: Metal framing (fixed), below 95ft | B6: U-0.30 | C6: U-0.30 | D6: U-0.73 | F6: Metal framing (fixed), below 95ft | G6: U-0.57 | H6: U-0.57 | I6: U-1.22 | Q6: Et | R6: tons | T6: AFUE
A7: Metal framing (fixed), 95ft and above | B7: U-0.36 | C7: U-0.36 | D7: U-0.70 | F7: Metal framing (fixed), 95ft and above | G7: U-0.57 | H7: U-0.57 | I7: U-1.22 | Q7: COP | R7: kW | T7: COP
A8: Metal framing (operable), below 95ft | B8: U-0.40 | C8: U-0.40 | D8: U-0.81 | F8: Metal framing (operable), below 95ft | G8: U-0.57 | H8: U-0.57 | I8: U-1.22 | T8: HSPF
A9: Metal framing (operable), 95ft and above | B9: U-0.42 | C9: U-0.42 | D9: U-0.81 | F9: Metal framing (operable), 95ft and above | G9: U-0.57 | H9: U-0.57 | I9: U-1.22
A10: Curtainwall fixed | B10: U-0.36 | C10: U-0.36 | D10: U-0.73 | F10: Curtainwall fixed | G10: U-0.57 | H10: U-0.57 | I10: U-1.22
A11: Metal framing (entrance door) | B11: U-0.77 | C11: U-0.68 | D11: U-0.77 | F11: Metal framing (entrance door) | G11: U-0.57 | H11: U-0.57 | I11: U-1.22
N12: Cost | O12: Source
B13: Non-Residential | C13: Residential | D13: Semiheated | G13: Non-Residential | H13: Residential | I13: Semiheated | M13: All Other | N13: 0.53 | O13: 0.55
A14: Nonmetal framing (all) | B14: 0.36 | C14: 0.36 | D14: NR | F14: Nonmetal framing (all) | G14: 0.39 | H14: 0.39 | I14: NR | M14: Dormitory | N14: 0.53 | O14: 0.55
A15: Metal framing (fixed), below 95ft | B15: 0.36 | C15: 0.36 | D15: NR | F15: Metal framing (fixed), below 95ft | G15: 0.39 | H15: 0.39 | I15: NR | M15: Healthcare/hospital | N15: 0.54 | O15: 0.56
A16: Metal framing (fixed), 95ft and above | B16: 0.36 | C16: 0.36 | D16: NR | F16: Metal framing (fixed), 95ft and above | G16: 0.39 | H16: 0.39 | I16: NR | M16: Hotel/motel | N16: 0.62 | O16: 0.62
A17: Metal framing (operable), below 95ft | B17: 0.36 | C17: 0.36 | D17: NR | F17: Metal framing (operable), below 95ft | G17: 0.39 | H17: 0.39 | I17: NR | M17: Multifamily | N17: 0.67 | O17: 0.68
A18: Metal framing (operable), 95ft and above | B18: 0.36 | C18: 0.36 | D18: NR | F18: Metal framing (operable), 95ft and above | G18: 0.39 | H18: 0.39 | I18: NR | M18: Office | N18: 0.54 | O18: 0.55
A19: Curtainwall fixed | B19: 0.36 | C19: 0.36 | D19: NR | F19: Curtainwall fixed | G19: 0.39 | H19: 0.39 | I19: NR | M19: Restaurant | N19: 0.56 | O19: 0.63
A20: Metal framing (entrance door) | B20: 0.36 | C20: 0.36 | D20: NR | F20: Metal framing (entrance door) | G20: 0.39 | H20: 0.39 | I20: NR | M20: Retail | N20: 0.45 | O20: 0.45
M21: School | N21: 0.45 | O21: 0.45
A22: Skylights | B22: Non-Residential | C22: Residential | D22: Semiheated | F22: Skylights | G22: Non-Residential | H22: Residential | I22: Semiheated | M22: Warehouse | N22: 0.42 | O22: 0.44
A23: 0% - 3.0% | B23: U-0.48 | C23: U-0.48 | D23: U-1.15 | F23: 0% - 2.0% | G23: U-0.69 | H23: U-0.58 | I23: U-1.36 | M23: Weighted Average
A24: 3.0%+ | B24: U-0.48 | C24: U-0.48 | D24: U-1.15 | F24: 2.1%+ | G24: U-0.69 | H24: U-0.58 | I24: U-1.36
A26: Skylights | B26: Non-Residential | C26: Residential | D26: Semiheated | F26: Skylights | G26: Non-Residential | H26: Residential | I26: Semiheated
A27: 0% - 3.0% | B27: 0.38 | C27: 0.38 | D27: NR | F27: 0% - 2.0% | G27: 0.49 | H27: 0.36 | I27: NR
A28: 3.0%+ | B28: 0.38 | C28: 0.38 | D28: NR | F28: 2.1%+ | G28: 0.39 | H28: 0.19 | I28: NR | M28: Grocery Store | N28: 7
M29: Healthcare (hospital) | N29: 21
B30: Non-Residential | C30: Residential | D30: Semiheated | G30: Non-Residential | H30: Residential | I30: Semiheated | M30: Hospital | N30: 27
A31: Insulation Entirely Above Deck | B31: U-0.030 | C31: U-0.030 | D31: U-0.093 | F31: Insulation Entirely Above Deck | G31: U-0.063 | H31: U-0.063 | I31: U-0.218 | M31: Hotel/motel (< 75 rooms) | N31: 24
A32: Metal Building | B32: U-0.035 | C32: U-0.035 | D32: U-0.082 | F32: Metal Building | G32: ERROR | H32: ERROR | I32: ERROR | M32: Hotel/motel (> 75 rooms) | N32: 34
A33: Attic and Other | B33: U-0.020 | C33: U-0.020 | D33: U-0.034 | F33: Attic and Other | G33: ERROR | H33: ERROR | I33: ERROR | M33: Multifamily
B34: Non-Residential | C34: Residential | D34: Semiheated | G34: Non-Residential | H34: Residential | I34: Semiheated | M34: Office (< 5000 ft2) | N34: 19
A35: Mass | B35: U-0.099 | C35: U-0.086 | D35: U-0.580 | F35: Mass | G35: ERROR | H35: ERROR | I35: ERROR | M35: Office (> 50,000 ft2) | N35: 40
A36: Metal Building | B36: U-0.048 | C36: U-0.048 | D36: U-0.162 | F36: Metal Building | G36: ERROR | H36: ERROR | I36: ERROR | M36: Office (5000 - 50,000 ft2) | N36: 31
A37: Steel-Framed | B37: U-0.061 | C37: U-0.061 | D37: U-0.124 | F37: Steel-Framed | G37: U-0.124 | H37: U-0.064 | I37: U-0.124 | M37: Other
A38: Wood-Framed and Other | B38: U-0.061 | C38: U-0.061 | D38: U-0.089 | F38: Wood-Framed and Other | G38: ERROR | H38: ERROR | I38: ERROR | M38: Restaurant (full service) | N38: 24
B39: Non-Residential | C39: Residential | D39: Semiheated | G39: Non-Residential | H39: Residential | I39: Semiheated | M39: Restaurant (quick service) | N39: 34
A40: Below-Grade Wall | B40: C-0.119 | C40: C-0.092 | D40: C-1.140 | F40: Below-Grade Wall | G40: C-1.140 | H40: C-1.140 | I40: C-1.140 | M40: Retail ( strip mall) | N40: 20
B41: Non-Residential | C41: Residential | D41: Semiheated | G41: Non-Residential | H41: Residential | I41: Semiheated | M41: Retail (Stand alone) | N41: 11
A42: Mass | B42: U-0.057 | C42: U-0.051 | D42: U-0.107 | F42: Mass | G42: ERROR | H42: ERROR | I42: ERROR | M42: School (primary) | N42: 22
A43: Steel-Joist | B43: U-0.033 | C43: U-0.033 | D43: U-0.052 | F43: Steel-Joist | G43: U-0.052 | H43: U-0.038 | I43: U-0.069 | M43: School (secondary and university) | N43: 22
A44: Wood-Framed and Other | B44: U-0.033 | C44: U-0.033 | D44: U-0.051 | F44: Wood-Framed and Other | G44: ERROR | H44: ERROR | I44: ERROR | M44: Warehouse (nonrefrigerated) | N44: 6
B45: Non-Residential | C45: Residential | D45: Semiheated | G45: Non-Residential | H45: Residential | I45: Semiheated
A46: Unheated | B46: F-0.520 | C46: F-0.520 | D46: F-0.730 | F46: Unheated | G46: F-0.520 | H46: F-0.730 | I46: F-0.7300
A47: Heated | B47: F-0.63 | C47: F-0.63 | D47: F-0.900 | F47: Heated | G47: ERROR | H47: ERROR | I47: ERROR
B48: Non-Residential | C48: Residential | D48: Semiheated | G48: Non-Residential | H48: Residential | I48: Semiheated
A49: Swinging | B49: U-0.370 | C49: U-0.370 | D49: U-0.370 | F49: Swinging | G49: U-0.700 | H49: U-0.700 | I49: U-0.700
A50: Nonswinging | B50: U-0.310 | C50: U-0.310 | D50: U-0.360 | F50: Nonswinging | G50: U-1.450 | H50: U-0.500 | I50: U-1.450
G53: Shivanie
A54: System 1: VAV with PFP boxes | B54: VAV
A55: System 10: PTAC | B55: Single-speed fan | G55: S11 system
A56: System 11: Packaged rooftop AC | B56: Single- or two-speed fan | G56: Water/ Ground | H56: Electric Res. | I56: Single Zone Residential System
A57: System 2: VAV with reheat | B57: VAV | G57: Air/ None | H57: Heat Pump | I57: Single Zone Non-Residential System
A58: System 3: Packaged VAV with PFP boxes | B58: VAV | H58: Fossil Fuel | I58: Other
A59: System 4: Packaged VAV with reheat | B59: VAV
A60: System 5: Two-pipe fan-coil | B60: Single- or two-speed fan | J60: G3.1.1-4 | R60: Sizes
A61: System 6: Water-source HP | B61: Single- or two-speed fan | G61: obsolete w new cover | J61: System No. | K61: System Type | L61: Fan Control | M61: Cooling Type | N61: Heating Type | O61: Efficiency | P61: Fan Power G3.1.2.9 [W] | R61: <17,000
A62: System 7: Four-pipe fan-coil | B62: Single- or two-speed fan | G62: Combo | H62: System | J62: System 1: PTAC | K62: Packaged terminal air conditioner | L62: Constant volume | M62: Direct expansion | N62: Hot-water fossil fuel boiler | O62: Cool: 3.2 COP -- Heat: Boiler | P62: Supply CFM * .3 | R62: >=17,000 and <65,000
A63: System 8: PTHP | B63: Single-speed fan | G63: Air/ NoneElectric Res.Other | H63: System 10 | J63: System 12: Single-zone, CV-HW | K63: Single-zone system | L63: Constant volume | M63: Chilled water | N63: Hot-water fossil fuel boiler | O63: Cool: Chiller -- Heat: Boiler | P63: bhp * 746 / fan motor efficiency | R63: >=65,000 and <135,000
A64: System 9: Packaged rooftop HP | B64: Single- or two-speed fan | G64: Air/ NoneElectric Res.Single Zone Non-Residential System | H64: System 8 | J64: System 3: PSZ-AC | K64: Packaged rooftop air conditioner | L64: Constant volume | M64: Direct expansion | N64: Fossil fuel furnace | O64: Cool: Table G3.5.1 -- Heat: Table G3.5.5 | P64: bhp * 746 / fan motor efficiency | R64: >=135,000 and <240,000
G65: Air/ NoneElectric Res.Single Zone Residential System | H65: System 8 | J65: System 5: Packaged VAV with Reheat | K65: Packaged rooftop VAV with reheat | L65: VAV | M65: Direct expansion | N65: Hot-water fossil fuel boiler | O65: Cool: Table G3.5.1 -- Heat: boiler | P65: bhp * 746 / fan motor efficiency | R65: >= 240,000 and <760,000
G66: Air/ NoneFossil Fuel Other | H66: System 4 | J66: System 7: VAV with reheat | K66: VAV with reheat | L66: VAV | M66: Chilled water | N66: Hot-water fossil fuel boiler | O66: Cool: Chiller -- Heat: Boiler | P66: bhp * 746 / fan motor efficiency | R66: >=760,000
G67: Air/ NoneFossil Fuel Single Zone Non-Residential System | H67: System 3 | J67: System 9: Heating and Ventilation | K67: Warm air furnace, gas fired | L67: Constant volume | M67: None | N67: Fossil fuel furnace | O67: Cool: none -- Heat: G3.5.5 | P67: Supply CFM x .3, if non mechanical cooling fan req: CFMnmc * .054
G68: Air/ NoneFossil Fuel Single Zone Residential System | H68: System 3
G69: Air/ NoneHeat Pump Other | H69: System 11
G70: Air/ NoneHeat Pump Single Zone Non-Residential System | H70: System 9
G71: Air/ NoneHeat Pump Single Zone Residential System | H71: System 9
A72: App. G | G72: Water/ GroundElectric Res.Other | H72: System 7
A73: Heated-only storage | B73: System 9: Heating and Ventilation | C73: Constant Volume | D73: Fossil fuel furnace | G73: Water/ GroundElectric Res.Single Zone Non-Residential System | H73: System 6 | J73: Section 11
A74: Nonresidential - < 3 floors and < 25,000 ft2 | B74: System 3: PSZ-AC | C74: Constant Volume | D74: Fossil fuel furnace | G74: Water/ GroundElectric Res.Single Zone Residential System | H74: System 5 | J74: Proposed | K74: Baseline Section 11 | L74: Fan Power s.11 | M74: Cooler Condensing Source | N74: Budget System Type | O74: Heating System Classification | P74: Efficiencies | S74: Master Value List
A75: Nonresidential - < 5 floors and 25,000 - 150,000 ft2 | B75: System 5: Packaged VAV with Reheat | C75: VAV | D75: Hot-water fossil fuel boiler | G75: Water/ GroundFossil Fuel Other | H75: System 2 | J75: Two-pipe fan coil | K75: System 5: Two-pipe fan-coil | L75: Refer to 6.5.3.1 | M75: Water/Ground | N75: Single-Zone Residential | O75: Electric Resistance | P75: Cool: Chiller -- Heat: Electric Resistance
A76: Nonresidential - > 5 floors or > 150,000 ft2 | B76: System 7: VAV with reheat | C76: VAV | D76: Hot-water fossil fuel boiler | G76: Water/ GroundFossil Fuel Single Zone Non-Residential System | H76: System 6 | J76: VAV with parallel fan-powered boxes | K76: System 1: VAV with PFP boxes | L76: Refer to 6.5.3.1 | M76: Water/Ground | N76: Other | O76: Electric Resistance | P76: Cool: Chiller -- Heat: Electric Resistance | S76: KEY | T76: Variable #1 | U76: Variable #2 | V76: Variable #3 | W76: System Type | X76: Fan Power | Y76: Efficiencies | Z76: Fan Airflow | AA76: Heating Type
A77: Nonresidential - 4-5 floors and < 25,000 ft2 | B77: System 5: Packaged VAV with Reheat | C77: VAV | D77: Hot-water fossil fuel boiler | G77: Water/ GroundFossil Fuel Single Zone Residential System | H77: System 1 | J77: Water-source heat pump | K77: System 6: Water-source HP | L77: Refer to 6.5.3.1 | M77: Water/Ground | N77: Single-Zone Residential | O77: Heat Pump | P77: Refer to Table 6.8.1-2 [Water to Air] (automated) | S77: =CONCATENATE(T:T,U:U,V:V) -> EtEcAFUECOPHSPFVariable #1Water/GroundAir/NoneWater/GroundWater/GroundWater/GroundWater/GroundWater/GroundWater/GroundWater/GroundWater/GroundWater/GroundAir/NoneAir/NoneAir/NoneAir/NoneAir/NoneAir/NoneAir/NoneAir/NoneAir/NoneVariable #2Electric Resistance Heat PumpFossil Fuel Electric Resistance Electric Resistance Electric Resistance Heat PumpHeat PumpHeat PumpFossil Fuel Fossil Fuel Fossil Fuel Electric Resistance Electric Resistance Electric Resistance Heat PumpHeat PumpHeat PumpFossil Fuel Fossil Fuel Fossil Fuel Variable #3Single-Zone Residential Single-Zone Non-Residential OtherSingle-Zone Residential Single-Zone Non-Residential OtherSingle-Zone Residential Single-Zone Non-Residential OtherSingle-Zone Residential Single-Zone Non-Residential OtherSingle-Zone Residential Single-Zone Non-Residential OtherSingle-Zone Residential Single-Zone Non-Residential OtherSingle-Zone Residential Single-Zone Non-Residential Other | T77: Water/Ground | U77: Electric Resistance | V77: Single-Zone Residential
A78: Public Assembly < 120,000 ft2 | B78: System 3: PSZ-AC | C78: Constant Volume | D78: Fossil fuel furnace | G78: Water/ GroundHeat Pump Other | H78: System 7 | J78: Four-pipe fan coil | K78: System 7: Four-pipe fan-coil | L78: Refer to 6.5.3.1 | M78: Water/Ground | N78: Single-Zone Non-Residential | O78: Fossil Fuel | P78: Cool: Chiller -- Heat: Boiler | S78: =CONCATENATE(T:T,U:U,V:V) -> EtEcAFUECOPHSPFVariable #1Water/GroundAir/NoneWater/GroundWater/GroundWater/GroundWater/GroundWater/GroundWater/GroundWater/GroundWater/GroundWater/GroundAir/NoneAir/NoneAir/NoneAir/NoneAir/NoneAir/NoneAir/NoneAir/NoneAir/NoneVariable #2Electric Resistance Heat PumpFossil Fuel Electric Resistance Electric Resistance Electric Resistance Heat PumpHeat PumpHeat PumpFossil Fuel Fossil Fuel Fossil Fuel Electric Resistance Electric Resistance Electric Resistance Heat PumpHeat PumpHeat PumpFossil Fuel Fossil Fuel Fossil Fuel Variable #3Single-Zone Residential Single-Zone Non-Residential OtherSingle-Zone Residential Single-Zone Non-Residential OtherSingle-Zone Residential Single-Zone Non-Residential OtherSingle-Zone Residential Single-Zone Non-Residential OtherSingle-Zone Residential Single-Zone Non-Residential OtherSingle-Zone Residential Single-Zone Non-Residential OtherSingle-Zone Residential Single-Zone Non-Residential Other | T78: Air/None | U78: Heat Pump | V78: Single-Zone Non-Residential
A79: Public Assembly > 120,000 ft2 | B79: System 12: Single-zone, CV-HW | C79: Constant Volume | D79: Hot-water fossil fuel boiler | G79: Water/ GroundHeat Pump Single Zone Non-Residential System | H79: System 6 | J79: VAV with reheat | K79: System 2: VAV with reheat | L79: Refer to 6.5.3.1 | M79: Water/Ground | N79: Other | O79: Fossil Fuel | P79: Cool: Chiller -- Heat: Boiler | S79: =CONCATENATE(T:T,U:U,V:V) -> EtEcAFUECOPHSPFVariable #1Water/GroundAir/NoneWater/GroundWater/GroundWater/GroundWater/GroundWater/GroundWater/GroundWater/GroundWater/GroundWater/GroundAir/NoneAir/NoneAir/NoneAir/NoneAir/NoneAir/NoneAir/NoneAir/NoneAir/NoneVariable #2Electric Resistance Heat PumpFossil Fuel Electric Resistance Electric Resistance Electric Resistance Heat PumpHeat PumpHeat PumpFossil Fuel Fossil Fuel Fossil Fuel Electric Resistance Electric Resistance Electric Resistance Heat PumpHeat PumpHeat PumpFossil Fuel Fossil Fuel Fossil Fuel Variable #3Single-Zone Residential Single-Zone Non-Residential OtherSingle-Zone Residential Single-Zone Non-Residential OtherSingle-Zone Residential Single-Zone Non-Residential OtherSingle-Zone Residential Single-Zone Non-Residential OtherSingle-Zone Residential Single-Zone Non-Residential OtherSingle-Zone Residential Single-Zone Non-Residential OtherSingle-Zone Residential Single-Zone Non-Residential Other | U79: Fossil Fuel | V79: Other
A80: Residential | B80: System 1: PTAC | C80: Constant Volume | D80: Hot-water fossil fuel boiler | G80: Water/ GroundHeat Pump Single Zone Residential System | H80: System 5 | J80: Packaged terminal heat pump | K80: System 8: PTHP | L80: Refer to 6.5.3.1 | M80: Air/None | N80: Single-Zone Residential | O80: Heat Pump | P80: Refer to Table 6.8.1-4 (automated) | S80: =CONCATENATE(T:T,U:U,V:V) -> EtEcAFUECOPHSPFVariable #1Water/GroundAir/NoneWater/GroundWater/GroundWater/GroundWater/GroundWater/GroundWater/GroundWater/GroundWater/GroundWater/GroundAir/NoneAir/NoneAir/NoneAir/NoneAir/NoneAir/NoneAir/NoneAir/NoneAir/NoneVariable #2Electric Resistance Heat PumpFossil Fuel Electric Resistance Electric Resistance Electric Resistance Heat PumpHeat PumpHeat PumpFossil Fuel Fossil Fuel Fossil Fuel Electric Resistance Electric Resistance Electric Resistance Heat PumpHeat PumpHeat PumpFossil Fuel Fossil Fuel Fossil Fuel Variable #3Single-Zone Residential Single-Zone Non-Residential OtherSingle-Zone Residential Single-Zone Non-Residential OtherSingle-Zone Residential Single-Zone Non-Residential OtherSingle-Zone Residential Single-Zone Non-Residential OtherSingle-Zone Residential Single-Zone Non-Residential OtherSingle-Zone Residential Single-Zone Non-Residential OtherSingle-Zone Residential Single-Zone Non-Residential Other
A81: Retail - < 2 floors | B81: System 3: PSZ-AC | C81: Constant Volume | D81: Fossil fuel furnace | J81: Packaged/split-system heat pump | K81: System 9: Packaged rooftop HP | L81: Refer to 6.5.3.1 | M81: Air/None | N81: Single-Zone Non-Residential | O81: Heat Pump | P81: Refer to Table 6.8.1-2 | S81: =CONCATENATE(T:T,U:U,V:V) -> EtEcAFUECOPHSPFVariable #1Water/GroundAir/NoneWater/GroundWater/GroundWater/GroundWater/GroundWater/GroundWater/GroundWater/GroundWater/GroundWater/GroundAir/NoneAir/NoneAir/NoneAir/NoneAir/NoneAir/NoneAir/NoneAir/NoneAir/NoneVariable #2Electric Resistance Heat PumpFossil Fuel Electric Resistance Electric Resistance Electric Resistance Heat PumpHeat PumpHeat PumpFossil Fuel Fossil Fuel Fossil Fuel Electric Resistance Electric Resistance Electric Resistance Heat PumpHeat PumpHeat PumpFossil Fuel Fossil Fuel Fossil Fuel Variable #3Single-Zone Residential Single-Zone Non-Residential OtherSingle-Zone Residential Single-Zone Non-Residential OtherSingle-Zone Residential Single-Zone Non-Residential OtherSingle-Zone Residential Single-Zone Non-Residential OtherSingle-Zone Residential Single-Zone Non-Residential OtherSingle-Zone Residential Single-Zone Non-Residential OtherSingle-Zone Residential Single-Zone Non-Residential Other | T81: Water/Ground | U81: Electric Resistance | V81: Single-Zone Residential | W81: System 5: Two-pipe fan-coil | X81: Refer to 6.5.3.1 | Y81: Cool: Chiller -- Heat: Electric Resistance | Z81: Single- or two-speed fan | AA81: Electric Resistance
J82: Packaged VAV with parallel fan-powered boxes | K82: System 3: Packaged VAV with PFP boxes | L82: Refer to 6.5.3.1 | M82: Air/None | N82: Other | O82: Fossil Fuel | P82: Cool: Table 6.8.1-1 -- Heat: Electric Resistance | S82: =CONCATENATE(T:T,U:U,V:V) -> EtEcAFUECOPHSPFVariable #1Water/GroundAir/NoneWater/GroundWater/GroundWater/GroundWater/GroundWater/GroundWater/GroundWater/GroundWater/GroundWater/GroundAir/NoneAir/NoneAir/NoneAir/NoneAir/NoneAir/NoneAir/NoneAir/NoneAir/NoneVariable #2Electric Resistance Heat PumpFossil Fuel Electric Resistance Electric Resistance Electric Resistance Heat PumpHeat PumpHeat PumpFossil Fuel Fossil Fuel Fossil Fuel Electric Resistance Electric Resistance Electric Resistance Heat PumpHeat PumpHeat PumpFossil Fuel Fossil Fuel Fossil Fuel Variable #3Single-Zone Residential Single-Zone Non-Residential OtherSingle-Zone Residential Single-Zone Non-Residential OtherSingle-Zone Residential Single-Zone Non-Residential OtherSingle-Zone Residential Single-Zone Non-Residential OtherSingle-Zone Residential Single-Zone Non-Residential OtherSingle-Zone Residential Single-Zone Non-Residential OtherSingle-Zone Residential Single-Zone Non-Residential Other | T82: Water/Ground | U82: Electric Resistance | V82: Single-Zone Non-Residential | W82: System 5: Two-pipe fan-coil | X82: Refer to 6.5.3.1 | Y82: Cool: Chiller -- Heat: Electric Resistance | Z82: Single- or two-speed fan | AA82: Electric Resistance
J83: Packaged terminal air conditioner | K83: System 10: PTAC | L83: Refer to 6.5.3.1 | M83: Air/None | N83: Single-Zone Residential | O83: Fossil Fuel | P83: Refer to Table 6.8.1-4 (automated) | S83: =CONCATENATE(T:T,U:U,V:V) -> EtEcAFUECOPHSPFVariable #1Water/GroundAir/NoneWater/GroundWater/GroundWater/GroundWater/GroundWater/GroundWater/GroundWater/GroundWater/GroundWater/GroundAir/NoneAir/NoneAir/NoneAir/NoneAir/NoneAir/NoneAir/NoneAir/NoneAir/NoneVariable #2Electric Resistance Heat PumpFossil Fuel Electric Resistance Electric Resistance Electric Resistance Heat PumpHeat PumpHeat PumpFossil Fuel Fossil Fuel Fossil Fuel Electric Resistance Electric Resistance Electric Resistance Heat PumpHeat PumpHeat PumpFossil Fuel Fossil Fuel Fossil Fuel Variable #3Single-Zone Residential Single-Zone Non-Residential OtherSingle-Zone Residential Single-Zone Non-Residential OtherSingle-Zone Residential Single-Zone Non-Residential OtherSingle-Zone Residential Single-Zone Non-Residential OtherSingle-Zone Residential Single-Zone Non-Residential OtherSingle-Zone Residential Single-Zone Non-Residential OtherSingle-Zone Residential Single-Zone Non-Residential Other | T83: Water/Ground | U83: Electric Resistance | V83: Other | W83: System 1: VAV with PFP boxes | X83: Refer to 6.5.3.1 | Y83: Cool: Chiller -- Heat: Electric Resistance | Z83: VAV | AA83: Electric Resistance
B84: System 1: PTAC | C84: Constant Volume | J84: Packaged/split-system air conditioner | K84: System 11: Packaged rooftop AC | L84: Refer to 6.5.3.1 | M84: Air/None | N84: Single-Zone Non-Residential | O84: Fossil Fuel | P84: Cool: Table 6.8.1-1 -- Heat: Table 6.8.1-5 | S84: =CONCATENATE(T:T,U:U,V:V) -> EtEcAFUECOPHSPFVariable #1Water/GroundAir/NoneWater/GroundWater/GroundWater/GroundWater/GroundWater/GroundWater/GroundWater/GroundWater/GroundWater/GroundAir/NoneAir/NoneAir/NoneAir/NoneAir/NoneAir/NoneAir/NoneAir/NoneAir/NoneVariable #2Electric Resistance Heat PumpFossil Fuel Electric Resistance Electric Resistance Electric Resistance Heat PumpHeat PumpHeat PumpFossil Fuel Fossil Fuel Fossil Fuel Electric Resistance Electric Resistance Electric Resistance Heat PumpHeat PumpHeat PumpFossil Fuel Fossil Fuel Fossil Fuel Variable #3Single-Zone Residential Single-Zone Non-Residential OtherSingle-Zone Residential Single-Zone Non-Residential OtherSingle-Zone Residential Single-Zone Non-Residential OtherSingle-Zone Residential Single-Zone Non-Residential OtherSingle-Zone Residential Single-Zone Non-Residential OtherSingle-Zone Residential Single-Zone Non-Residential OtherSingle-Zone Residential Single-Zone Non-Residential Other | T84: Water/Ground | U84: Heat Pump | V84: Single-Zone Residential | W84: System 6: Water-source HP | X84: Refer to 6.5.3.1 | Y84: Refer to Table 6.8.1-2 [Water to Air] (automated) | Z84: Single- or two-speed fan | AA84: Electric Heat Pump and boiler
B85: System 12: Single-zone, CV-HW | C85: Constant Volume | J85: Packaged VAV with reheat | K85: System 4: Packaged VAV with reheat | L85: Refer to 6.5.3.1 | M85: Air/None | N85: Other | O85: Fossil Fuel | P85: Cool: Table 6.8.1-1 -- Heat: Boiler | S85: =CONCATENATE(T:T,U:U,V:V) -> EtEcAFUECOPHSPFVariable #1Water/GroundAir/NoneWater/GroundWater/GroundWater/GroundWater/GroundWater/GroundWater/GroundWater/GroundWater/GroundWater/GroundAir/NoneAir/NoneAir/NoneAir/NoneAir/NoneAir/NoneAir/NoneAir/NoneAir/NoneVariable #2Electric Resistance Heat PumpFossil Fuel Electric Resistance Electric Resistance Electric Resistance Heat PumpHeat PumpHeat PumpFossil Fuel Fossil Fuel Fossil Fuel Electric Resistance Electric Resistance Electric Resistance Heat PumpHeat PumpHeat PumpFossil Fuel Fossil Fuel Fossil Fuel Variable #3Single-Zone Residential Single-Zone Non-Residential OtherSingle-Zone Residential Single-Zone Non-Residential OtherSingle-Zone Residential Single-Zone Non-Residential OtherSingle-Zone Residential Single-Zone Non-Residential OtherSingle-Zone Residential Single-Zone Non-Residential OtherSingle-Zone Residential Single-Zone Non-Residential OtherSingle-Zone Residential Single-Zone Non-Residential Other | T85: Water/Ground | U85: Heat Pump | V85: Single-Zone Non-Residential | W85: System 6: Water-source HP | X85: Refer to 6.5.3.1 | Y85: Refer to Table 6.8.1-2 [Water to Air] (automated) | Z85: Single- or two-speed fan | AA85: Electric Heat Pump and boiler
B86: System 3: PSZ-AC | C86: Constant Volume | J86: VRF | K86: System 9: Packaged rooftop HP | L86: Refer to 6.5.3.1 | M86: Air/None | N86: Single-Zone Residential | O86: Heat Pump | P86: Refer to Table 6.8.1-2 | S86: =CONCATENATE(T:T,U:U,V:V) -> EtEcAFUECOPHSPFVariable #1Water/GroundAir/NoneWater/GroundWater/GroundWater/GroundWater/GroundWater/GroundWater/GroundWater/GroundWater/GroundWater/GroundAir/NoneAir/NoneAir/NoneAir/NoneAir/NoneAir/NoneAir/NoneAir/NoneAir/NoneVariable #2Electric Resistance Heat PumpFossil Fuel Electric Resistance Electric Resistance Electric Resistance Heat PumpHeat PumpHeat PumpFossil Fuel Fossil Fuel Fossil Fuel Electric Resistance Electric Resistance Electric Resistance Heat PumpHeat PumpHeat PumpFossil Fuel Fossil Fuel Fossil Fuel Variable #3Single-Zone Residential Single-Zone Non-Residential OtherSingle-Zone Residential Single-Zone Non-Residential OtherSingle-Zone Residential Single-Zone Non-Residential OtherSingle-Zone Residential Single-Zone Non-Residential OtherSingle-Zone Residential Single-Zone Non-Residential OtherSingle-Zone Residential Single-Zone Non-Residential OtherSingle-Zone Residential Single-Zone Non-Residential Other | T86: Water/Ground | U86: Heat Pump | V86: Other | W86: System 6: Water-source HP | X86: Refer to 6.5.3.1 | Y86: Refer to Table 6.8.1-2 [Water to Air] (automated) | Z86: Single- or two-speed fan | AA86: Electric Heat Pump and boiler
B87: System 3: PSZ-AC | C87: Constant Volume | J87: Unit heaters | K87: System 11: Packaged rooftop AC | L87: Refer to 6.5.3.1 | M87: Air/None | N87: Single-Zone Non-Residential | O87: Fossil Fuel | P87: Cool: Table 6.8.1-1 -- Heat: Table 6.8.1-5 | S87: =CONCATENATE(T:T,U:U,V:V) -> EtEcAFUECOPHSPFVariable #1Water/GroundAir/NoneWater/GroundWater/GroundWater/GroundWater/GroundWater/GroundWater/GroundWater/GroundWater/GroundWater/GroundAir/NoneAir/NoneAir/NoneAir/NoneAir/NoneAir/NoneAir/NoneAir/NoneAir/NoneVariable #2Electric Resistance Heat PumpFossil Fuel Electric Resistance Electric Resistance Electric Resistance Heat PumpHeat PumpHeat PumpFossil Fuel Fossil Fuel Fossil Fuel Electric Resistance Electric Resistance Electric Resistance Heat PumpHeat PumpHeat PumpFossil Fuel Fossil Fuel Fossil Fuel Variable #3Single-Zone Residential Single-Zone Non-Residential OtherSingle-Zone Residential Single-Zone Non-Residential OtherSingle-Zone Residential Single-Zone Non-Residential OtherSingle-Zone Residential Single-Zone Non-Residential OtherSingle-Zone Residential Single-Zone Non-Residential OtherSingle-Zone Residential Single-Zone Non-Residential OtherSingle-Zone Residential Single-Zone Non-Residential Other | T87: Water/Ground | U87: Fossil Fuel | V87: Single-Zone Residential | W87: System 7: Four-pipe fan-coil | X87: Refer to 6.5.3.1 | Y87: Cool: Chiller -- Heat: Boiler | Z87: Single- or two-speed fan | AA87: Hot-water fossil fuel boiler
B88: System 3: PSZ-AC | C88: Constant Volume | S88: =CONCATENATE(T:T,U:U,V:V) -> EtEcAFUECOPHSPFVariable #1Water/GroundAir/NoneWater/GroundWater/GroundWater/GroundWater/GroundWater/GroundWater/GroundWater/GroundWater/GroundWater/GroundAir/NoneAir/NoneAir/NoneAir/NoneAir/NoneAir/NoneAir/NoneAir/NoneAir/NoneVariable #2Electric Resistance Heat PumpFossil Fuel Electric Resistance Electric Resistance Electric Resistance Heat PumpHeat PumpHeat PumpFossil Fuel Fossil Fuel Fossil Fuel Electric Resistance Electric Resistance Electric Resistance Heat PumpHeat PumpHeat PumpFossil Fuel Fossil Fuel Fossil Fuel Variable #3Single-Zone Residential Single-Zone Non-Residential OtherSingle-Zone Residential Single-Zone Non-Residential OtherSingle-Zone Residential Single-Zone Non-Residential OtherSingle-Zone Residential Single-Zone Non-Residential OtherSingle-Zone Residential Single-Zone Non-Residential OtherSingle-Zone Residential Single-Zone Non-Residential OtherSingle-Zone Residential Single-Zone Non-Residential Other | T88: Water/Ground | U88: Fossil Fuel | V88: Single-Zone Non-Residential | W88: System 7: Four-pipe fan-coil | X88: Refer to 6.5.3.1 | Y88: Cool: Chiller -- Heat: Boiler | Z88: VAV | AA88: Hot-water fossil fuel boiler
B89: System 5: Packaged VAV with Reheat | C89: VAV | S89: =CONCATENATE(T:T,U:U,V:V) -> EtEcAFUECOPHSPFVariable #1Water/GroundAir/NoneWater/GroundWater/GroundWater/GroundWater/GroundWater/GroundWater/GroundWater/GroundWater/GroundWater/GroundAir/NoneAir/NoneAir/NoneAir/NoneAir/NoneAir/NoneAir/NoneAir/NoneAir/NoneVariable #2Electric Resistance Heat PumpFossil Fuel Electric Resistance Electric Resistance Electric Resistance Heat PumpHeat PumpHeat PumpFossil Fuel Fossil Fuel Fossil Fuel Electric Resistance Electric Resistance Electric Resistance Heat PumpHeat PumpHeat PumpFossil Fuel Fossil Fuel Fossil Fuel Variable #3Single-Zone Residential Single-Zone Non-Residential OtherSingle-Zone Residential Single-Zone Non-Residential OtherSingle-Zone Residential Single-Zone Non-Residential OtherSingle-Zone Residential Single-Zone Non-Residential OtherSingle-Zone Residential Single-Zone Non-Residential OtherSingle-Zone Residential Single-Zone Non-Residential OtherSingle-Zone Residential Single-Zone Non-Residential Other | T89: Water/Ground | U89: Fossil Fuel | V89: Other | W89: System 2: VAV with reheat | X89: Refer to 6.5.3.1 | Y89: Cool: Chiller -- Heat: Boiler | Z89: VAV | AA89: Hot-water fossil fuel boiler
B90: System 5: Packaged VAV with Reheat | C90: VAV | S90: =CONCATENATE(T:T,U:U,V:V) -> EtEcAFUECOPHSPFVariable #1Water/GroundAir/NoneWater/GroundWater/GroundWater/GroundWater/GroundWater/GroundWater/GroundWater/GroundWater/GroundWater/GroundAir/NoneAir/NoneAir/NoneAir/NoneAir/NoneAir/NoneAir/NoneAir/NoneAir/NoneVariable #2Electric Resistance Heat PumpFossil Fuel Electric Resistance Electric Resistance Electric Resistance Heat PumpHeat PumpHeat PumpFossil Fuel Fossil Fuel Fossil Fuel Electric Resistance Electric Resistance Electric Resistance Heat PumpHeat PumpHeat PumpFossil Fuel Fossil Fuel Fossil Fuel Variable #3Single-Zone Residential Single-Zone Non-Residential OtherSingle-Zone Residential Single-Zone Non-Residential OtherSingle-Zone Residential Single-Zone Non-Residential OtherSingle-Zone Residential Single-Zone Non-Residential OtherSingle-Zone Residential Single-Zone Non-Residential OtherSingle-Zone Residential Single-Zone Non-Residential OtherSingle-Zone Residential Single-Zone Non-Residential Other | T90: Air/None | U90: Electric Resistance | V90: Single-Zone Residential | W90: System 8: PTHP | X90: Refer to 6.5.3.1 | Y90: Refer to Table 6.8.1-4 (automated) | Z90: Single-speed fan | AA90: Electric Heat Pump
B91: System 7: VAV with reheat | C91: VAV | S91: =CONCATENATE(T:T,U:U,V:V) -> EtEcAFUECOPHSPFVariable #1Water/GroundAir/NoneWater/GroundWater/GroundWater/GroundWater/GroundWater/GroundWater/GroundWater/GroundWater/GroundWater/GroundAir/NoneAir/NoneAir/NoneAir/NoneAir/NoneAir/NoneAir/NoneAir/NoneAir/NoneVariable #2Electric Resistance Heat PumpFossil Fuel Electric Resistance Electric Resistance Electric Resistance Heat PumpHeat PumpHeat PumpFossil Fuel Fossil Fuel Fossil Fuel Electric Resistance Electric Resistance Electric Resistance Heat PumpHeat PumpHeat PumpFossil Fuel Fossil Fuel Fossil Fuel Variable #3Single-Zone Residential Single-Zone Non-Residential OtherSingle-Zone Residential Single-Zone Non-Residential OtherSingle-Zone Residential Single-Zone Non-Residential OtherSingle-Zone Residential Single-Zone Non-Residential OtherSingle-Zone Residential Single-Zone Non-Residential OtherSingle-Zone Residential Single-Zone Non-Residential OtherSingle-Zone Residential Single-Zone Non-Residential Other | T91: Air/None | U91: Electric Resistance | V91: Single-Zone Non-Residential | W91: System 9: Packaged rooftop HP | X91: Refer to 6.5.3.1 | Y91: Refer to Table 6.8.1-2 | Z91: Single- or two-speed fan | AA91: Electric Heat Pump
B92: System 9: Heating and Ventilation | C92: Constant Volume | S92: =CONCATENATE(T:T,U:U,V:V) -> EtEcAFUECOPHSPFVariable #1Water/GroundAir/NoneWater/GroundWater/GroundWater/GroundWater/GroundWater/GroundWater/GroundWater/GroundWater/GroundWater/GroundAir/NoneAir/NoneAir/NoneAir/NoneAir/NoneAir/NoneAir/NoneAir/NoneAir/NoneVariable #2Electric Resistance Heat PumpFossil Fuel Electric Resistance Electric Resistance Electric Resistance Heat PumpHeat PumpHeat PumpFossil Fuel Fossil Fuel Fossil Fuel Electric Resistance Electric Resistance Electric Resistance Heat PumpHeat PumpHeat PumpFossil Fuel Fossil Fuel Fossil Fuel Variable #3Single-Zone Residential Single-Zone Non-Residential OtherSingle-Zone Residential Single-Zone Non-Residential OtherSingle-Zone Residential Single-Zone Non-Residential OtherSingle-Zone Residential Single-Zone Non-Residential OtherSingle-Zone Residential Single-Zone Non-Residential OtherSingle-Zone Residential Single-Zone Non-Residential OtherSingle-Zone Residential Single-Zone Non-Residential Other | T92: Air/None | U92: Electric Resistance | V92: Other | W92: System 3: Packaged VAV with PFP boxes | X92: Refer to 6.5.3.1 | Y92: Cool: Table 6.8.1-1 -- Heat: Electric Resistance | Z92: VAV | AA92: Electric Resistance
S93: =CONCATENATE(T:T,U:U,V:V) -> EtEcAFUECOPHSPFVariable #1Water/GroundAir/NoneWater/GroundWater/GroundWater/GroundWater/GroundWater/GroundWater/GroundWater/GroundWater/GroundWater/GroundAir/NoneAir/NoneAir/NoneAir/NoneAir/NoneAir/NoneAir/NoneAir/NoneAir/NoneVariable #2Electric Resistance Heat PumpFossil Fuel Electric Resistance Electric Resistance Electric Resistance Heat PumpHeat PumpHeat PumpFossil Fuel Fossil Fuel Fossil Fuel Electric Resistance Electric Resistance Electric Resistance Heat PumpHeat PumpHeat PumpFossil Fuel Fossil Fuel Fossil Fuel Variable #3Single-Zone Residential Single-Zone Non-Residential OtherSingle-Zone Residential Single-Zone Non-Residential OtherSingle-Zone Residential Single-Zone Non-Residential OtherSingle-Zone Residential Single-Zone Non-Residential OtherSingle-Zone Residential Single-Zone Non-Residential OtherSingle-Zone Residential Single-Zone Non-Residential OtherSingle-Zone Residential Single-Zone Non-Residential Other | T93: Air/None | U93: Heat Pump | V93: Single-Zone Residential | W93: System 8: PTHP | X93: Refer to 6.5.3.1 | Y93: Refer to Table 6.8.1-4 (automated) | Z93: Single-speed fan | AA93: Electric Heat Pump
S94: =CONCATENATE(T:T,U:U,V:V) -> EtEcAFUECOPHSPFVariable #1Water/GroundAir/NoneWater/GroundWater/GroundWater/GroundWater/GroundWater/GroundWater/GroundWater/GroundWater/GroundWater/GroundAir/NoneAir/NoneAir/NoneAir/NoneAir/NoneAir/NoneAir/NoneAir/NoneAir/NoneVariable #2Electric Resistance Heat PumpFossil Fuel Electric Resistance Electric Resistance Electric Resistance Heat PumpHeat PumpHeat PumpFossil Fuel Fossil Fuel Fossil Fuel Electric Resistance Electric Resistance Electric Resistance Heat PumpHeat PumpHeat PumpFossil Fuel Fossil Fuel Fossil Fuel Variable #3Single-Zone Residential Single-Zone Non-Residential OtherSingle-Zone Residential Single-Zone Non-Residential OtherSingle-Zone Residential Single-Zone Non-Residential OtherSingle-Zone Residential Single-Zone Non-Residential OtherSingle-Zone Residential Single-Zone Non-Residential OtherSingle-Zone Residential Single-Zone Non-Residential OtherSingle-Zone Residential Single-Zone Non-Residential Other | T94: Air/None | U94: Heat Pump | V94: Single-Zone Non-Residential | W94: System 9: Packaged rooftop HP | X94: Refer to 6.5.3.1 | Y94: Refer to Table 6.8.1-2 | Z94: Single- or two-speed fan | AA94: Electric Heat Pump
A95: All Others | B95: Gas Storage Water Heater | S95: =CONCATENATE(T:T,U:U,V:V) -> EtEcAFUECOPHSPFVariable #1Water/GroundAir/NoneWater/GroundWater/GroundWater/GroundWater/GroundWater/GroundWater/GroundWater/GroundWater/GroundWater/GroundAir/NoneAir/NoneAir/NoneAir/NoneAir/NoneAir/NoneAir/NoneAir/NoneAir/NoneVariable #2Electric Resistance Heat PumpFossil Fuel Electric Resistance Electric Resistance Electric Resistance Heat PumpHeat PumpHeat PumpFossil Fuel Fossil Fuel Fossil Fuel Electric Resistance Electric Resistance Electric Resistance Heat PumpHeat PumpHeat PumpFossil Fuel Fossil Fuel Fossil Fuel Variable #3Single-Zone Residential Single-Zone Non-Residential OtherSingle-Zone Residential Single-Zone Non-Residential OtherSingle-Zone Residential Single-Zone Non-Residential OtherSingle-Zone Residential Single-Zone Non-Residential OtherSingle-Zone Residential Single-Zone Non-Residential OtherSingle-Zone Residential Single-Zone Non-Residential OtherSingle-Zone Residential Single-Zone Non-Residential Other | T95: Air/None | U95: Heat Pump | V95: Other | W95: System 3: Packaged VAV with PFP boxes | X95: Refer to 6.5.3.1 | Y95: Cool: Table 6.8.1-1 -- Heat: Electric Resistance | Z95: VAV | AA95: Electric Resistance
A96: Automotive facility | B96: Gas Storage Water Heater | S96: =CONCATENATE(T:T,U:U,V:V) -> EtEcAFUECOPHSPFVariable #1Water/GroundAir/NoneWater/GroundWater/GroundWater/GroundWater/GroundWater/GroundWater/GroundWater/GroundWater/GroundWater/GroundAir/NoneAir/NoneAir/NoneAir/NoneAir/NoneAir/NoneAir/NoneAir/NoneAir/NoneVariable #2Electric Resistance Heat PumpFossil Fuel Electric Resistance Electric Resistance Electric Resistance Heat PumpHeat PumpHeat PumpFossil Fuel Fossil Fuel Fossil Fuel Electric Resistance Electric Resistance Electric Resistance Heat PumpHeat PumpHeat PumpFossil Fuel Fossil Fuel Fossil Fuel Variable #3Single-Zone Residential Single-Zone Non-Residential OtherSingle-Zone Residential Single-Zone Non-Residential OtherSingle-Zone Residential Single-Zone Non-Residential OtherSingle-Zone Residential Single-Zone Non-Residential OtherSingle-Zone Residential Single-Zone Non-Residential OtherSingle-Zone Residential Single-Zone Non-Residential OtherSingle-Zone Residential Single-Zone Non-Residential Other | T96: Air/None | U96: Fossil Fuel | V96: Single-Zone Residential | W96: System 10: PTAC | X96: Refer to 6.5.3.1 | Y96: Refer to Table 6.8.1-4 (automated) | Z96: Single-speed fan | AA96: Hot-water fossil fuel boiler
A97: Convenience Store | B97: Electric Resistance Storage Water Heater | J97: =CONCATENATE(K:K,L:L,M:M) -> System TypePackaged terminal air conditionerSingle-zone systemPackaged rooftop air conditionerPackaged rooftop VAV with reheatVAV with reheatWarm air furnace, gas firedBaseline Section 11System 5: Two-pipe fan-coilSystem 1: VAV with PFP boxesSystem 6: Water-source HPSystem 7: Four-pipe fan-coilSystem 2: VAV with reheatSystem 8: PTHPSystem 9: Packaged rooftop HPSystem 3: Packaged VAV with PFP boxesSystem 10: PTACSystem 11: Packaged rooftop ACSystem 4: Packaged VAV with reheatSystem 9: Packaged rooftop HPSystem 11: Packaged rooftop ACFan ControlConstant volumeConstant volumeConstant volumeVAVVAVConstant volumeFan Power s.11Refer to 6.5.3.1 Refer to 6.5.3.1 Refer to 6.5.3.1 Refer to 6.5.3.1 Refer to 6.5.3.1 Refer to 6.5.3.1 Refer to 6.5.3.1 Refer to 6.5.3.1 Refer to 6.5.3.1 Refer to 6.5.3.1 Refer to 6.5.3.1 Refer to 6.5.3.1 Refer to 6.5.3.1 40All OtherDormitoryHealthcare/hospitalHotel/motelMultifamilyOfficeRestaurantRetailSchoolWarehouseWeighted AverageGrocery StoreHealthcare (hospital)HospitalHotel/motel (< 75 rooms)Hotel/motel (> 75 rooms)MultifamilyOffice (< 5000 ft2)Office (> 50,000 ft2)Office (5000 - 50,000 ft2)OtherRestaurant (full service)Restaurant (quick service)Retail ( strip mall)Retail (Stand alone)School (primary)School (secondary and university)Warehouse (nonrefrigerated)Cooling TypeDirect expansionChilled waterDirect expansionDirect expansionChilled waterNoneCooler Condensing SourceWater/GroundWater/GroundWater/GroundWater/GroundWater/GroundAir/NoneAir/NoneAir/NoneAir/NoneAir/NoneAir/NoneAir/NoneAir/None | S97: =CONCATENATE(T:T,U:U,V:V) -> EtEcAFUECOPHSPFVariable #1Water/GroundAir/NoneWater/GroundWater/GroundWater/GroundWater/GroundWater/GroundWater/GroundWater/GroundWater/GroundWater/GroundAir/NoneAir/NoneAir/NoneAir/NoneAir/NoneAir/NoneAir/NoneAir/NoneAir/NoneVariable #2Electric Resistance Heat PumpFossil Fuel Electric Resistance Electric Resistance Electric Resistance Heat PumpHeat PumpHeat PumpFossil Fuel Fossil Fuel Fossil Fuel Electric Resistance Electric Resistance Electric Resistance Heat PumpHeat PumpHeat PumpFossil Fuel Fossil Fuel Fossil Fuel Variable #3Single-Zone Residential Single-Zone Non-Residential OtherSingle-Zone Residential Single-Zone Non-Residential OtherSingle-Zone Residential Single-Zone Non-Residential OtherSingle-Zone Residential Single-Zone Non-Residential OtherSingle-Zone Residential Single-Zone Non-Residential OtherSingle-Zone Residential Single-Zone Non-Residential OtherSingle-Zone Residential Single-Zone Non-Residential Other | T97: Air/None | U97: Fossil Fuel | V97: Single-Zone Non-Residential | W97: System 11: Packaged rooftop AC | X97: Refer to 6.5.3.1 | Y97: Cool: Table 6.8.1-1 -- Heat: Table 6.8.1-5 | Z97: Single- or two-speed fan | AA97: Fossil Fuel Furnace
A98: Convention center | B98: Electric Resistance Storage Water Heater | J98: =CONCATENATE(K:K,L:L,M:M) -> System TypePackaged terminal air conditionerSingle-zone systemPackaged rooftop air conditionerPackaged rooftop VAV with reheatVAV with reheatWarm air furnace, gas firedBaseline Section 11System 5: Two-pipe fan-coilSystem 1: VAV with PFP boxesSystem 6: Water-source HPSystem 7: Four-pipe fan-coilSystem 2: VAV with reheatSystem 8: PTHPSystem 9: Packaged rooftop HPSystem 3: Packaged VAV with PFP boxesSystem 10: PTACSystem 11: Packaged rooftop ACSystem 4: Packaged VAV with reheatSystem 9: Packaged rooftop HPSystem 11: Packaged rooftop ACFan ControlConstant volumeConstant volumeConstant volumeVAVVAVConstant volumeFan Power s.11Refer to 6.5.3.1 Refer to 6.5.3.1 Refer to 6.5.3.1 Refer to 6.5.3.1 Refer to 6.5.3.1 Refer to 6.5.3.1 Refer to 6.5.3.1 Refer to 6.5.3.1 Refer to 6.5.3.1 Refer to 6.5.3.1 Refer to 6.5.3.1 Refer to 6.5.3.1 Refer to 6.5.3.1 40All OtherDormitoryHealthcare/hospitalHotel/motelMultifamilyOfficeRestaurantRetailSchoolWarehouseWeighted AverageGrocery StoreHealthcare (hospital)HospitalHotel/motel (< 75 rooms)Hotel/motel (> 75 rooms)MultifamilyOffice (< 5000 ft2)Office (> 50,000 ft2)Office (5000 - 50,000 ft2)OtherRestaurant (full service)Restaurant (quick service)Retail ( strip mall)Retail (Stand alone)School (primary)School (secondary and university)Warehouse (nonrefrigerated)Cooling TypeDirect expansionChilled waterDirect expansionDirect expansionChilled waterNoneCooler Condensing SourceWater/GroundWater/GroundWater/GroundWater/GroundWater/GroundAir/NoneAir/NoneAir/NoneAir/NoneAir/NoneAir/NoneAir/NoneAir/None | S98: =CONCATENATE(T:T,U:U,V:V) -> EtEcAFUECOPHSPFVariable #1Water/GroundAir/NoneWater/GroundWater/GroundWater/GroundWater/GroundWater/GroundWater/GroundWater/GroundWater/GroundWater/GroundAir/NoneAir/NoneAir/NoneAir/NoneAir/NoneAir/NoneAir/NoneAir/NoneAir/NoneVariable #2Electric Resistance Heat PumpFossil Fuel Electric Resistance Electric Resistance Electric Resistance Heat PumpHeat PumpHeat PumpFossil Fuel Fossil Fuel Fossil Fuel Electric Resistance Electric Resistance Electric Resistance Heat PumpHeat PumpHeat PumpFossil Fuel Fossil Fuel Fossil Fuel Variable #3Single-Zone Residential Single-Zone Non-Residential OtherSingle-Zone Residential Single-Zone Non-Residential OtherSingle-Zone Residential Single-Zone Non-Residential OtherSingle-Zone Residential Single-Zone Non-Residential OtherSingle-Zone Residential Single-Zone Non-Residential OtherSingle-Zone Residential Single-Zone Non-Residential OtherSingle-Zone Residential Single-Zone Non-Residential Other | T98: Air/None | U98: Fossil Fuel | V98: Other | W98: System 4: Packaged VAV with reheat | X98: Refer to 6.5.3.1 | Y98: Cool: Table 6.8.1-1 -- Heat: Boiler | Z98: VAV | AA98: Hot-water fossil fuel boiler
A99: Courthouse | B99: Electric Resistance Storage Water Heater | J99: =CONCATENATE(K:K,L:L,M:M) -> System TypePackaged terminal air conditionerSingle-zone systemPackaged rooftop air conditionerPackaged rooftop VAV with reheatVAV with reheatWarm air furnace, gas firedBaseline Section 11System 5: Two-pipe fan-coilSystem 1: VAV with PFP boxesSystem 6: Water-source HPSystem 7: Four-pipe fan-coilSystem 2: VAV with reheatSystem 8: PTHPSystem 9: Packaged rooftop HPSystem 3: Packaged VAV with PFP boxesSystem 10: PTACSystem 11: Packaged rooftop ACSystem 4: Packaged VAV with reheatSystem 9: Packaged rooftop HPSystem 11: Packaged rooftop ACFan ControlConstant volumeConstant volumeConstant volumeVAVVAVConstant volumeFan Power s.11Refer to 6.5.3.1 Refer to 6.5.3.1 Refer to 6.5.3.1 Refer to 6.5.3.1 Refer to 6.5.3.1 Refer to 6.5.3.1 Refer to 6.5.3.1 Refer to 6.5.3.1 Refer to 6.5.3.1 Refer to 6.5.3.1 Refer to 6.5.3.1 Refer to 6.5.3.1 Refer to 6.5.3.1 40All OtherDormitoryHealthcare/hospitalHotel/motelMultifamilyOfficeRestaurantRetailSchoolWarehouseWeighted AverageGrocery StoreHealthcare (hospital)HospitalHotel/motel (< 75 rooms)Hotel/motel (> 75 rooms)MultifamilyOffice (< 5000 ft2)Office (> 50,000 ft2)Office (5000 - 50,000 ft2)OtherRestaurant (full service)Restaurant (quick service)Retail ( strip mall)Retail (Stand alone)School (primary)School (secondary and university)Warehouse (nonrefrigerated)Cooling TypeDirect expansionChilled waterDirect expansionDirect expansionChilled waterNoneCooler Condensing SourceWater/GroundWater/GroundWater/GroundWater/GroundWater/GroundAir/NoneAir/NoneAir/NoneAir/NoneAir/NoneAir/NoneAir/NoneAir/None
A100: Dining: bar lounge/leisure | B100: Gas Storage Water Heater | J100: =CONCATENATE(K:K,L:L,M:M) -> System TypePackaged terminal air conditionerSingle-zone systemPackaged rooftop air conditionerPackaged rooftop VAV with reheatVAV with reheatWarm air furnace, gas firedBaseline Section 11System 5: Two-pipe fan-coilSystem 1: VAV with PFP boxesSystem 6: Water-source HPSystem 7: Four-pipe fan-coilSystem 2: VAV with reheatSystem 8: PTHPSystem 9: Packaged rooftop HPSystem 3: Packaged VAV with PFP boxesSystem 10: PTACSystem 11: Packaged rooftop ACSystem 4: Packaged VAV with reheatSystem 9: Packaged rooftop HPSystem 11: Packaged rooftop ACFan ControlConstant volumeConstant volumeConstant volumeVAVVAVConstant volumeFan Power s.11Refer to 6.5.3.1 Refer to 6.5.3.1 Refer to 6.5.3.1 Refer to 6.5.3.1 Refer to 6.5.3.1 Refer to 6.5.3.1 Refer to 6.5.3.1 Refer to 6.5.3.1 Refer to 6.5.3.1 Refer to 6.5.3.1 Refer to 6.5.3.1 Refer to 6.5.3.1 Refer to 6.5.3.1 40All OtherDormitoryHealthcare/hospitalHotel/motelMultifamilyOfficeRestaurantRetailSchoolWarehouseWeighted AverageGrocery StoreHealthcare (hospital)HospitalHotel/motel (< 75 rooms)Hotel/motel (> 75 rooms)MultifamilyOffice (< 5000 ft2)Office (> 50,000 ft2)Office (5000 - 50,000 ft2)OtherRestaurant (full service)Restaurant (quick service)Retail ( strip mall)Retail (Stand alone)School (primary)School (secondary and university)Warehouse (nonrefrigerated)Cooling TypeDirect expansionChilled waterDirect expansionDirect expansionChilled waterNoneCooler Condensing SourceWater/GroundWater/GroundWater/GroundWater/GroundWater/GroundAir/NoneAir/NoneAir/NoneAir/NoneAir/NoneAir/NoneAir/NoneAir/None
A101: Dining: cafeteria/fast food | B101: Gas Storage Water Heater | J101: =CONCATENATE(K:K,L:L,M:M) -> System TypePackaged terminal air conditionerSingle-zone systemPackaged rooftop air conditionerPackaged rooftop VAV with reheatVAV with reheatWarm air furnace, gas firedBaseline Section 11System 5: Two-pipe fan-coilSystem 1: VAV with PFP boxesSystem 6: Water-source HPSystem 7: Four-pipe fan-coilSystem 2: VAV with reheatSystem 8: PTHPSystem 9: Packaged rooftop HPSystem 3: Packaged VAV with PFP boxesSystem 10: PTACSystem 11: Packaged rooftop ACSystem 4: Packaged VAV with reheatSystem 9: Packaged rooftop HPSystem 11: Packaged rooftop ACFan ControlConstant volumeConstant volumeConstant volumeVAVVAVConstant volumeFan Power s.11Refer to 6.5.3.1 Refer to 6.5.3.1 Refer to 6.5.3.1 Refer to 6.5.3.1 Refer to 6.5.3.1 Refer to 6.5.3.1 Refer to 6.5.3.1 Refer to 6.5.3.1 Refer to 6.5.3.1 Refer to 6.5.3.1 Refer to 6.5.3.1 Refer to 6.5.3.1 Refer to 6.5.3.1 40All OtherDormitoryHealthcare/hospitalHotel/motelMultifamilyOfficeRestaurantRetailSchoolWarehouseWeighted AverageGrocery StoreHealthcare (hospital)HospitalHotel/motel (< 75 rooms)Hotel/motel (> 75 rooms)MultifamilyOffice (< 5000 ft2)Office (> 50,000 ft2)Office (5000 - 50,000 ft2)OtherRestaurant (full service)Restaurant (quick service)Retail ( strip mall)Retail (Stand alone)School (primary)School (secondary and university)Warehouse (nonrefrigerated)Cooling TypeDirect expansionChilled waterDirect expansionDirect expansionChilled waterNoneCooler Condensing SourceWater/GroundWater/GroundWater/GroundWater/GroundWater/GroundAir/NoneAir/NoneAir/NoneAir/NoneAir/NoneAir/NoneAir/NoneAir/None
A102: Dining: family | B102: Gas Storage Water Heater | J102: =CONCATENATE(K:K,L:L,M:M) -> System TypePackaged terminal air conditionerSingle-zone systemPackaged rooftop air conditionerPackaged rooftop VAV with reheatVAV with reheatWarm air furnace, gas firedBaseline Section 11System 5: Two-pipe fan-coilSystem 1: VAV with PFP boxesSystem 6: Water-source HPSystem 7: Four-pipe fan-coilSystem 2: VAV with reheatSystem 8: PTHPSystem 9: Packaged rooftop HPSystem 3: Packaged VAV with PFP boxesSystem 10: PTACSystem 11: Packaged rooftop ACSystem 4: Packaged VAV with reheatSystem 9: Packaged rooftop HPSystem 11: Packaged rooftop ACFan ControlConstant volumeConstant volumeConstant volumeVAVVAVConstant volumeFan Power s.11Refer to 6.5.3.1 Refer to 6.5.3.1 Refer to 6.5.3.1 Refer to 6.5.3.1 Refer to 6.5.3.1 Refer to 6.5.3.1 Refer to 6.5.3.1 Refer to 6.5.3.1 Refer to 6.5.3.1 Refer to 6.5.3.1 Refer to 6.5.3.1 Refer to 6.5.3.1 Refer to 6.5.3.1 40All OtherDormitoryHealthcare/hospitalHotel/motelMultifamilyOfficeRestaurantRetailSchoolWarehouseWeighted AverageGrocery StoreHealthcare (hospital)HospitalHotel/motel (< 75 rooms)Hotel/motel (> 75 rooms)MultifamilyOffice (< 5000 ft2)Office (> 50,000 ft2)Office (5000 - 50,000 ft2)OtherRestaurant (full service)Restaurant (quick service)Retail ( strip mall)Retail (Stand alone)School (primary)School (secondary and university)Warehouse (nonrefrigerated)Cooling TypeDirect expansionChilled waterDirect expansionDirect expansionChilled waterNoneCooler Condensing SourceWater/GroundWater/GroundWater/GroundWater/GroundWater/GroundAir/NoneAir/NoneAir/NoneAir/NoneAir/NoneAir/NoneAir/NoneAir/None
A103: Dormitory | B103: Gas Storage Water Heater | J103: =CONCATENATE(K:K,L:L,M:M) -> System TypePackaged terminal air conditionerSingle-zone systemPackaged rooftop air conditionerPackaged rooftop VAV with reheatVAV with reheatWarm air furnace, gas firedBaseline Section 11System 5: Two-pipe fan-coilSystem 1: VAV with PFP boxesSystem 6: Water-source HPSystem 7: Four-pipe fan-coilSystem 2: VAV with reheatSystem 8: PTHPSystem 9: Packaged rooftop HPSystem 3: Packaged VAV with PFP boxesSystem 10: PTACSystem 11: Packaged rooftop ACSystem 4: Packaged VAV with reheatSystem 9: Packaged rooftop HPSystem 11: Packaged rooftop ACFan ControlConstant volumeConstant volumeConstant volumeVAVVAVConstant volumeFan Power s.11Refer to 6.5.3.1 Refer to 6.5.3.1 Refer to 6.5.3.1 Refer to 6.5.3.1 Refer to 6.5.3.1 Refer to 6.5.3.1 Refer to 6.5.3.1 Refer to 6.5.3.1 Refer to 6.5.3.1 Refer to 6.5.3.1 Refer to 6.5.3.1 Refer to 6.5.3.1 Refer to 6.5.3.1 40All OtherDormitoryHealthcare/hospitalHotel/motelMultifamilyOfficeRestaurantRetailSchoolWarehouseWeighted AverageGrocery StoreHealthcare (hospital)HospitalHotel/motel (< 75 rooms)Hotel/motel (> 75 rooms)MultifamilyOffice (< 5000 ft2)Office (> 50,000 ft2)Office (5000 - 50,000 ft2)OtherRestaurant (full service)Restaurant (quick service)Retail ( strip mall)Retail (Stand alone)School (primary)School (secondary and university)Warehouse (nonrefrigerated)Cooling TypeDirect expansionChilled waterDirect expansionDirect expansionChilled waterNoneCooler Condensing SourceWater/GroundWater/GroundWater/GroundWater/GroundWater/GroundAir/NoneAir/NoneAir/NoneAir/NoneAir/NoneAir/NoneAir/NoneAir/None
...

Sheet 6j. HVAC Water-side CHW  
B2: 6j | C2: Water-Side HVAC - Chilled Water
B3: Model Input Parameter | C3: HVAC System / Group (BASELINE DESIGN) | E3: HVAC System / Group (PROPOSED DESIGN)
C4: Description | D4: Units | E4: Description | F4: Units | G4: Supporting Doc. Location | H4: Model Output Report
B5: System Designation(s)
B6: # and Type of Chillers (and capacity of chiller if more than 1 type or size)
B7: Total Chiller Capacity
B8: Chiller Efficiency - Full Load
B9: Chiller Efficiency - Part Load
B10: Chilled Water (CHW) Supply Temp | D10: °F | F10: °F
B11: CHW ΔT | D11: °F | F11: °F
B12: CHW Supply Temp Reset Parameters
B13: CHW Loop Configuration
B14: Number of Primary CHW Pumps | D14: # | F14: #
B15: Primary CHW Pump Power
B16: Primary CHW Pump Flow | D16: gpm | F16: gpm
B17: Primary CHW Pump Control
B18: Number of Secondary CHW Pumps | D18: # | F18: #
B19: Secondary CHW Pump Power
B20: Secondary CHW Pump Flow | D20: gpm | F20: gpm
B21: Secondary CHW Pump Control
B22: Water-Side Economizer
B23: Water-Side Energy Recovery
B24: Other (describe)
B25: Other (describe)
B26: Other (describe)
B27: Other (describe)

Sheet 6k. HVAC Water-side CW&CT
B2: 6k | C2: Water-Side HVAC - Cooling Tower and Condenser Water
B3: Model Input Parameter | C3: HVAC System / Group (BASELINE DESIGN) | E3: HVAC System / Group (PROPOSED DESIGN)
C4: Description | D4: Units | E4: Description | F4: Units | G4: Supporting Doc. Location | H4: Model Output Report
B5: System Designation(s)
B6: Number of Cooling Towers/Fluid Coolers
B7: Cooling Tower Fan Power
B8: Cooling Tower Fan Control
B9: Condenser Water (CW) Leaving Temp | D9: °F | F9: °F
B10: CW ΔT | D10: °F | F10: °F
B11: CW Loop Temp Reset Parameters
B12: Number of CW Pumps | D12: # | F12: #
B13: CW Pump Power
B14: CW Pump Flow | D14: gpm | F14: gpm
B15: CW Pump Control
B16: Performance | D16: gpm/hp | F16: gpm/hp
B17: Other (describe)
B18: Other (describe)
B19: Other (describe)
B20: Other (describe)

Sheet 6l. HVAC Water-side HW&Steam
B1: 6l
B2: Water-Side HVAC: Hot Water or Steam
B3: Model Input Parameter | C3: HVAC System / Group (BASELINE DESIGN) | E3: HVAC System / Group (PROPOSED DESIGN)
C4: Description | D4: Units | E4: Description | F4: Units | G4: Supporting Doc. Location | H4: Model Output Report
B5: System Designation(s)
B6: Number and Type of Boilers
B7: Total Boiler Capacity
B8: Boiler Efficiency
B9: Hot Water or Steam (HHW) Supply Temp | D9: °F | F9: °F
B10: HHW ΔT | D10: °F | F10: °F
B11: HHW Temp Reset Parameters
B12: HHW Loop Configuration
B13: Number of Primary HHW Pumps | D13: # | F13: #
B14: Primary HHW Pump Power
B15: Primary HHW Pump Flow | D15: gpm | F15: gpm
B16: Primary HHW Pump Control
B17: Number of Secondary HHW Pumps | D17: # | F17: #
B18: Secondary HHW Pump Power
B19: Secondary HHW Pump Flow | D19: gpm | F19: gpm
B20: Secondary HHW Pump Control
B21: Other (describe)
B22: Other (describe)
B23: Other (describe)
B24: Other (describe)

Sheet 6m. HVAC- Geothermal
B1: 6m
B2: Geothermal Systems
B3: Model Input Parameter | C3: HVAC System / Group (BASELINE DESIGN) | E3: HVAC System / Group (PROPOSED DESIGN)
C4: Description | D4: Units | E4: Description | F4: Units | G4: Supporting Doc. Location | H4: Model Output Report
B5: System Designation(s)
B6: Type of Geothermal system | C6: NA
B7: Soil Conductivity (if applicable) | C7: NA
B8: Geothermal source design temperature - summer | C8: NA | F8: °F
B9: Geothermal source design temperature - winter | C9: NA | F9: °F
B10: Geoexchange loop design fluid supply temperature - cooling | C10: NA | F10: °F
B11: Geoexchange loop design fluid supply temperature -heating | C11: NA | F11: °F
B12: Geoexchange loop - operating temperature | C12: NA
B13: Geothermal energy transfer effect | C13: NA
B14: Geothermal Loop Pumping Configuration | C14: NA
B15: Number of Geothermal Loop Pumps | C15: NA | F15: #
B16: Geothermal Loop Pump Control | C16: NA
B17: Geothermal Pump Power | C17: NA | F17: W/gpm
B18: Geothermal Loop Flow | C18: NA | F18: gpm
B19: Geothermal Air-side Efficiency curves | C19: NA
B20: Other (describe) | C20: NA
B21: Other (describe) | C21: NA
B22: Other (describe) | C22: NA
B23: Other (describe) | C23: NA

Sheet 6n. CHP
B2: 6n | C2: Combined Heat & Power Systems
B3: Model Input Parameter | C3: HVAC System / Group (BASELINE DESIGN) | E3: HVAC System / Group (PROPOSED DESIGN)
C4: Description | D4: Units | E4: Description | F4: Units | G4: Supporting Doc. Location | H4: Model Output Report
B5: CHP: Type of generator | C5: NA
B6: Quantity of CHP generators | C6: NA
B7: Total capacity of CHP generators (kW) at design conditions | C7: NA | F7: kW
B8: CHP: Thermal efficiency (%) at design conditions | C8: NA | F8: %
B9: CHP: Electrical efficiency (%) at design conditions | C9: NA | F9: %
B10: CHP: Controls / Schedule | C10: NA
B11: CHP: Fuel Source | C11: NA
B12: CHP: Where is the recovered heat used? (e.g. gas absorption chillers, hot water distribution loop, etc.) | C12: NA
B13: CHP: Backup heat source when waste heat from CHP is unavailable? (e.g. fossil fuel boilers) | C13: NA
B14: CHP: Parasitic losses (e.g. air handling unit to cool the intake air) | C14: NA
B15: Other (describe) | C15: NA
B16: Other (describe) | C16: NA
B17: Other (describe) | C17: NA
B18: Other (describe) | C18: NA

Sheet Lists-Areas
A2: BPF weighted avg | B2: Envelope Backstop weighted avg | C2: WWR weighted avg
A3: All Other | B3: All other | C3: Grocery Store
A4: All Other | B4: All other | C4: All Other | G4: Group A | H4: Assembly
A5: All Other | B5: Dormitory | C5: All Other | G5: Group B | H5: office
A6: Healthcare/ hospital | B6: All other | C6: Healthcare (hospital) | G6: Group E & I-4 | H6: Education
A7: Healthcare/ hospital | B7: All other | C7: Hospital | G7: Group I-4
A8: Hotel/motel | B8: Hotel/motel | C8: Hotel/motel (< 75 rooms) | G8: Group I-1
A9: Hotel/motel | B9: Hotel/motel | C9: Hotel/motel (> 75 rooms) | G9: Group F
A10: Multifamily | B10: Multifamily | C10: Multifamily | G10: Group B, H, I-2 and I-3
A11: Office | B11: All other | C11: Office (< 5000 ft2) | G11: Group H
A12: Office | B12: All other | C12: Office (> 50,000 ft2) | G12: Group I-2
A13: Office | B13: All other | C13: Office (5000 - 50,000 ft2) | G13: Group I-3
A14: Restaurant | B14: All other | C14: Restaurant (full service) | G14: Group M
A15: Restaurant | B15: All other | C15: Restaurant (quick service) | G15: Group R-1
A16: Retail | B16: All other | C16: Retail ( strip mall) | G16: Group R-2
A17: Retail | B17: All other | C17: Retail (Stand alone) | G17: Group S and U
A18: School | B18: All other | C18: School (primary)
A19: School | B19: All other | C19: School (secondary and university)
A20: Warehouse | B20: All other | C20: Warehouse (nonrefrigerated)
C31: Other

Sheet Lighting Lookup
A1: Building Area Method Categories | B1: Table 9.5.1 LPD (W/sf) | C1: Table G | E1: Space by Space Categories | F1: Table 9.6.1 LPD (W/sf) | I1: Additional Controls
A2: Automotive facility | B2: 0.64 | C2: 0.9 | E2: Atrium - first 40ft in height | F2: 0.03 | G2: 0.0375 | I2: None
A3: Convention center | B3: 0.7 | C3: 1.2 | E3: Atrium - height above 40ft | F3: 0.03 | G3: 0.0375 | I3: Decorative
A4: Courthouse | B4: 0.74 | C4: 1.2 | E4: Audience/seating area - all other | F4: 0.43 | G4: 0.9 | I4: Retail Display
A5: Dining: bar lounge/leisure | B5: 0.69 | C5: 1.3 | E5: Audience/seating area - auditorium | F5: 0.63 | G5: 0.9 | I5: Room Cavity Ratio
A6: Dining: cafeteria/fast food | B6: 0.66 | C6: 1.4 | E6: Audience/seating area - convention center | F6: 0.65 | G6: 0.7 | I6: Control Allowance
A7: Dining: family | B7: 0.61 | C7: 1.6 | E7: Audience/seating area - exercise center | F7: 0.43 | G7: 0.3
A8: Dormitory | B8: 0.52 | C8: 1 | E8: Audience/seating area - gymnasium | F8: 0.43 | G8: 0.4
A9: Exercise center | B9: 0.65 | C9: 1 | E9: Audience/seating area - motion picture theater | F9: 0.64 | G9: 1.2
A10: Fire station | B10: 0.5 | C10: 1 | E10: Audience/seating area - penitentiary | F10: 0.28 | G10: 0.7
A11: Gymnasium | B11: 0.67 | C11: 1.1 | E11: Audience/seating area - performing arts theater | F11: 2.03 | G11: 2.6
A12: Health-care clinic | B12: 0.68 | C12: 1 | E12: Audience/seating area - religious facility | F12: 1.53 | G12: 1.7
A13: Hospital | B13: 0.86 | C13: 1.2 | E13: Audience/seating area - sports arena | F13: 0.42 | G13: 0.4
A14: Hotel/Motel | B14: 0.7 | C14: 1.09 | E14: Audience/seating area - transportation facility | F14: 0.4 | G14: 0.5
A15: Library | B15: 0.78 | C15: 1.3 | E15: Automotive | F15: 0.53 | G15: 0.7
A16: Manufacturing facility | B16: 0.6 | C16: 1.17 | E16: Banking Activity Area | F16: 0.79 | G16: 1.5
A17: Motion picture theater | B17: 0.62 | C17: 1.2 | E17: Classroom/lecture/training - all other | F17: 0.74 | G17: 1.4
A18: Multifamily | B18: 0.49 | C18: 0.7 | E18: Classroom/lecture/training - penitentiary | F18: 1.06 | G18: 1.3
... A33: Workshop | B33: 0.83 | C33: 1.4 | E33: Dining Area - Family Dining | F33: 0.54 | G33: 2.1
E34: Dining Area - penitentiary | F34: 0.72 | G34: 1.3
E35: Dormitory - living quarters | F35: 0.46 | G35: 1.11
E36: Electrical/Mechanical | F36: 0.39 | G36: 1.5
E37: Emergency Vehicle Garage | F37: 0.41 | G37: 0.8
E38: Facility for Visually Impaired - in a chapel | F38: 0.89 | G38: 2.77
E39: Facility for Visually Impaired - in a rec room/common living rm | F39: 1.53 | G39: 3.02
E40: Fire station - sleeping quarters | F40: 0.19 | G40: 0.3
E41: Food Preparation Area | F41: 0.92 | G41: 1.2
E42: Guest Room | F42: 0.75 | G42: 1.14
E43: Gymnasium/Exercise Center-Playing Area | F43: 0.75 | G43: 1.4
E44: Gymnasium/Fitness Center - exercise area | F44: 0.5 | G44: 0.9
E45: Healthcare facility - exam treatment room | F45: 1.16 | G45: 1.5
... E80: Parking Area, Interior | F80: 0.11 | G80: 0.2
E81: Performing Arts Theater - dressing room | F81: 0.35
E82: Pharmacy Area | F82: 1.23 | G82: 1.2
E83: Post Office-Sorting Area | F83: 0.66 | G83: 1.2
E84: Religious Buildings-Fellowship Hall | F84: 0.54 | G84: 0.9
E85: Religious Buildings-Worship Pulpit, Choir | F85: 0.98 | G85: 2.4
E86: Restroom - all other | F86: 0.75 | G86: 0.9
E87: Restroom - visually impaired | F87: 0.81 | G87: 1.52
E88: Retail-Dressing/Fitting Room | F88: 0.49 | G88: 0.89
E89: Retail-Mall Concourse | F89: 0.79 | G89: 1.7
E90: Sales Area | F90: 1.06 | G90: 1.7
E91: Seating Area, General | F91: 0.38 | G91: 0.68
E92: Sports Arena-Court Sports Area-Class 1 | F92: 2.26 | G92: 4.61
E93: Sports Arena-Court Sports Area-Class 2 | F93: 1.45 | G93: 3.01
... E108: Workshop | F108: 1.09 | G108: 1.9

Sheet Lighting Zones
B1: Lighting Zone | C1: Description | D1: Base Site Allowance (watts)
A2: 1 | B2: 0 | C2: Undeveloped areas within national and state parks, forest land and rural areas and other undeveloped areas as approved by the AHJ | D2: 0
A3: 2 | B3: 1 | C3: Park Land | D3: 350
A4: 3 | B4: 2 | C4: R districts, R districts with C overlays and MX districts | D4: 400
A5: 4 | B5: 3 | C5: M districts, except MX; C districts, except C5, C6 and C overlays on R | D5: 500
A6: 5 | B6: 4 | C6: C5 and C6 districts | D6: 900
B11: YES
B12: NO

Sheet Raw Data
D1: Area Allowance (watts/sq.ft) | I1: Linear Allowance (watts/linear foot) | S1: Area Allowance (watts/sq.ft) | X1: Linear Allowance (watts/linear foot)
A2: Surface | B2: Surface Type | C2: Type | D2: LZ0 | E2: LZ1 | F2: LZ2 | G2: LZ3 | H2: LZ4 | I2: LZ0 | J2: LZ1 | K2: LZ2 | L2: LZ3 | M2: LZ4 | N2: Base Allowance | O2: Unit Allowance | Q2: Surface2 | R2: Surface Type | S2: LZ0 | T2: LZ1 | U2: LZ2 | V2: LZ3 | W2: LZ4 | X2: LZ0 | Y2: LZ1 | Z2: LZ2 | AA2: LZ3 | AB2: LZ4 | AC2: Base Allowance | AD2: Unit Allowance
A3: ATM or Night Depository | B3: Nontradable | C3: 1 | N3: =AC19 -> 135 | O3: =AD19 -> 45 | Q3: Uncovered parking areas and drives | R3: Tradable | S3: 0 | T3: 0.03 | U3: 0.04 | V3: 0.05 | W3: 0.05
A4: Building façade | B4: Nontradable | D4: =S18 -> 0 | E4: 0 | F4: 0.1 | G4: 0.15 | H4: 0.2 | I4: =X18 -> 0 | J4: =Y18 -> 0 | K4: =Z18 -> 2.5 | L4: =AA18 -> 3.75 | M4: =AB18 -> 5 | Q4: Walkways less than 10' wide | R4: Tradable | X4: 0 | Y4: 0.5 | Z4: 0.5 | AA4: 0.6 | AB4: 0.7
A5: Drive-thrus | B5: Nontradable | O5: =AD22 -> 200 | Q5: Walkways >= 10' wide | R5: Tradable | S5: 0 | T5: 0.1 | U5: 0.1 | V5: 0.11 | W5: 0.14
A6: Entrances and gatehouse inspection at guarded facilities (uncovered) | B6: Nontradable | D6: =S20 -> 0 | E6: =T20 -> 0.5 | F6: =U20 -> 0.5 | G6: =V20 -> 0.5 | H6: =W20 -> 0.5 | Q6: Plaza areas | R6: Tradable | S6: 0 | T6: 0.1 | U6: 0.1 | V6: 0.11 | W6: 0.14
A7: Entry canopies | B7: Tradable | D7: =S13 -> 0 | E7: =T13 -> 0.2 | F7: =U13 -> 0.25 | G7: =V13 -> 0.4 | H7: =W13 -> 0.4 | Q7: Special feature areas | R7: Tradable | S7: 0 | T7: 0.1 | U7: 0.1 | V7: 0.11 | W7: 0.14
A8: Landscaping | B8: Tradable | D8: =S11 -> 0 | E8: =T11 -> 0.03 | F8: =U11 -> 0.04 | G8: =V11 -> 0.04 | H8: =W11 -> 0.04 | Q8: Dining areas | R8: Tradable | S8: 0 | T8: 0.65 | U8: 0.65 | V8: 0.75 | W8: 0.95
A9: Loading area for emergency service vehicles (uncovered) | B9: Nontradable | D9: =S21 -> 0 | E9: =T21 -> 0.35 | F9: =U21 -> 0.35 | G9: =V21 -> 0.35 | H9: =W21 -> 0.35 | Q9: Stairways | R9: Tradable | S9: 0 | T9: 0.6 | U9: 0.7 | V9: 0.7 | W9: 0.7
A10: Loading docks | B10: Tradable | D10: =S14 -> 0 | E10: =T14 -> 0.35 | F10: =U14 -> 0.35 | G10: =V14 -> 0.35 | H10: =W14 -> 0.35 | Q10: Pedestrian tunnels | R10: Tradable | S10: 0 | T10: 0.12 | U10: 0.12 | V10: 0.14 | W10: 0.21
A11: Other entrances/exits | B11: Tradable | I11: =#REF! -> #REF! | J11: =#REF! -> #REF! | K11: =#REF! -> #REF! | L11: =#REF! -> #REF! | M11: =#REF! -> #REF! | Q11: Landscaping | R11: Tradable | S11: 0 | T11: 0.03 | U11: 0.04 | V11: 0.04 | W11: 0.04
A12: Outdoor sales area | B12: Tradable | D12: =S16 -> 0 | E12: =T16 -> 0.2 | F12: =U16 -> 0.2 | G12: =V16 -> 0.35 | H12: =W16 -> 0.5 | Q12: Pedestrian and vehicular entrances and exits | R12: Tradable | X12: 0 | Y12: 12.6 | Z12: 12.6 | AA12: 20 | AB12: 20
A13: Parking near 24-hour retail entrances (main only) | B13: Nontradable | O13: =AD23 -> 400 | Q13: Entry canopies | R13: Tradable | S13: 0 | T13: 0.2 | U13: 0.25 | V13: 0.4 | W13: 0.4
A14: Pedestrian tunnels | B14: Tradable | D14: =S10 -> 0 | E14: =T10 -> 0.12 | F14: =U10 -> 0.12 | G14: =V10 -> 0.14 | H14: =W10 -> 0.21 | Q14: Loading docks | R14: Tradable | S14: 0 | T14: 0.35 | U14: 0.35 | V14: 0.35 | W14: 0.35
A15: Plaza areas | B15: Tradable | D15: =S6 -> 0 | E15: =T6 -> 0.1 | F15: =U6 -> 0.1 | G15: =V6 -> 0.11 | H15: =W6 -> 0.14 | Q15: Sales canopy | R15: Tradable | S15: 0 | T15: 0.4 | U15: 0.4 | V15: 0.6 | W15: 0.7
A16: Primary building entrances | B16: Tradable | I16: =X12 -> 0 | J16: =Y12 -> 12.6 | K16: =Z12 -> 12.6 | L16: =AA12 -> 20 | M16: =AB12 -> 20 | Q16: Outdoor sales area | R16: Tradable | S16: 0 | T16: 0.2 | U16: 0.2 | V16: 0.35 | W16: 0.5
A17: Roadway/parking, entry, trailhead, toilet facility | B17: Nontradable | O17: =AD24 -> 0 | Q17: Street frontage for vehicle sales | R17: Tradable | X17: 0 | Y17: 0 | Z17: 7 | AA17: 7 | AB17: 21
A18: Sales canopy | B18: Tradable | D18: =S15 -> 0 | E18: =T15 -> 0.4 | F18: =U15 -> 0.4 | G18: =V15 -> 0.6 | H18: =W15 -> 0.7 | Q18: Building façade | R18: Nontradable | S18: 0 | T18: 0 | U18: 0.1 | V18: 0.15 | W18: 0.2 | X18: 0 | Y18: 0 | Z18: 2.5 | AA18: 3.75 | AB18: 5
A19: Special feature areas | B19: Tradable | D19: =S7 -> 0 | E19: =T7 -> 0.1 | F19: =U7 -> 0.1 | G19: =V7 -> 0.11 | H19: =W7 -> 0.14 | Q19: ATM or Night Depository | R19: Nontradable | AC19: 135 | AD19: 45
A20: Stairways | B20: Tradable | D20: =S9 -> 0 | E20: =T9 -> 0.6 | F20: =U9 -> 0.7 | G20: =V9 -> 0.7 | H20: =W9 -> 0.7 | Q20: Entrances and gatehouse inspection at guarded facilities (uncovered) | R20: Nontradable | S20: 0 | T20: 0.5 | U20: 0.5 | V20: 0.5 | W20: 0.5
A21: Street frontage for vehicle sales | B21: Tradable | I21: =X17 -> 0 | J21: =Y17 -> 0 | K21: =Z17 -> 7 | L21: =AA17 -> 7 | M21: =AB17 -> 21 | Q21: Loading area for emergency service vehicles (uncovered) | R21: Nontradable | S21: 0 | T21: 0.35 | U21: 0.35 | V21: 0.35 | W21: 0.35
A22: Uncovered parking areas and drive | B22: Tradable | D22: =S3 -> 0 | E22: =T3 -> 0.03 | F22: =U3 -> 0.04 | G22: =V3 -> 0.05 | H22: =W3 -> 0.05 | Q22: Drive-thrus | R22: Nontradable | AD22: 200
A23: Walkways >= 10' wide | B23: Tradable | D23: =S5 -> 0 | E23: =T5 -> 0.1 | F23: =U5 -> 0.1 | G23: =V5 -> 0.11 | H23: =W5 -> 0.14 | Q23: Parking near 24-hour retail entrances (main only) | R23: Nontradable | AD23: 400
A24: Walkways less than 10' wide | B24: Tradable | I24: =X4 -> 0 | J24: =Y4 -> 0.5 | K24: =Z4 -> 0.5 | L24: =AA4 -> 0.6 | M24: =AB4 -> 0.7 | Q24: Roadway/parking, entry, trailhead, toilet facility | R24: Nontradable | AD24: 0
